Workbook

Sheet 00_README
A1: API, Condições Socioeconômicas e Proficiência em Inglês
A2: Objetivo
A3: Esta planilha analisa a associação entre desempenho acadêmico de escolas da Califórnia e duas características contextuais dos estudantes: elegibilidade para refeição subsidiada e não proficiência em inglês.
A4: Pergunta de pesquisa
A5: Entre escolas fundamentais da Califórnia, como condições socioeducacionais dos alunos se associam ao desempenho acadêmico medido pelo API em 2000?
A6: Dados
A7: Fonte dos dados: dataset/api.csv.
A8: Fonte do dicionário e contexto: dataset/api_doc.txt.
A9: Unidade de análise: escola.
A10: Variável resposta: API00, índice de desempenho acadêmico em 2000.
A11: Preditor principal: REFS, percentual de alunos elegíveis para refeição subsidiada.
A12: Preditor complementar: NPI, percentual de alunos não proficientes em inglês.
... A42: REFS e NPI são positivamente correlacionadas; por isso, os coeficientes do modelo múltiplo exigem cautela.

Sheet 01_DADOS_BRUTOS
A1: ID | B1: TIPO | C1: NOME | D1: API00 | E1: API99 | F1: META | G1: EDU | H1: TEST_INSC | I1: TEST_NUM | J1: REFS | K1: NPI
A2: 1611190130229 | B2: Superior | C2: Alameda High | D2: 731 | E2: 693 | F2: 5 | G2: 3.45 | H2: 1278 | I2: 1090 | J2: 14 | K2: 16
A3: 1611190132878 | B3: Superior | C3: Encinal High | D3: 622 | E3: 589 | F3: 11 | G3: 3.0599999 | H3: 1113 | I3: 840 | J3: 20 | K3: 18
A4: 1611196000004 | B4: Medio | C4: Chipman Middle | D4: 622 | E4: 572 | F4: 11 | G4: 2.8199999 | H4: 546 | I4: 472 | J4: 55 | K4: 25
A5: 1611196090005 | B5: Fundamental | C5: Lum (Donald D.) | D5: 774 | E5: 732 | F5: 3 | G5: 3.3199999 | H5: 330 | I5: 272 | J5: 35 | K5: 26
A6: 1611196090013 | B6: Fundamental | C6: Edison Elementa | D6: 811 | E6: 784 | F6: 1 | G6: 3.76 | H6: 233 | I6: 216 | J6: 15 | K6: 9
A7: 1611196090021 | B7: Fundamental | C7: Otis (Frank) El | D7: 780 | E7: 725 | F7: 4 | G7: 3.4400001 | H7: 276 | I7: 247 | J7: 25 | K7: 18
A8: 1611196090039 | B8: Fundamental | C8: Franklin Elemen | D8: 808 | E8: 765 | F8: 2 | G8: 3.23 | H8: 180 | I8: 167 | J8: 22 | K8: 9
A9: 1611196090047 | B9: Fundamental | C9: Haight Elementa | D9: 739 | E9: 667 | F9: 7 | G9: 2.75 | H9: 363 | I9: 292 | J9: 50 | K9: 35
A10: 1611196090054 | B10: Medio | C10: Lincoln Middle | D10: 795 | E10: 792 | F10: 1 | G10: 3.74 | H10: 850 | I10: 782 | J10: 10 | K10: 10
A11: 1611196090062 | B11: Fundamental | C11: Longfellow Elem | D11: 650 | E11: 580 | F11: 11 | G11: 2.6600001 | H11: 263 | I11: 219 | J11: 71 | K11: 41
A12: 1611196090104 | B12: Fundamental | C12: Washington Elem | D12: 668 | E12: 621 | F12: 9 | G12: 2.9200001 | H12: 369 | I12: 330 | J12: 48 | K12: 21
A13: 1611196090112 | B13: Medio | C13: Wood (Will C.) | D13: 701 | E13: 651 | F13: 7 | G13: 3.3299999 | H13: 792 | I13: 646 | J13: 32 | K13: 22
... A5424: 58727516056824 | B5424: Fundamental | C5424: Far West Elemen | D5424: 763 | E5424: 764 | F5424: 2 | G5424: 2.55 | H5424: 360 | I5424: 247 | J5424: 45 | K5424: 0

Sheet 02_DICIONARIO
A1: Variável | B1: Descrição | C1: Tipo | D1: Uso
A2: TIPO | B2: Nível de ensino da escola | C2: Categórica | D2: Recorte analítico
A3: API00 | B3: Índice de desempenho acadêmico em 2000 | C3: Quantitativa | D3: Variável resposta
A4: REFS | B4: Percentual de alunos elegíveis para refeição subsidiada | C4: Quantitativa | D4: Proxy socioeconômica
A5: NPI | B5: Percentual de alunos não proficientes em inglês | C5: Quantitativa | D5: Variável contextual
A7: Conteúdo de dataset/api_doc.txt
A8: Performance estudantil em escolas da California
A10: Descrição
A11: O API é um índice numérico na escala de 200 a 1.000 que indica o desempenho estudantil de uma escola ou distrito em testes anuais. O API é calculado para toda a escola, incluindo alunos desfavorecidos socioeconômicos, alunos com deficiência físico-motora e não proficientes em inglês [1].
A13: As pontuações do API para escolas de mesma graduação (ensino fundamental, médio e superior) são classificadas em "decis", com 1 representando os 10% de escolas com desempenho mais baixo e 10 os 10% de desempenho mais alto. As escolas têm dois rankings: (1) um ranking estadual que compara cada escola com todas as outras escolas do mesmo tipo no estado e (2) um ranking de escolas semelhantes que compara cada escola com 100 outras com populações de alunos similares e outras características [1].
A15: O Conselho Estadual de Educação da California* definiu a meta de API estadual em 800 de 1.000. A Lei de responsabilidade das escolas públicas exige que a maioria das escolas melhore seu desempenho a cada ano em 5% da diferença entre sua API e a meta estadual de 800, com uma meta mínima de crescimento de cinco pontos [1].
A17: Formato
A18: Dataframe com 6194 observações (linhas) e 37 variáveis (colunas).
A20: id: Identificação única da escola.
A21: tipo: Nível de ensino da escola (fundamental, medio e superior).
A22: nm: Nome da escola (15 caracteres).
A23: nmc: Nome completo da escola (40 caracteres).
... A65: * Califórnia é um dos 50 estados dos Estados Unidos, localizado na região dos estados do Pacífico. É o estado mais populoso do país, com 39.538.223 habitantes e o terceiro em extensão territorial, superado apenas pelo Alasca e pelo Texas (Wikipedia, 2021).

Sheet 03_DADOS_LIMPOS
A1: ={'01_DADOS_BRUTOS'!A1:K1;FILTER('01_DADOS_BRUTOS'!A2:K5424;'01_DADOS_BRUTOS'!B2:B5424="Fundamental";'01_DADOS_BRUTOS'!D2:D5424<>"";'01_DADOS_BRUTOS'!J2:J5424<>"";'01_DADOS_BRUTOS'!K2:K5424<>"")} | M1: Checkpoint por fórmula
M2: n_escolas_fundamentais | N2: =COUNTA(A2:A3813)
M3: media_API00 | N3: =AVERAGE(D2:D3813)
M4: media_REFS | N4: =AVERAGE(J2:J3813)
M5: media_NPI | N5: =AVERAGE(K2:K3813)

Sheet 04_RESUMO_POR_TIPO
A1: TIPO | B1: n_escolas | C1: percentual_amostra | D1: media_API00 | E1: desvio_API00 | F1: media_REFS | G1: desvio_REFS | H1: media_NPI | I1: desvio_NPI
A2: Fundamental | B2: =COUNTIF('01_DADOS_BRUTOS'!B2:B5424;A2) | C2: =B2/COUNTA('01_DADOS_BRUTOS'!A2:A5424)*100 | D2: =AVERAGEIF('01_DADOS_BRUTOS'!B2:B5424;A2;'01_DADOS_BRUTOS'!D2:D5424) | E2: =STDEV(FILTER('01_DADOS_BRUTOS'!D2:D5424;'01_DADOS_BRUTOS'!B2:B5424=A2)) | F2: =AVERAGEIF('01_DADOS_BRUTOS'!B2:B5424;A2;'01_DADOS_BRUTOS'!J2:J5424) | G2: =STDEV(FILTER('01_DADOS_BRUTOS'!J2:J5424;'01_DADOS_BRUTOS'!B2:B5424=A2)) | H2: =AVERAGEIF('01_DADOS_BRUTOS'!B2:B5424;A2;'01_DADOS_BRUTOS'!K2:K5424) | I2: =STDEV(FILTER('01_DADOS_BRUTOS'!K2:K5424;'01_DADOS_BRUTOS'!B2:B5424=A2))
A3: Medio | B3: =COUNTIF('01_DADOS_BRUTOS'!B2:B5424;A3) | C3: =B3/COUNTA('01_DADOS_BRUTOS'!A2:A5424)*100 | D3: =AVERAGEIF('01_DADOS_BRUTOS'!B2:B5424;A3;'01_DADOS_BRUTOS'!D2:D5424) | E3: =STDEV(FILTER('01_DADOS_BRUTOS'!D2:D5424;'01_DADOS_BRUTOS'!B2:B5424=A3)) | F3: =AVERAGEIF('01_DADOS_BRUTOS'!B2:B5424;A3;'01_DADOS_BRUTOS'!J2:J5424) | G3: =STDEV(FILTER('01_DADOS_BRUTOS'!J2:J5424;'01_DADOS_BRUTOS'!B2:B5424=A3)) | H3: =AVERAGEIF('01_DADOS_BRUTOS'!B2:B5424;A3;'01_DADOS_BRUTOS'!K2:K5424) | I3: =STDEV(FILTER('01_DADOS_BRUTOS'!K2:K5424;'01_DADOS_BRUTOS'!B2:B5424=A3))
A4: Superior | B4: =COUNTIF('01_DADOS_BRUTOS'!B2:B5424;A4) | C4: =B4/COUNTA('01_DADOS_BRUTOS'!A2:A5424)*100 | D4: =AVERAGEIF('01_DADOS_BRUTOS'!B2:B5424;A4;'01_DADOS_BRUTOS'!D2:D5424) | E4: =STDEV(FILTER('01_DADOS_BRUTOS'!D2:D5424;'01_DADOS_BRUTOS'!B2:B5424=A4)) | F4: =AVERAGEIF('01_DADOS_BRUTOS'!B2:B5424;A4;'01_DADOS_BRUTOS'!J2:J5424) | G4: =STDEV(FILTER('01_DADOS_BRUTOS'!J2:J5424;'01_DADOS_BRUTOS'!B2:B5424=A4)) | H4: =AVERAGEIF('01_DADOS_BRUTOS'!B2:B5424;A4;'01_DADOS_BRUTOS'!K2:K5424) | I4: =STDEV(FILTER('01_DADOS_BRUTOS'!K2:K5424;'01_DADOS_BRUTOS'!B2:B5424=A4))
A7: Interpretação
A8: A tabela justifica o recorte para TIPO = Fundamental, pois os tipos de escola têm composição e médias distintas.

Sheet 05_DESCRITIVAS_E_CORRELACOES
A1: estatistica | B1: API00 | C1: REFS | D1: NPI
A2: contagem | B2: =COUNTA(FILTER('03_DADOS_LIMPOS'!D2:D;ISNUMBER('03_DADOS_LIMPOS'!D2:D))) | C2: =COUNTA(FILTER('03_DADOS_LIMPOS'!J2:J;ISNUMBER('03_DADOS_LIMPOS'!D2:D))) | D2: =COUNTA(FILTER('03_DADOS_LIMPOS'!K2:K;ISNUMBER('03_DADOS_LIMPOS'!D2:D)))
A3: media | B3: =AVERAGE(FILTER('03_DADOS_LIMPOS'!D2:D;ISNUMBER('03_DADOS_LIMPOS'!D2:D))) | C3: =AVERAGE(FILTER('03_DADOS_LIMPOS'!J2:J;ISNUMBER('03_DADOS_LIMPOS'!D2:D))) | D3: =AVERAGE(FILTER('03_DADOS_LIMPOS'!K2:K;ISNUMBER('03_DADOS_LIMPOS'!D2:D)))
A4: desvio_padrao | B4: =STDEV(FILTER('03_DADOS_LIMPOS'!D2:D;ISNUMBER('03_DADOS_LIMPOS'!D2:D))) | C4: =STDEV(FILTER('03_DADOS_LIMPOS'!J2:J;ISNUMBER('03_DADOS_LIMPOS'!D2:D))) | D4: =STDEV(FILTER('03_DADOS_LIMPOS'!K2:K;ISNUMBER('03_DADOS_LIMPOS'!D2:D)))
A5: minimo | B5: =MIN(FILTER('03_DADOS_LIMPOS'!D2:D;ISNUMBER('03_DADOS_LIMPOS'!D2:D))) | C5: =MIN(FILTER('03_DADOS_LIMPOS'!J2:J;ISNUMBER('03_DADOS_LIMPOS'!D2:D))) | D5: =MIN(FILTER('03_DADOS_LIMPOS'!K2:K;ISNUMBER('03_DADOS_LIMPOS'!D2:D)))
A6: Q1 | B6: =QUARTILE(FILTER('03_DADOS_LIMPOS'!D2:D;ISNUMBER('03_DADOS_LIMPOS'!D2:D));1) | C6: =QUARTILE(FILTER('03_DADOS_LIMPOS'!J2:J;ISNUMBER('03_DADOS_LIMPOS'!D2:D));1) | D6: =QUARTILE(FILTER('03_DADOS_LIMPOS'!K2:K;ISNUMBER('03_DADOS_LIMPOS'!D2:D));1)
A7: mediana | B7: =MEDIAN(FILTER('03_DADOS_LIMPOS'!D2:D;ISNUMBER('03_DADOS_LIMPOS'!D2:D))) | C7: =MEDIAN(FILTER('03_DADOS_LIMPOS'!J2:J;ISNUMBER('03_DADOS_LIMPOS'!D2:D))) | D7: =MEDIAN(FILTER('03_DADOS_LIMPOS'!K2:K;ISNUMBER('03_DADOS_LIMPOS'!D2:D)))
A8: Q3 | B8: =QUARTILE(FILTER('03_DADOS_LIMPOS'!D2:D;ISNUMBER('03_DADOS_LIMPOS'!D2:D));3) | C8: =QUARTILE(FILTER('03_DADOS_LIMPOS'!J2:J;ISNUMBER('03_DADOS_LIMPOS'!D2:D));3) | D8: =QUARTILE(FILTER('03_DADOS_LIMPOS'!K2:K;ISNUMBER('03_DADOS_LIMPOS'!D2:D));3)
A9: maximo | B9: =MAX(FILTER('03_DADOS_LIMPOS'!D2:D;ISNUMBER('03_DADOS_LIMPOS'!D2:D))) | C9: =MAX(FILTER('03_DADOS_LIMPOS'!J2:J;ISNUMBER('03_DADOS_LIMPOS'!D2:D))) | D9: =MAX(FILTER('03_DADOS_LIMPOS'!K2:K;ISNUMBER('03_DADOS_LIMPOS'!D2:D)))
A11: Matriz de correlação | B11: API00 | C11: REFS | D11: NPI
A12: API00 | B12: =CORREL(FILTER('03_DADOS_LIMPOS'!D2:D;ISNUMBER('03_DADOS_LIMPOS'!D2:D));FILTER('03_DADOS_LIMPOS'!D2:D;ISNUMBER('03_DADOS_LIMPOS'!D2:D))) | C12: =CORREL(FILTER('03_DADOS_LIMPOS'!D2:D;ISNUMBER('03_DADOS_LIMPOS'!D2:D));FILTER('03_DADOS_LIMPOS'!J2:J;ISNUMBER('03_DADOS_LIMPOS'!D2:D))) | D12: =CORREL(FILTER('03_DADOS_LIMPOS'!D2:D;ISNUMBER('03_DADOS_LIMPOS'!D2:D));FILTER('03_DADOS_LIMPOS'!K2:K;ISNUMBER('03_DADOS_LIMPOS'!D2:D)))
A13: REFS | B13: =CORREL(FILTER('03_DADOS_LIMPOS'!J2:J;ISNUMBER('03_DADOS_LIMPOS'!D2:D));FILTER('03_DADOS_LIMPOS'!D2:D;ISNUMBER('03_DADOS_LIMPOS'!D2:D))) | C13: =CORREL(FILTER('03_DADOS_LIMPOS'!J2:J;ISNUMBER('03_DADOS_LIMPOS'!D2:D));FILTER('03_DADOS_LIMPOS'!J2:J;ISNUMBER('03_DADOS_LIMPOS'!D2:D))) | D13: =CORREL(FILTER('03_DADOS_LIMPOS'!J2:J;ISNUMBER('03_DADOS_LIMPOS'!D2:D));FILTER('03_DADOS_LIMPOS'!K2:K;ISNUMBER('03_DADOS_LIMPOS'!D2:D)))
A14: NPI | B14: =CORREL(FILTER('03_DADOS_LIMPOS'!K2:K;ISNUMBER('03_DADOS_LIMPOS'!D2:D));FILTER('03_DADOS_LIMPOS'!D2:D;ISNUMBER('03_DADOS_LIMPOS'!D2:D))) | C14: =CORREL(FILTER('03_DADOS_LIMPOS'!K2:K;ISNUMBER('03_DADOS_LIMPOS'!D2:D));FILTER('03_DADOS_LIMPOS'!J2:J;ISNUMBER('03_DADOS_LIMPOS'!D2:D))) | D14: =CORREL(FILTER('03_DADOS_LIMPOS'!K2:K;ISNUMBER('03_DADOS_LIMPOS'!D2:D));FILTER('03_DADOS_LIMPOS'!K2:K;ISNUMBER('03_DADOS_LIMPOS'!D2:D)))
A16: Interpretação
A17: REFS e NPI são positivamente correlacionadas; o modelo múltiplo exige cautela por colinearidade.

Sheet 06_MODELO_REFS
A1: Modelo | B1: API00 ~ REFS
A2: n | B2: =COUNTA(FILTER('03_DADOS_LIMPOS'!D2:D;ISNUMBER('03_DADOS_LIMPOS'!D2:D)))
A3: gl | B3: =B2-2
A4: alpha | B4: 0.05
A5: nivel_confianca | B5: =1-B4
A7: Métrica | B7: Fórmula
A8: Intercepto | B8: =INTERCEPT(FILTER('03_DADOS_LIMPOS'!D2:D;ISNUMBER('03_DADOS_LIMPOS'!D2:D));FILTER('03_DADOS_LIMPOS'!J2:J;ISNUMBER('03_DADOS_LIMPOS'!D2:D)))
A9: Coeficiente REFS | B9: =SLOPE(FILTER('03_DADOS_LIMPOS'!D2:D;ISNUMBER('03_DADOS_LIMPOS'!D2:D));FILTER('03_DADOS_LIMPOS'!J2:J;ISNUMBER('03_DADOS_LIMPOS'!D2:D)))
A10: R2 | B10: =RSQ(FILTER('03_DADOS_LIMPOS'!D2:D;ISNUMBER('03_DADOS_LIMPOS'!D2:D));FILTER('03_DADOS_LIMPOS'!J2:J;ISNUMBER('03_DADOS_LIMPOS'!D2:D)))
A11: Erro padrão residual | B11: =STEYX(FILTER('03_DADOS_LIMPOS'!D2:D;ISNUMBER('03_DADOS_LIMPOS'!D2:D));FILTER('03_DADOS_LIMPOS'!J2:J;ISNUMBER('03_DADOS_LIMPOS'!D2:D)))
A13: Parâmetro | B13: Coeficiente | C13: Erro padrão | D13: t | E13: valor-p | F13: IC95 inferior | G13: IC95 superior
A14: Intercepto | B14: =B8 | C14: =INDEX(LINEST(FILTER('03_DADOS_LIMPOS'!D2:D;ISNUMBER('03_DADOS_LIMPOS'!D2:D));FILTER('03_DADOS_LIMPOS'!J2:J;ISNUMBER('03_DADOS_LIMPOS'!D2:D));TRUE;TRUE);2;2) | D14: =B14/C14 | E14: =T.DIST.2T(ABS(D14);$B$3) | F14: =B14-TINV($B$4;$B$3)*C14 | G14: =B14+TINV($B$4;$B$3)*C14
A15: REFS | B15: =B9 | C15: =INDEX(LINEST(FILTER('03_DADOS_LIMPOS'!D2:D;ISNUMBER('03_DADOS_LIMPOS'!D2:D));FILTER('03_DADOS_LIMPOS'!J2:J;ISNUMBER('03_DADOS_LIMPOS'!D2:D));TRUE;TRUE);2;1) | D15: =B15/C15 | E15: =T.DIST.2T(ABS(D15);$B$3) | F15: =B15-TINV($B$4;$B$3)*C15 | G15: =B15+TINV($B$4;$B$3)*C15
A18: Nota sobre alpha
A19: alpha = 0,05 porque o intervalo é de 95%: alpha = 1 - 0,95.
A20: TINV(alpha; gl) retorna o valor crítico t bilateral usado no IC95.
A22: Interpretação
A23: O IC95 de REFS está totalmente abaixo de zero.
A24: O valor-p pequeno indica evidência estatística de associação linear negativa.
A25: ID | B25: NOME | C25: API00 | D25: REFS | E25: API00_ajustado_REFS | F25: residuo_REFS | G25: residuo_padronizado_REFS | H25: abs_residuo_padronizado_REFS
A26: ='03_DADOS_LIMPOS'!A2 | B26: ='03_DADOS_LIMPOS'!C2 | C26: ='03_DADOS_LIMPOS'!D2 | D26: ='03_DADOS_LIMPOS'!J2 | E26: =$B$8+$B$9*D26 | F26: =C26-E26 | G26: =F26/$B$11 | H26: =ABS(G26)
A27: ='03_DADOS_LIMPOS'!A3 | B27: ='03_DADOS_LIMPOS'!C3 | C27: ='03_DADOS_LIMPOS'!D3 | D27: ='03_DADOS_LIMPOS'!J3 | E27: =$B$8+$B$9*D27 | F27: =C27-E27 | G27: =F27/$B$11 | H27: =ABS(G27)
A28: ='03_DADOS_LIMPOS'!A4 | B28: ='03_DADOS_LIMPOS'!C4 | C28: ='03_DADOS_LIMPOS'!D4 | D28: ='03_DADOS_LIMPOS'!J4 | E28: =$B$8+$B$9*D28 | F28: =C28-E28 | G28: =F28/$B$11 | H28: =ABS(G28)
A29: ='03_DADOS_LIMPOS'!A5 | B29: ='03_DADOS_LIMPOS'!C5 | C29: ='03_DADOS_LIMPOS'!D5 | D29: ='03_DADOS_LIMPOS'!J5 | E29: =$B$8+$B$9*D29 | F29: =C29-E29 | G29: =F29/$B$11 | H29: =ABS(G29)
A30: ='03_DADOS_LIMPOS'!A6 | B30: ='03_DADOS_LIMPOS'!C6 | C30: ='03_DADOS_LIMPOS'!D6 | D30: ='03_DADOS_LIMPOS'!J6 | E30: =$B$8+$B$9*D30 | F30: =C30-E30 | G30: =F30/$B$11 | H30: =ABS(G30)
A31: ='03_DADOS_LIMPOS'!A7 | B31: ='03_DADOS_LIMPOS'!C7 | C31: ='03_DADOS_LIMPOS'!D7 | D31: ='03_DADOS_LIMPOS'!J7 | E31: =$B$8+$B$9*D31 | F31: =C31-E31 | G31: =F31/$B$11 | H31: =ABS(G31)
A32: ='03_DADOS_LIMPOS'!A8 | B32: ='03_DADOS_LIMPOS'!C8 | C32: ='03_DADOS_LIMPOS'!D8 | D32: ='03_DADOS_LIMPOS'!J8 | E32: =$B$8+$B$9*D32 | F32: =C32-E32 | G32: =F32/$B$11 | H32: =ABS(G32)
A33: ='03_DADOS_LIMPOS'!A9 | B33: ='03_DADOS_LIMPOS'!C9 | C33: ='03_DADOS_LIMPOS'!D9 | D33: ='03_DADOS_LIMPOS'!J9 | E33: =$B$8+$B$9*D33 | F33: =C33-E33 | G33: =F33/$B$11 | H33: =ABS(G33)
A34: ='03_DADOS_LIMPOS'!A10 | B34: ='03_DADOS_LIMPOS'!C10 | C34: ='03_DADOS_LIMPOS'!D10 | D34: ='03_DADOS_LIMPOS'!J10 | E34: =$B$8+$B$9*D34 | F34: =C34-E34 | G34: =F34/$B$11 | H34: =ABS(G34)
A35: ='03_DADOS_LIMPOS'!A11 | B35: ='03_DADOS_LIMPOS'!C11 | C35: ='03_DADOS_LIMPOS'!D11 | D35: ='03_DADOS_LIMPOS'!J11 | E35: =$B$8+$B$9*D35 | F35: =C35-E35 | G35: =F35/$B$11 | H35: =ABS(G35)
A36: ='03_DADOS_LIMPOS'!A12 | B36: ='03_DADOS_LIMPOS'!C12 | C36: ='03_DADOS_LIMPOS'!D12 | D36: ='03_DADOS_LIMPOS'!J12 | E36: =$B$8+$B$9*D36 | F36: =C36-E36 | G36: =F36/$B$11 | H36: =ABS(G36)
A37: ='03_DADOS_LIMPOS'!A13 | B37: ='03_DADOS_LIMPOS'!C13 | C37: ='03_DADOS_LIMPOS'!D13 | D37: ='03_DADOS_LIMPOS'!J13 | E37: =$B$8+$B$9*D37 | F37: =C37-E37 | G37: =F37/$B$11 | H37: =ABS(G37)
... A3837: ='03_DADOS_LIMPOS'!A3813 | B3837: ='03_DADOS_LIMPOS'!C3813 | C3837: ='03_DADOS_LIMPOS'!D3813 | D3837: ='03_DADOS_LIMPOS'!J3813 | E3837: =$B$8+$B$9*D3837 | F3837: =C3837-E3837 | G3837: =F3837/$B$11 | H3837: =ABS(G3837)

Sheet 07_MODELO_NPI
A1: Modelo | B1: API00 ~ NPI
A2: n | B2: =COUNTA(FILTER('03_DADOS_LIMPOS'!D2:D;ISNUMBER('03_DADOS_LIMPOS'!D2:D)))
A3: gl | B3: =B2-2
A4: alpha | B4: 0.05
A5: nivel_confianca | B5: =1-B4
A7: Métrica | B7: Fórmula
A8: Intercepto | B8: =INTERCEPT(FILTER('03_DADOS_LIMPOS'!D2:D;ISNUMBER('03_DADOS_LIMPOS'!D2:D));FILTER('03_DADOS_LIMPOS'!K2:K;ISNUMBER('03_DADOS_LIMPOS'!D2:D)))
A9: Coeficiente NPI | B9: =SLOPE(FILTER('03_DADOS_LIMPOS'!D2:D;ISNUMBER('03_DADOS_LIMPOS'!D2:D));FILTER('03_DADOS_LIMPOS'!K2:K;ISNUMBER('03_DADOS_LIMPOS'!D2:D)))
A10: R2 | B10: =RSQ(FILTER('03_DADOS_LIMPOS'!D2:D;ISNUMBER('03_DADOS_LIMPOS'!D2:D));FILTER('03_DADOS_LIMPOS'!K2:K;ISNUMBER('03_DADOS_LIMPOS'!D2:D)))
A11: Erro padrão residual | B11: =STEYX(FILTER('03_DADOS_LIMPOS'!D2:D;ISNUMBER('03_DADOS_LIMPOS'!D2:D));FILTER('03_DADOS_LIMPOS'!K2:K;ISNUMBER('03_DADOS_LIMPOS'!D2:D)))
A13: Parâmetro | B13: Coeficiente | C13: Erro padrão | D13: t | E13: valor-p | F13: IC95 inferior | G13: IC95 superior
A14: Intercepto | B14: =B8 | C14: =INDEX(LINEST(FILTER('03_DADOS_LIMPOS'!D2:D;ISNUMBER('03_DADOS_LIMPOS'!D2:D));FILTER('03_DADOS_LIMPOS'!K2:K;ISNUMBER('03_DADOS_LIMPOS'!D2:D));TRUE;TRUE);2;2) | D14: =B14/C14 | E14: =T.DIST.2T(ABS(D14);$B$3) | F14: =B14-TINV($B$4;$B$3)*C14 | G14: =B14+TINV($B$4;$B$3)*C14
A15: NPI | B15: =B9 | C15: =INDEX(LINEST(FILTER('03_DADOS_LIMPOS'!D2:D;ISNUMBER('03_DADOS_LIMPOS'!D2:D));FILTER('03_DADOS_LIMPOS'!K2:K;ISNUMBER('03_DADOS_LIMPOS'!D2:D));TRUE;TRUE);2;1) | D15: =B15/C15 | E15: =T.DIST.2T(ABS(D15);$B$3) | F15: =B15-TINV($B$4;$B$3)*C15 | G15: =B15+TINV($B$4;$B$3)*C15
A18: Nota sobre alpha
A19: alpha = 0,05 porque o intervalo é de 95%: alpha = 1 - 0,95.
A20: TINV(alpha; gl) retorna o valor crítico t bilateral usado no IC95.
A22: Interpretação
A23: O IC95 de NPI está totalmente abaixo de zero.
A24: O valor-p pequeno indica evidência estatística de associação linear negativa.
A25: ID | B25: NOME | C25: API00 | D25: NPI | E25: API00_ajustado_NPI | F25: residuo_NPI | G25: residuo_padronizado_NPI | H25: abs_residuo_padronizado_NPI
A26: ='03_DADOS_LIMPOS'!A2 | B26: ='03_DADOS_LIMPOS'!C2 | C26: ='03_DADOS_LIMPOS'!D2 | D26: ='03_DADOS_LIMPOS'!K2 | E26: =$B$8+$B$9*D26 | F26: =C26-E26 | G26: =F26/$B$11 | H26: =ABS(G26)
A27: ='03_DADOS_LIMPOS'!A3 | B27: ='03_DADOS_LIMPOS'!C3 | C27: ='03_DADOS_LIMPOS'!D3 | D27: ='03_DADOS_LIMPOS'!K3 | E27: =$B$8+$B$9*D27 | F27: =C27-E27 | G27: =F27/$B$11 | H27: =ABS(G27)
A28: ='03_DADOS_LIMPOS'!A4 | B28: ='03_DADOS_LIMPOS'!C4 | C28: ='03_DADOS_LIMPOS'!D4 | D28: ='03_DADOS_LIMPOS'!K4 | E28: =$B$8+$B$9*D28 | F28: =C28-E28 | G28: =F28/$B$11 | H28: =ABS(G28)
A29: ='03_DADOS_LIMPOS'!A5 | B29: ='03_DADOS_LIMPOS'!C5 | C29: ='03_DADOS_LIMPOS'!D5 | D29: ='03_DADOS_LIMPOS'!K5 | E29: =$B$8+$B$9*D29 | F29: =C29-E29 | G29: =F29/$B$11 | H29: =ABS(G29)
A30: ='03_DADOS_LIMPOS'!A6 | B30: ='03_DADOS_LIMPOS'!C6 | C30: ='03_DADOS_LIMPOS'!D6 | D30: ='03_DADOS_LIMPOS'!K6 | E30: =$B$8+$B$9*D30 | F30: =C30-E30 | G30: =F30/$B$11 | H30: =ABS(G30)
A31: ='03_DADOS_LIMPOS'!A7 | B31: ='03_DADOS_LIMPOS'!C7 | C31: ='03_DADOS_LIMPOS'!D7 | D31: ='03_DADOS_LIMPOS'!K7 | E31: =$B$8+$B$9*D31 | F31: =C31-E31 | G31: =F31/$B$11 | H31: =ABS(G31)
A32: ='03_DADOS_LIMPOS'!A8 | B32: ='03_DADOS_LIMPOS'!C8 | C32: ='03_DADOS_LIMPOS'!D8 | D32: ='03_DADOS_LIMPOS'!K8 | E32: =$B$8+$B$9*D32 | F32: =C32-E32 | G32: =F32/$B$11 | H32: =ABS(G32)
A33: ='03_DADOS_LIMPOS'!A9 | B33: ='03_DADOS_LIMPOS'!C9 | C33: ='03_DADOS_LIMPOS'!D9 | D33: ='03_DADOS_LIMPOS'!K9 | E33: =$B$8+$B$9*D33 | F33: =C33-E33 | G33: =F33/$B$11 | H33: =ABS(G33)
A34: ='03_DADOS_LIMPOS'!A10 | B34: ='03_DADOS_LIMPOS'!C10 | C34: ='03_DADOS_LIMPOS'!D10 | D34: ='03_DADOS_LIMPOS'!K10 | E34: =$B$8+$B$9*D34 | F34: =C34-E34 | G34: =F34/$B$11 | H34: =ABS(G34)
A35: ='03_DADOS_LIMPOS'!A11 | B35: ='03_DADOS_LIMPOS'!C11 | C35: ='03_DADOS_LIMPOS'!D11 | D35: ='03_DADOS_LIMPOS'!K11 | E35: =$B$8+$B$9*D35 | F35: =C35-E35 | G35: =F35/$B$11 | H35: =ABS(G35)
A36: ='03_DADOS_LIMPOS'!A12 | B36: ='03_DADOS_LIMPOS'!C12 | C36: ='03_DADOS_LIMPOS'!D12 | D36: ='03_DADOS_LIMPOS'!K12 | E36: =$B$8+$B$9*D36 | F36: =C36-E36 | G36: =F36/$B$11 | H36: =ABS(G36)
A37: ='03_DADOS_LIMPOS'!A13 | B37: ='03_DADOS_LIMPOS'!C13 | C37: ='03_DADOS_LIMPOS'!D13 | D37: ='03_DADOS_LIMPOS'!K13 | E37: =$B$8+$B$9*D37 | F37: =C37-E37 | G37: =F37/$B$11 | H37: =ABS(G37)
... A3837: ='03_DADOS_LIMPOS'!A3813 | B3837: ='03_DADOS_LIMPOS'!C3813 | C3837: ='03_DADOS_LIMPOS'!D3813 | D3837: ='03_DADOS_LIMPOS'!K3813 | E3837: =$B$8+$B$9*D3837 | F3837: =C3837-E3837 | G3837: =F3837/$B$11 | H3837: =ABS(G3837)

Sheet 08_MODELO_MULTIPLO
A1: Modelo | B1: API00 ~ REFS + NPI
A2: n | B2: =COUNTA(FILTER('03_DADOS_LIMPOS'!D2:D;ISNUMBER('03_DADOS_LIMPOS'!D2:D)))
A3: k | B3: 2
A4: gl | B4: =B2-B3-1
A5: alpha | B5: 0.05
A6: nivel_confianca | B6: =1-B5
A8: Métrica | B8: Fórmula
A9: Intercepto | B9: =INDEX(LINEST(FILTER('03_DADOS_LIMPOS'!D2:D;ISNUMBER('03_DADOS_LIMPOS'!D2:D));FILTER('03_DADOS_LIMPOS'!J2:K;ISNUMBER('03_DADOS_LIMPOS'!D2:D));TRUE;TRUE);1;3)
A10: Coeficiente REFS | B10: =INDEX(LINEST(FILTER('03_DADOS_LIMPOS'!D2:D;ISNUMBER('03_DADOS_LIMPOS'!D2:D));FILTER('03_DADOS_LIMPOS'!J2:K;ISNUMBER('03_DADOS_LIMPOS'!D2:D));TRUE;TRUE);1;2)
A11: Coeficiente NPI | B11: =INDEX(LINEST(FILTER('03_DADOS_LIMPOS'!D2:D;ISNUMBER('03_DADOS_LIMPOS'!D2:D));FILTER('03_DADOS_LIMPOS'!J2:K;ISNUMBER('03_DADOS_LIMPOS'!D2:D));TRUE;TRUE);1;1)
A12: R2 | B12: =INDEX(LINEST(FILTER('03_DADOS_LIMPOS'!D2:D;ISNUMBER('03_DADOS_LIMPOS'!D2:D));FILTER('03_DADOS_LIMPOS'!J2:K;ISNUMBER('03_DADOS_LIMPOS'!D2:D));TRUE;TRUE);3;1)
A13: R2 ajustado | B13: =1-(1-B12)*(B2-1)/(B2-B3-1)
A14: Erro padrão residual | B14: =INDEX(LINEST(FILTER('03_DADOS_LIMPOS'!D2:D;ISNUMBER('03_DADOS_LIMPOS'!D2:D));FILTER('03_DADOS_LIMPOS'!J2:K;ISNUMBER('03_DADOS_LIMPOS'!D2:D));TRUE;TRUE);3;2)
A16: Ordem LINEST | B16: Se X estiver como REFS:NPI, LINEST retorna NPI, REFS e intercepto.
A18: Parâmetro | B18: Coeficiente | C18: Erro padrão | D18: t | E18: valor-p | F18: IC95 inferior | G18: IC95 superior
A19: Intercepto | B19: =B9 | C19: =INDEX(LINEST(FILTER('03_DADOS_LIMPOS'!D2:D;ISNUMBER('03_DADOS_LIMPOS'!D2:D));FILTER('03_DADOS_LIMPOS'!J2:K;ISNUMBER('03_DADOS_LIMPOS'!D2:D));TRUE;TRUE);2;3) | D19: =B19/C19 | E19: =T.DIST.2T(ABS(D19);$B$4) | F19: =B19-TINV($B$5;$B$4)*C19 | G19: =B19+TINV($B$5;$B$4)*C19
A20: REFS | B20: =B10 | C20: =INDEX(LINEST(FILTER('03_DADOS_LIMPOS'!D2:D;ISNUMBER('03_DADOS_LIMPOS'!D2:D));FILTER('03_DADOS_LIMPOS'!J2:K;ISNUMBER('03_DADOS_LIMPOS'!D2:D));TRUE;TRUE);2;2) | D20: =B20/C20 | E20: =T.DIST.2T(ABS(D20);$B$4) | F20: =B20-TINV($B$5;$B$4)*C20 | G20: =B20+TINV($B$5;$B$4)*C20
A21: NPI | B21: =B11 | C21: =INDEX(LINEST(FILTER('03_DADOS_LIMPOS'!D2:D;ISNUMBER('03_DADOS_LIMPOS'!D2:D));FILTER('03_DADOS_LIMPOS'!J2:K;ISNUMBER('03_DADOS_LIMPOS'!D2:D));TRUE;TRUE);2;1) | D21: =B21/C21 | E21: =T.DIST.2T(ABS(D21);$B$4) | F21: =B21-TINV($B$5;$B$4)*C21 | G21: =B21+TINV($B$5;$B$4)*C21
A24: Nota sobre alpha
A25: alpha = 0,05 porque o intervalo é de 95%: alpha = 1 - 0,95.
A26: TINV(alpha; gl) retorna o valor crítico t bilateral usado no IC95.
A28: Interpretação
A29: Os IC95 de REFS e NPI permanecem abaixo de zero.
A30: ID | B30: NOME | C30: API00 | D30: REFS | E30: NPI | F30: API00_ajustado_MULTI | G30: residuo_MULTI | H30: residuo_padronizado_MULTI | I30: abs_residuo_padronizado_MULTI
A31: ='03_DADOS_LIMPOS'!A2 | B31: ='03_DADOS_LIMPOS'!C2 | C31: ='03_DADOS_LIMPOS'!D2 | D31: ='03_DADOS_LIMPOS'!J2 | E31: ='03_DADOS_LIMPOS'!K2 | F31: =$B$9+$B$10*D31+$B$11*E31 | G31: =C31-F31 | H31: =G31/$B$14 | I31: =ABS(H31)
A32: ='03_DADOS_LIMPOS'!A3 | B32: ='03_DADOS_LIMPOS'!C3 | C32: ='03_DADOS_LIMPOS'!D3 | D32: ='03_DADOS_LIMPOS'!J3 | E32: ='03_DADOS_LIMPOS'!K3 | F32: =$B$9+$B$10*D32+$B$11*E32 | G32: =C32-F32 | H32: =G32/$B$14 | I32: =ABS(H32)
A33: ='03_DADOS_LIMPOS'!A4 | B33: ='03_DADOS_LIMPOS'!C4 | C33: ='03_DADOS_LIMPOS'!D4 | D33: ='03_DADOS_LIMPOS'!J4 | E33: ='03_DADOS_LIMPOS'!K4 | F33: =$B$9+$B$10*D33+$B$11*E33 | G33: =C33-F33 | H33: =G33/$B$14 | I33: =ABS(H33)
A34: ='03_DADOS_LIMPOS'!A5 | B34: ='03_DADOS_LIMPOS'!C5 | C34: ='03_DADOS_LIMPOS'!D5 | D34: ='03_DADOS_LIMPOS'!J5 | E34: ='03_DADOS_LIMPOS'!K5 | F34: =$B$9+$B$10*D34+$B$11*E34 | G34: =C34-F34 | H34: =G34/$B$14 | I34: =ABS(H34)
A35: ='03_DADOS_LIMPOS'!A6 | B35: ='03_DADOS_LIMPOS'!C6 | C35: ='03_DADOS_LIMPOS'!D6 | D35: ='03_DADOS_LIMPOS'!J6 | E35: ='03_DADOS_LIMPOS'!K6 | F35: =$B$9+$B$10*D35+$B$11*E35 | G35: =C35-F35 | H35: =G35/$B$14 | I35: =ABS(H35)
A36: ='03_DADOS_LIMPOS'!A7 | B36: ='03_DADOS_LIMPOS'!C7 | C36: ='03_DADOS_LIMPOS'!D7 | D36: ='03_DADOS_LIMPOS'!J7 | E36: ='03_DADOS_LIMPOS'!K7 | F36: =$B$9+$B$10*D36+$B$11*E36 | G36: =C36-F36 | H36: =G36/$B$14 | I36: =ABS(H36)
A37: ='03_DADOS_LIMPOS'!A8 | B37: ='03_DADOS_LIMPOS'!C8 | C37: ='03_DADOS_LIMPOS'!D8 | D37: ='03_DADOS_LIMPOS'!J8 | E37: ='03_DADOS_LIMPOS'!K8 | F37: =$B$9+$B$10*D37+$B$11*E37 | G37: =C37-F37 | H37: =G37/$B$14 | I37: =ABS(H37)
A38: ='03_DADOS_LIMPOS'!A9 | B38: ='03_DADOS_LIMPOS'!C9 | C38: ='03_DADOS_LIMPOS'!D9 | D38: ='03_DADOS_LIMPOS'!J9 | E38: ='03_DADOS_LIMPOS'!K9 | F38: =$B$9+$B$10*D38+$B$11*E38 | G38: =C38-F38 | H38: =G38/$B$14 | I38: =ABS(H38)
A39: ='03_DADOS_LIMPOS'!A10 | B39: ='03_DADOS_LIMPOS'!C10 | C39: ='03_DADOS_LIMPOS'!D10 | D39: ='03_DADOS_LIMPOS'!J10 | E39: ='03_DADOS_LIMPOS'!K10 | F39: =$B$9+$B$10*D39+$B$11*E39 | G39: =C39-F39 | H39: =G39/$B$14 | I39: =ABS(H39)
A40: ='03_DADOS_LIMPOS'!A11 | B40: ='03_DADOS_LIMPOS'!C11 | C40: ='03_DADOS_LIMPOS'!D11 | D40: ='03_DADOS_LIMPOS'!J11 | E40: ='03_DADOS_LIMPOS'!K11 | F40: =$B$9+$B$10*D40+$B$11*E40 | G40: =C40-F40 | H40: =G40/$B$14 | I40: =ABS(H40)
A41: ='03_DADOS_LIMPOS'!A12 | B41: ='03_DADOS_LIMPOS'!C12 | C41: ='03_DADOS_LIMPOS'!D12 | D41: ='03_DADOS_LIMPOS'!J12 | E41: ='03_DADOS_LIMPOS'!K12 | F41: =$B$9+$B$10*D41+$B$11*E41 | G41: =C41-F41 | H41: =G41/$B$14 | I41: =ABS(H41)
A42: ='03_DADOS_LIMPOS'!A13 | B42: ='03_DADOS_LIMPOS'!C13 | C42: ='03_DADOS_LIMPOS'!D13 | D42: ='03_DADOS_LIMPOS'!J13 | E42: ='03_DADOS_LIMPOS'!K13 | F42: =$B$9+$B$10*D42+$B$11*E42 | G42: =C42-F42 | H42: =G42/$B$14 | I42: =ABS(H42)
... A3842: ='03_DADOS_LIMPOS'!A3813 | B3842: ='03_DADOS_LIMPOS'!C3813 | C3842: ='03_DADOS_LIMPOS'!D3813 | D3842: ='03_DADOS_LIMPOS'!J3813 | E3842: ='03_DADOS_LIMPOS'!K3813 | F3842: =$B$9+$B$10*D3842+$B$11*E3842 | G3842: =C3842-F3842 | H3842: =G3842/$B$14 | I3842: =ABS(H3842)

Sheet 09_COMPARACAO_MODELOS
A1: Modelo | B1: Tipo | C1: R2 | D1: R2 ajustado | E1: Erro padrão residual | F1: Interpretação inferencial
A2: API00 ~ REFS | B2: RLS principal | C2: ='06_MODELO_REFS'!B10 | D2: ='06_MODELO_REFS'!B10 | E2: ='06_MODELO_REFS'!B11 | F2: REFS negativo, IC95 abaixo de zero, p <0,001
A3: API00 ~ NPI | B3: RLS complementar | C3: ='07_MODELO_NPI'!B10 | D3: ='07_MODELO_NPI'!B10 | E3: ='07_MODELO_NPI'!B11 | F3: NPI negativo, IC95 abaixo de zero, p <0,001
A4: API00 ~ REFS + NPI | B4: Regressão múltipla | C4: ='08_MODELO_MULTIPLO'!B12 | D4: ='08_MODELO_MULTIPLO'!B13 | E4: ='08_MODELO_MULTIPLO'!B14 | F4: ambos negativos, IC95 abaixo de zero, p <0,001
A6: Interpretação
A7: REFS explica mais variação de API00 do que NPI isoladamente.
A8: O modelo múltiplo melhora o ajuste, mas pouco em relação ao modelo com REFS.
A9: Valor-p pequeno não mede tamanho do efeito e não prova causalidade.
A10: IC95 informa faixa plausível para o coeficiente sob o modelo especificado.
A11: Os gráficos de modelos simples mostram a reta de MQ diretamente; os gráficos do modelo múltiplo são projeções dos valores ajustados.

Sheet 10_DIAGNOSTICOS
A1: Resíduos versus ajustados - API00 ~ REFS | E1: Resíduos versus ajustados - API00 ~ NPI | I1: Resíduos versus ajustados - API00 ~ REFS + NPI | M1: Interpretação
A2: fitted | B2: residual | E2: fitted | F2: residual | I2: fitted | J2: residual | M2: Verificar caudas e padrões de dispersão. Normalidade não deve ser usada como critério automático.
A3: ='06_MODELO_REFS'!E26 | B3: ='06_MODELO_REFS'!F26 | E3: ='07_MODELO_NPI'!E26 | F3: ='07_MODELO_NPI'!F26 | I3: ='08_MODELO_MULTIPLO'!F31 | J3: ='08_MODELO_MULTIPLO'!G31 | M3: Valor-p e IC95 dependem da adequação aproximada das hipóteses do modelo.
A4: ='06_MODELO_REFS'!E27 | B4: ='06_MODELO_REFS'!F27 | E4: ='07_MODELO_NPI'!E27 | F4: ='07_MODELO_NPI'!F27 | I4: ='08_MODELO_MULTIPLO'!F32 | J4: ='08_MODELO_MULTIPLO'!G32
A5: ='06_MODELO_REFS'!E28 | B5: ='06_MODELO_REFS'!F28 | E5: ='07_MODELO_NPI'!E28 | F5: ='07_MODELO_NPI'!F28 | I5: ='08_MODELO_MULTIPLO'!F33 | J5: ='08_MODELO_MULTIPLO'!G33
A6: ='06_MODELO_REFS'!E29 | B6: ='06_MODELO_REFS'!F29 | E6: ='07_MODELO_NPI'!E29 | F6: ='07_MODELO_NPI'!F29 | I6: ='08_MODELO_MULTIPLO'!F34 | J6: ='08_MODELO_MULTIPLO'!G34
A7: ='06_MODELO_REFS'!E30 | B7: ='06_MODELO_REFS'!F30 | E7: ='07_MODELO_NPI'!E30 | F7: ='07_MODELO_NPI'!F30 | I7: ='08_MODELO_MULTIPLO'!F35 | J7: ='08_MODELO_MULTIPLO'!G35
A8: ='06_MODELO_REFS'!E31 | B8: ='06_MODELO_REFS'!F31 | E8: ='07_MODELO_NPI'!E31 | F8: ='07_MODELO_NPI'!F31 | I8: ='08_MODELO_MULTIPLO'!F36 | J8: ='08_MODELO_MULTIPLO'!G36
A9: ='06_MODELO_REFS'!E32 | B9: ='06_MODELO_REFS'!F32 | E9: ='07_MODELO_NPI'!E32 | F9: ='07_MODELO_NPI'!F32 | I9: ='08_MODELO_MULTIPLO'!F37 | J9: ='08_MODELO_MULTIPLO'!G37
A10: ='06_MODELO_REFS'!E33 | B10: ='06_MODELO_REFS'!F33 | E10: ='07_MODELO_NPI'!E33 | F10: ='07_MODELO_NPI'!F33 | I10: ='08_MODELO_MULTIPLO'!F38 | J10: ='08_MODELO_MULTIPLO'!G38
A11: ='06_MODELO_REFS'!E34 | B11: ='06_MODELO_REFS'!F34 | E11: ='07_MODELO_NPI'!E34 | F11: ='07_MODELO_NPI'!F34 | I11: ='08_MODELO_MULTIPLO'!F39 | J11: ='08_MODELO_MULTIPLO'!G39
A12: ='06_MODELO_REFS'!E35 | B12: ='06_MODELO_REFS'!F35 | E12: ='07_MODELO_NPI'!E35 | F12: ='07_MODELO_NPI'!F35 | I12: ='08_MODELO_MULTIPLO'!F40 | J12: ='08_MODELO_MULTIPLO'!G40
A13: ='06_MODELO_REFS'!E36 | B13: ='06_MODELO_REFS'!F36 | E13: ='07_MODELO_NPI'!E36 | F13: ='07_MODELO_NPI'!F36 | I13: ='08_MODELO_MULTIPLO'!F41 | J13: ='08_MODELO_MULTIPLO'!G41
A14: ='06_MODELO_REFS'!E37 | B14: ='06_MODELO_REFS'!F37 | E14: ='07_MODELO_NPI'!E37 | F14: ='07_MODELO_NPI'!F37 | I14: ='08_MODELO_MULTIPLO'!F42 | J14: ='08_MODELO_MULTIPLO'!G42
A15: ='06_MODELO_REFS'!E38 | B15: ='06_MODELO_REFS'!F38 | E15: ='07_MODELO_NPI'!E38 | F15: ='07_MODELO_NPI'!F38 | I15: ='08_MODELO_MULTIPLO'!F43 | J15: ='08_MODELO_MULTIPLO'!G43
... A3814: ='06_MODELO_REFS'!E3837 | B3814: ='06_MODELO_REFS'!F3837 | E3814: ='07_MODELO_NPI'!E3837 | F3814: ='07_MODELO_NPI'!F3837 | I3814: ='08_MODELO_MULTIPLO'!F3842 | J3814: ='08_MODELO_MULTIPLO'!G3842
A3818: QQ-plot simplificado API00 ~ REFS | F3818: QQ-plot simplificado API00 ~ NPI | K3818: QQ-plot simplificado API00 ~ REFS + NPI
A3819: i | B3819: p | C3819: quantil_normal | D3819: residuo_ordenado | F3819: i | G3819: p | H3819: quantil_normal | I3819: residuo_ordenado | K3819: i | L3819: p | M3819: quantil_normal | N3819: residuo_ordenado
A3820: 1 | B3820: =(A3820-0,5)/3812 | C3820: =NORM.S.INV(B3820) | D3820: =INDEX(SORT('06_MODELO_REFS'!F$26:F$3837;1;TRUE);A3820) | F3820: 1 | G3820: =(F3820-0,5)/3812 | H3820: =NORM.S.INV(G3820) | I3820: =INDEX(SORT('07_MODELO_NPI'!F$26:F$3837;1;TRUE);F3820) | K3820: 1 | L3820: =(K3820-0,5)/3812 | M3820: =NORM.S.INV(L3820) | N3820: =INDEX(SORT('08_MODELO_MULTIPLO'!G$31:G$3842;1;TRUE);K3820)
A3821: 2 | B3821: =(A3821-0,5)/3812 | C3821: =NORM.S.INV(B3821) | D3821: =INDEX(SORT('06_MODELO_REFS'!F$26:F$3837;1;TRUE);A3821) | F3821: 2 | G3821: =(F3821-0,5)/3812 | H3821: =NORM.S.INV(G3821) | I3821: =INDEX(SORT('07_MODELO_NPI'!F$26:F$3837;1;TRUE);F3821) | K3821: 2 | L3821: =(K3821-0,5)/3812 | M3821: =NORM.S.INV(L3821) | N3821: =INDEX(SORT('08_MODELO_MULTIPLO'!G$31:G$3842;1;TRUE);K3821)
A3822: 3 | B3822: =(A3822-0,5)/3812 | C3822: =NORM.S.INV(B3822) | D3822: =INDEX(SORT('06_MODELO_REFS'!F$26:F$3837;1;TRUE);A3822) | F3822: 3 | G3822: =(F3822-0,5)/3812 | H3822: =NORM.S.INV(G3822) | I3822: =INDEX(SORT('07_MODELO_NPI'!F$26:F$3837;1;TRUE);F3822) | K3822: 3 | L3822: =(K3822-0,5)/3812 | M3822: =NORM.S.INV(L3822) | N3822: =INDEX(SORT('08_MODELO_MULTIPLO'!G$31:G$3842;1;TRUE);K3822)
A3823: 4 | B3823: =(A3823-0,5)/3812 | C3823: =NORM.S.INV(B3823) | D3823: =INDEX(SORT('06_MODELO_REFS'!F$26:F$3837;1;TRUE);A3823) | F3823: 4 | G3823: =(F3823-0,5)/3812 | H3823: =NORM.S.INV(G3823) | I3823: =INDEX(SORT('07_MODELO_NPI'!F$26:F$3837;1;TRUE);F3823) | K3823: 4 | L3823: =(K3823-0,5)/3812 | M3823: =NORM.S.INV(L3823) | N3823: =INDEX(SORT('08_MODELO_MULTIPLO'!G$31:G$3842;1;TRUE);K3823)
A3824: 5 | B3824: =(A3824-0,5)/3812 | C3824: =NORM.S.INV(B3824) | D3824: =INDEX(SORT('06_MODELO_REFS'!F$26:F$3837;1;TRUE);A3824) | F3824: 5 | G3824: =(F3824-0,5)/3812 | H3824: =NORM.S.INV(G3824) | I3824: =INDEX(SORT('07_MODELO_NPI'!F$26:F$3837;1;TRUE);F3824) | K3824: 5 | L3824: =(K3824-0,5)/3812 | M3824: =NORM.S.INV(L3824) | N3824: =INDEX(SORT('08_MODELO_MULTIPLO'!G$31:G$3842;1;TRUE);K3824)
A3825: 6 | B3825: =(A3825-0,5)/3812 | C3825: =NORM.S.INV(B3825) | D3825: =INDEX(SORT('06_MODELO_REFS'!F$26:F$3837;1;TRUE);A3825) | F3825: 6 | G3825: =(F3825-0,5)/3812 | H3825: =NORM.S.INV(G3825) | I3825: =INDEX(SORT('07_MODELO_NPI'!F$26:F$3837;1;TRUE);F3825) | K3825: 6 | L3825: =(K3825-0,5)/3812 | M3825: =NORM.S.INV(L3825) | N3825: =INDEX(SORT('08_MODELO_MULTIPLO'!G$31:G$3842;1;TRUE);K3825)
A3826: 7 | B3826: =(A3826-0,5)/3812 | C3826: =NORM.S.INV(B3826) | D3826: =INDEX(SORT('06_MODELO_REFS'!F$26:F$3837;1;TRUE);A3826) | F3826: 7 | G3826: =(F3826-0,5)/3812 | H3826: =NORM.S.INV(G3826) | I3826: =INDEX(SORT('07_MODELO_NPI'!F$26:F$3837;1;TRUE);F3826) | K3826: 7 | L3826: =(K3826-0,5)/3812 | M3826: =NORM.S.INV(L3826) | N3826: =INDEX(SORT('08_MODELO_MULTIPLO'!G$31:G$3842;1;TRUE);K3826)
A3827: 8 | B3827: =(A3827-0,5)/3812 | C3827: =NORM.S.INV(B3827) | D3827: =INDEX(SORT('06_MODELO_REFS'!F$26:F$3837;1;TRUE);A3827) | F3827: 8 | G3827: =(F3827-0,5)/3812 | H3827: =NORM.S.INV(G3827) | I3827: =INDEX(SORT('07_MODELO_NPI'!F$26:F$3837;1;TRUE);F3827) | K3827: 8 | L3827: =(K3827-0,5)/3812 | M3827: =NORM.S.INV(L3827) | N3827: =INDEX(SORT('08_MODELO_MULTIPLO'!G$31:G$3842;1;TRUE);K3827)
A3828: 9 | B3828: =(A3828-0,5)/3812 | C3828: =NORM.S.INV(B3828) | D3828: =INDEX(SORT('06_MODELO_REFS'!F$26:F$3837;1;TRUE);A3828) | F3828: 9 | G3828: =(F3828-0,5)/3812 | H3828: =NORM.S.INV(G3828) | I3828: =INDEX(SORT('07_MODELO_NPI'!F$26:F$3837;1;TRUE);F3828) | K3828: 9 | L3828: =(K3828-0,5)/3812 | M3828: =NORM.S.INV(L3828) | N3828: =INDEX(SORT('08_MODELO_MULTIPLO'!G$31:G$3842;1;TRUE);K3828)
A3829: 10 | B3829: =(A3829-0,5)/3812 | C3829: =NORM.S.INV(B3829) | D3829: =INDEX(SORT('06_MODELO_REFS'!F$26:F$3837;1;TRUE);A3829) | F3829: 10 | G3829: =(F3829-0,5)/3812 | H3829: =NORM.S.INV(G3829) | I3829: =INDEX(SORT('07_MODELO_NPI'!F$26:F$3837;1;TRUE);F3829) | K3829: 10 | L3829: =(K3829-0,5)/3812 | M3829: =NORM.S.INV(L3829) | N3829: =INDEX(SORT('08_MODELO_MULTIPLO'!G$31:G$3842;1;TRUE);K3829)
A3830: 11 | B3830: =(A3830-0,5)/3812 | C3830: =NORM.S.INV(B3830) | D3830: =INDEX(SORT('06_MODELO_REFS'!F$26:F$3837;1;TRUE);A3830) | F3830: 11 | G3830: =(F3830-0,5)/3812 | H3830: =NORM.S.INV(G3830) | I3830: =INDEX(SORT('07_MODELO_NPI'!F$26:F$3837;1;TRUE);F3830) | K3830: 11 | L3830: =(K3830-0,5)/3812 | M3830: =NORM.S.INV(L3830) | N3830: =INDEX(SORT('08_MODELO_MULTIPLO'!G$31:G$3842;1;TRUE);K3830)
A3831: 12 | B3831: =(A3831-0,5)/3812 | C3831: =NORM.S.INV(B3831) | D3831: =INDEX(SORT('06_MODELO_REFS'!F$26:F$3837;1;TRUE);A3831) | F3831: 12 | G3831: =(F3831-0,5)/3812 | H3831: =NORM.S.INV(G3831) | I3831: =INDEX(SORT('07_MODELO_NPI'!F$26:F$3837;1;TRUE);F3831) | K3831: 12 | L3831: =(K3831-0,5)/3812 | M3831: =NORM.S.INV(L3831) | N3831: =INDEX(SORT('08_MODELO_MULTIPLO'!G$31:G$3842;1;TRUE);K3831)
... A7631: 3812 | B7631: =(A7631-0,5)/3812 | C7631: =NORM.S.INV(B7631) | D7631: =INDEX(SORT('06_MODELO_REFS'!F$26:F$3837;1;TRUE);A7631) | F7631: 3812 | G7631: =(F7631-0,5)/3812 | H7631: =NORM.S.INV(G7631) | I7631: =INDEX(SORT('07_MODELO_NPI'!F$26:F$3837;1;TRUE);F7631) | K7631: 3812 | L7631: =(K7631-0,5)/3812 | M7631: =NORM.S.INV(L7631) | N7631: =INDEX(SORT('08_MODELO_MULTIPLO'!G$31:G$3842;1;TRUE);K7631)

Sheet 11_OUTLIERS
A1: Modelo | B1: n | C1: |resíduo padronizado| > 2 | D1: |resíduo padronizado| > 3 | E1: % > 3
A2: API00 ~ REFS | B2: ='06_MODELO_REFS'!B2 | C2: =SUMPRODUCT(--(ABS('06_MODELO_REFS'!G26:G3837)>2)) | D2: =SUMPRODUCT(--(ABS('06_MODELO_REFS'!G26:G3837)>3)) | E2: =D2/B2*100
A3: API00 ~ NPI | B3: ='07_MODELO_NPI'!B2 | C3: =SUMPRODUCT(--(ABS('07_MODELO_NPI'!G26:G3837)>2)) | D3: =SUMPRODUCT(--(ABS('07_MODELO_NPI'!G26:G3837)>3)) | E3: =D3/B3*100
A4: API00 ~ REFS + NPI | B4: ='08_MODELO_MULTIPLO'!B2 | C4: =SUMPRODUCT(--(ABS('08_MODELO_MULTIPLO'!H31:H3842)>2)) | D4: =SUMPRODUCT(--(ABS('08_MODELO_MULTIPLO'!H31:H3842)>3)) | E4: =D4/B4*100
A6: 10 escolas mais atípicas no modelo API00 ~ REFS
A7: ID | B7: NOME | C7: API00 | D7: REFS | E7: valor_ajustado_REFS | F7: residuo_REFS | G7: residuo_padronizado_REFS | H7: abs_residuo_padronizado_REFS | I7: linha_auxiliar
A8: =INDEX('06_MODELO_REFS'!A$26:A$3837;$I8) | B8: =INDEX('06_MODELO_REFS'!B$26:B$3837;$I8) | C8: =INDEX('06_MODELO_REFS'!C$26:C$3837;$I8) | D8: =INDEX('06_MODELO_REFS'!D$26:D$3837;$I8) | E8: =INDEX('06_MODELO_REFS'!E$26:E$3837;$I8) | F8: =INDEX('06_MODELO_REFS'!F$26:F$3837;$I8) | G8: =INDEX('06_MODELO_REFS'!G$26:G$3837;$I8) | H8: =LARGE('06_MODELO_REFS'!H$26:H$3837;1) | I8: =MATCH(H8;'06_MODELO_REFS'!H$26:H$3837;0)
A9: =INDEX('06_MODELO_REFS'!A$26:A$3837;$I9) | B9: =INDEX('06_MODELO_REFS'!B$26:B$3837;$I9) | C9: =INDEX('06_MODELO_REFS'!C$26:C$3837;$I9) | D9: =INDEX('06_MODELO_REFS'!D$26:D$3837;$I9) | E9: =INDEX('06_MODELO_REFS'!E$26:E$3837;$I9) | F9: =INDEX('06_MODELO_REFS'!F$26:F$3837;$I9) | G9: =INDEX('06_MODELO_REFS'!G$26:G$3837;$I9) | H9: =LARGE('06_MODELO_REFS'!H$26:H$3837;2) | I9: =MATCH(H9;'06_MODELO_REFS'!H$26:H$3837;0)
A10: =INDEX('06_MODELO_REFS'!A$26:A$3837;$I10) | B10: =INDEX('06_MODELO_REFS'!B$26:B$3837;$I10) | C10: =INDEX('06_MODELO_REFS'!C$26:C$3837;$I10) | D10: =INDEX('06_MODELO_REFS'!D$26:D$3837;$I10) | E10: =INDEX('06_MODELO_REFS'!E$26:E$3837;$I10) | F10: =INDEX('06_MODELO_REFS'!F$26:F$3837;$I10) | G10: =INDEX('06_MODELO_REFS'!G$26:G$3837;$I10) | H10: =LARGE('06_MODELO_REFS'!H$26:H$3837;3) | I10: =MATCH(H10;'06_MODELO_REFS'!H$26:H$3837;0)
A11: =INDEX('06_MODELO_REFS'!A$26:A$3837;$I11) | B11: =INDEX('06_MODELO_REFS'!B$26:B$3837;$I11) | C11: =INDEX('06_MODELO_REFS'!C$26:C$3837;$I11) | D11: =INDEX('06_MODELO_REFS'!D$26:D$3837;$I11) | E11: =INDEX('06_MODELO_REFS'!E$26:E$3837;$I11) | F11: =INDEX('06_MODELO_REFS'!F$26:F$3837;$I11) | G11: =INDEX('06_MODELO_REFS'!G$26:G$3837;$I11) | H11: =LARGE('06_MODELO_REFS'!H$26:H$3837;4) | I11: =MATCH(H11;'06_MODELO_REFS'!H$26:H$3837;0)
A12: =INDEX('06_MODELO_REFS'!A$26:A$3837;$I12) | B12: =INDEX('06_MODELO_REFS'!B$26:B$3837;$I12) | C12: =INDEX('06_MODELO_REFS'!C$26:C$3837;$I12) | D12: =INDEX('06_MODELO_REFS'!D$26:D$3837;$I12) | E12: =INDEX('06_MODELO_REFS'!E$26:E$3837;$I12) | F12: =INDEX('06_MODELO_REFS'!F$26:F$3837;$I12) | G12: =INDEX('06_MODELO_REFS'!G$26:G$3837;$I12) | H12: =LARGE('06_MODELO_REFS'!H$26:H$3837;5) | I12: =MATCH(H12;'06_MODELO_REFS'!H$26:H$3837;0)
A13: =INDEX('06_MODELO_REFS'!A$26:A$3837;$I13) | B13: =INDEX('06_MODELO_REFS'!B$26:B$3837;$I13) | C13: =INDEX('06_MODELO_REFS'!C$26:C$3837;$I13) | D13: =INDEX('06_MODELO_REFS'!D$26:D$3837;$I13) | E13: =INDEX('06_MODELO_REFS'!E$26:E$3837;$I13) | F13: =INDEX('06_MODELO_REFS'!F$26:F$3837;$I13) | G13: =INDEX('06_MODELO_REFS'!G$26:G$3837;$I13) | H13: =LARGE('06_MODELO_REFS'!H$26:H$3837;6) | I13: =MATCH(H13;'06_MODELO_REFS'!H$26:H$3837;0)
A14: =INDEX('06_MODELO_REFS'!A$26:A$3837;$I14) | B14: =INDEX('06_MODELO_REFS'!B$26:B$3837;$I14) | C14: =INDEX('06_MODELO_REFS'!C$26:C$3837;$I14) | D14: =INDEX('06_MODELO_REFS'!D$26:D$3837;$I14) | E14: =INDEX('06_MODELO_REFS'!E$26:E$3837;$I14) | F14: =INDEX('06_MODELO_REFS'!F$26:F$3837;$I14) | G14: =INDEX('06_MODELO_REFS'!G$26:G$3837;$I14) | H14: =LARGE('06_MODELO_REFS'!H$26:H$3837;7) | I14: =MATCH(H14;'06_MODELO_REFS'!H$26:H$3837;0)
A15: =INDEX('06_MODELO_REFS'!A$26:A$3837;$I15) | B15: =INDEX('06_MODELO_REFS'!B$26:B$3837;$I15) | C15: =INDEX('06_MODELO_REFS'!C$26:C$3837;$I15) | D15: =INDEX('06_MODELO_REFS'!D$26:D$3837;$I15) | E15: =INDEX('06_MODELO_REFS'!E$26:E$3837;$I15) | F15: =INDEX('06_MODELO_REFS'!F$26:F$3837;$I15) | G15: =INDEX('06_MODELO_REFS'!G$26:G$3837;$I15) | H15: =LARGE('06_MODELO_REFS'!H$26:H$3837;8) | I15: =MATCH(H15;'06_MODELO_REFS'!H$26:H$3837;0)
A16: =INDEX('06_MODELO_REFS'!A$26:A$3837;$I16) | B16: =INDEX('06_MODELO_REFS'!B$26:B$3837;$I16) | C16: =INDEX('06_MODELO_REFS'!C$26:C$3837;$I16) | D16: =INDEX('06_MODELO_REFS'!D$26:D$3837;$I16) | E16: =INDEX('06_MODELO_REFS'!E$26:E$3837;$I16) | F16: =INDEX('06_MODELO_REFS'!F$26:F$3837;$I16) | G16: =INDEX('06_MODELO_REFS'!G$26:G$3837;$I16) | H16: =LARGE('06_MODELO_REFS'!H$26:H$3837;9) | I16: =MATCH(H16;'06_MODELO_REFS'!H$26:H$3837;0)
A17: =INDEX('06_MODELO_REFS'!A$26:A$3837;$I17) | B17: =INDEX('06_MODELO_REFS'!B$26:B$3837;$I17) | C17: =INDEX('06_MODELO_REFS'!C$26:C$3837;$I17) | D17: =INDEX('06_MODELO_REFS'!D$26:D$3837;$I17) | E17: =INDEX('06_MODELO_REFS'!E$26:E$3837;$I17) | F17: =INDEX('06_MODELO_REFS'!F$26:F$3837;$I17) | G17: =INDEX('06_MODELO_REFS'!G$26:G$3837;$I17) | H17: =LARGE('06_MODELO_REFS'!H$26:H$3837;10) | I17: =MATCH(H17;'06_MODELO_REFS'!H$26:H$3837;0)
A21: Interpretação
A22: Observações atípicas são diagnósticas e não devem ser removidas automaticamente.

Sheet 12_RESULTADOS_FINAIS
A1: Pergunta de pesquisa: entre escolas fundamentais da Califórnia, como condições socioeducacionais se associam ao API00?
A2: Recorte analítico: escolas com TIPO = Fundamental.
A3: Modelo principal: API00 ~ REFS.
A4: Modelo complementar: API00 ~ NPI.
A5: Modelo múltiplo: API00 ~ REFS + NPI.
A6: REFS tem associação negativa forte com API00 e maior capacidade explicativa isolada do que NPI.
A7: NPI também tem associação negativa com API00.
A8: No modelo múltiplo, NPI contribui, mas com efeito parcial menor do que no modelo simples.
A9: Todos os coeficientes principais têm valor-p <0,001 e IC95 abaixo de zero.
A10: Os gráficos de dispersão com ajuste por MQ apoiam visualmente as associações negativas nos modelos simples.
A11: Os gráficos do modelo múltiplo devem ser lidos como projeções dos valores ajustados.
A12: A análise é associativa, restrita à base analisada e não autoriza interpretação causal.
