Workbook

Sheet Página1
B2: Fundamentos de Estatística - Conceitos e Aplicações
B3: Bem-vindo à seção Fundamentos de Estatística - Conceitos e Aplicações. Nesta seção exploramos os fundamentos da estatística, com foco especial em estatística descritiva e estatística inferencial. Nas subseções a seguir, apresentamos a teoria estatística e fornecemos aplicações práticas no Google Planilhas. Caso você ainda não esteja familiarizado com Google Planilhas, recomenda-se primeiro acessar a página de suporte do programa.
B5: Treinamento e ajuda do Planilhas Google
B6: O Google Planilhas é um programa de planilhas baseado na nuvem que faz parte do pacote gratuito do Google. Ele permite criar, editar e formatar tabelas diretamente no seu navegador ou aplicativo móvel, sem a necessidade de instalar softwares como o Excel.
B8: Pilares do Google Planilha
B9: Colaboração em Tempo Real: Diversas pessoas podem editar o mesmo arquivo simultaneamente. Você vê quem está alterando cada célula e pode conversar via chat ou comentários dentro do documento.
B10: Armazenamento na Nuvem: Todos os arquivos são salvos automaticamente no Google Drive. Isso significa que você pode acessar seus dados de qualquer dispositivo com internet e nunca perde o trabalho por esquecer de salvar.
B11: Gratuidade e Acessibilidade: Para uso pessoal, a ferramenta é totalmente gratuita. Basta ter uma conta Google (@gmail.com).
B13: Primeiros Passos
B14: Folha de referência do Planilhas
B15: Guias de produtividade do Planilhas
B16: Solução de problemas e mais recursos do Planilhas
... B22: O XLMiner Analysis ToolPak é o principal complemento (add-on) para o Google Planilhas que permite realizar análises estatísticas complexas, funcionando como um substituto direto para a ferramenta "Análise de Dados" do Excel de desktop.
B23: Link: | C23: XLMiner Analysis ToolPak
B25: Como funcionam no ecossistema Google
B26: Os complementos permitem que você personalize sua ferramenta de trabalho. Eles estendem o poder da planilha para tarefas específicas.
B27: Instalação: São encontrados no Google Workspace Marketplace.
B28: Integração: Após instalados, eles aparecem no menu Extensões.
B29: Foco: Geralmente resolvem problemas de nicho, como automação de e-mails, criação de gráficos avançados ou, no caso do XLMiner, análises estatísticas complexas.
B31: Citação
B32: Estas aulas são baseadas no projeto de e-learning SOGA-Py que foi desenvolvido no Departamento de Ciências da Terra por Annette Rudolph, Joachim Krois e Kai Hartmann. O contato pode ser realizado por e-mail, pelo endereço soga[at]zedat.fu-berlin.de.
B34: Você pode utilizar este projeto livremente sob a Licença Creative Commons Atribuição-CompartilhaIgual 4.0 Internacional.
B35: Por favor, cite da seguinte forma: Rudolph, A., Krois, J., Hartmann, K. (2023): Estatística e Análise de Geodados usando Python (SOGA-Py). Departamento de Ciências da Terra, Universidade Livre de Berlim.

Sheet dados
A1: Mês | B1: Precipitação | C1: Temperatura | D1: Vento | E1: Vendas | F1: Feminino | G1: Classe Pluv. | H1: Índice Vendas | I1: Classe Vendas | J1: Tipo Falha | K1: Qtde Falhas | L1: Taxa | M1: Fator | N1: Custo Mensal | O1: Peso | P1: Fator Ponderado | Q1: xi^wi | R1: und. vend. ord. | S1: Mediana | T1: Média | U1: und. vend. ord. 2024 | V1: Mediana 2024 | W1: Média 2024
A2: 45078 | B2: 58 | C2: 26 | D2: 14 | E2: 1861 | F2: =0.6 + 0.1 * ((B2 - AVERAGE($B$2:$B$32)) / STDEVA($B$2:$B$32)) -> 0.50931694 | G2: =IF(B2/AVERAGE($B$2:$B$32)<0.75,"Seco",IF(B2/AVERAGE($B$2:$B$32)<1.25,"Normal","Chuvoso")) -> Seco | H2: =E2/AVERAGE($E$2:$E$32) -> 0.5988768 | I2: =IF(H2<0.75,"Baixa", IF(H2<1.25,"Normal", "Alta")) -> Baixa | J2: Costura | K2: =ROUNDUP( 1+3*(E2/AVERAGE($E$2:$E$32))+2*(B2/AVERAGE($B$2:$B$32)),0) -> 5 | L2: =IF(ISNUMBER(E1),(E2/E1)-1,"") | M2: =IF(ISNUMBER(E1),E2/E1,"") | N2: =$C$38/E2 -> 1.6120365 | O2: =IF(B2>MEDIAN($B$2:$B$20),2,1) -> 1 | P2: =IF($M$2="","",M2^O2) | Q2: =IF(M2="","",M2^O2) | R2: {=SORT(E2:E32)} -> 1745 | S2: =MEDIAN(E2:E32) -> 2771 | T2: =AVERAGE(E2:E20) -> 3079.0526 | U2: {=SORT(E9:E20)} -> 1979 | V2: =MEDIAN(E9:E20) -> 2642.5 | W2: =AVERAGE(E9:E20) -> 3051.6667
A3: =A2+31 -> 45109 | B3: 49 | C3: 28 | D3: 12 | E3: 1745 | F3: =0.6 + 0.1 * ((B3 - AVERAGE($B$2:$B$32)) / STDEVA($B$2:$B$32)) -> 0.46959862 | G3: =IF(B3/AVERAGE($B$2:$B$32)<0.75,"Seco",IF(B3/AVERAGE($B$2:$B$32)<1.25,"Normal","Chuvoso")) -> Seco | H3: =E3/AVERAGE($E$2:$E$32) -> 0.56154756 | I3: =IF(H3<0.75,"Baixa", IF(H3<1.25,"Normal", "Alta")) -> Baixa | J3: Costura | K3: =ROUNDUP(1+3*(E3/AVERAGE($E$2:$E$32))+2*(B3/AVERAGE($B$2:$B$32)),0) -> 4 | L3: =IF(ISNUMBER(E2),(E3/E2)-1,"") -> -0.06233208 | M3: =IF(ISNUMBER(E2),E3/E2,"") -> 0.93766792 | N3: =$C$38/E3 -> 1.7191977 | O3: =IF(B3>MEDIAN($B$2:$B$20),2,1) -> 1 | P3: =IF(M3="","",M3^O3) -> 0.93766792 | Q3: =IF(M3="","",M3^O3) -> 0.93766792 | R3: 1861 | S3: =$S$2 -> 2771 | T3: =$T$2 -> 3079.0526 | U3: 2097 | V3: =$V$2 -> 2642.5 | W3: =$W$2 -> 3051.6667
A4: =A3+31 -> 45140 | B4: 62 | C4: 29 | D4: 12 | E4: 1977 | F4: =0.6 + 0.1 * ((B4 - AVERAGE($B$2:$B$32)) / STDEVA($B$2:$B$32)) -> 0.52696953 | G4: =IF(B4/AVERAGE($B$2:$B$32)<0.75,"Seco",IF(B4/AVERAGE($B$2:$B$32)<1.25,"Normal","Chuvoso")) -> Normal | H4: =E4/AVERAGE($E$2:$E$32) -> 0.63620604 | I4: =IF(H4<0.75,"Baixa", IF(H4<1.25,"Normal", "Alta")) -> Baixa | J4: Montagem | K4: =ROUNDUP( 1+3*(E4/AVERAGE($E$2:$E$32))+2*(B4/AVERAGE($B$2:$B$32)),0) -> 5 | L4: =IF(ISNUMBER(E3),(E4/E3)-1,"") -> 0.13295129 | M4: =IF(ISNUMBER(E3),E4/E3,"") -> 1.1329513 | N4: =$C$38/E4 -> 1.5174507 | O4: =IF(B4>MEDIAN($B$2:$B$20),2,1) -> 1 | P4: =IF(M4="","",M4^O4) -> 1.1329513 | Q4: =IF(M4="","",M4^O4) -> 1.1329513 | R4: 1920 | S4: =$S$2 -> 2771 | T4: =$T$2 -> 3079.0526 | U4: 2205 | V4: =$V$2 -> 2642.5 | W4: =$W$2 -> 3051.6667
A5: =A4+31 -> 45171 | B5: 100 | C5: 18 | D5: 14 | E5: 3908 | F5: =0.6 + 0.1 * ((B5 - AVERAGE($B$2:$B$32)) / STDEVA($B$2:$B$32)) -> 0.69466913 | G5: =IF(B5/AVERAGE($B$2:$B$32)<0.75,"Seco",IF(B5/AVERAGE($B$2:$B$32)<1.25,"Normal","Chuvoso")) -> Chuvoso | H5: =E5/AVERAGE($E$2:$E$32) -> 1.2576091 | I5: =IF(H5<0.75,"Baixa", IF(H5<1.25,"Normal", "Alta")) -> Alta | J5: Varetas | K5: =ROUNDUP( 1+3*(E5/AVERAGE($E$2:$E$32))+2*(B5/AVERAGE($B$2:$B$32)),0) -> 8 | L5: =IF(ISNUMBER(E4),(E5/E4)-1,"") -> 0.97673242 | M5: =IF(ISNUMBER(E4),E5/E4,"") -> 1.9767324 | N5: =$C$38/E5 -> 0.76765609 | O5: =IF(B5>MEDIAN($B$2:$B$20),2,1) -> 2 | P5: =IF(M5="","",M5^O5) -> 3.9074711 | Q5: =IF(M5="","",M5^O5) -> 3.9074711 | R5: 1977 | S5: =$S$2 -> 2771 | T5: =$T$2 -> 3079.0526 | U5: 2254 | V5: =$V$2 -> 2642.5 | W5: =$W$2 -> 3051.6667
A6: =A5+31 -> 45202 | B6: 110 | C6: 14 | D6: 15 | E6: 5325 | F6: =0.6 + 0.1 * ((B6 - AVERAGE($B$2:$B$32)) / STDEVA($B$2:$B$32)) -> 0.7388006 | G6: =IF(B6/AVERAGE($B$2:$B$32)<0.75,"Seco",IF(B6/AVERAGE($B$2:$B$32)<1.25,"Normal","Chuvoso")) -> Chuvoso | H6: =E6/AVERAGE($E$2:$E$32) -> 1.713605 | I6: =IF(H6<0.75,"Baixa", IF(H6<1.25,"Normal", "Alta")) -> Alta | J6: Varetas | K6: =ROUNDUP( 1+3*(E6/AVERAGE($E$2:$E$32))+2*(B6/AVERAGE($B$2:$B$32)),0) -> 9 | L6: =IF(ISNUMBER(E5),(E6/E5)-1,"") -> 0.36258956 | M6: =IF(ISNUMBER(E5),E6/E5,"") -> 1.3625896 | N6: =$C$38/E6 -> 0.56338028 | O6: =IF(B6>MEDIAN($B$2:$B$20),2,1) -> 2 | P6: =IF(M6="","",M6^O6) -> 1.8566503 | Q6: =IF(M6="","",M6^O6) -> 1.8566503 | R6: 1979 | S6: =$S$2 -> 2771 | T6: =$T$2 -> 3079.0526 | U6: 2358 | V6: =$V$2 -> 2642.5 | W6: =$W$2 -> 3051.6667
A7: =A6+31 -> 45233 | B7: 102 | C7: 13 | D7: 17 | E7: 4098 | F7: =0.6 + 0.1 * ((B7 - AVERAGE($B$2:$B$32)) / STDEVA($B$2:$B$32)) -> 0.70349542 | G7: =IF(B7/AVERAGE($B$2:$B$32)<0.75,"Seco",IF(B7/AVERAGE($B$2:$B$32)<1.25,"Normal","Chuvoso")) -> Chuvoso | H7: =E7/AVERAGE($E$2:$E$32) -> 1.3187518 | I7: =IF(H7<0.75,"Baixa", IF(H7<1.25,"Normal", "Alta")) -> Alta | J7: Tecido | K7: =ROUNDUP( 1+3*(E7/AVERAGE($E$2:$E$32))+2*(B7/AVERAGE($B$2:$B$32)),0) -> 8 | L7: =IF(ISNUMBER(E6),(E7/E6)-1,"") -> -0.23042254 | M7: =IF(ISNUMBER(E6),E7/E6,"") -> 0.76957746 | N7: =$C$38/E7 -> 0.73206442 | O7: =IF(B7>MEDIAN($B$2:$B$20),2,1) -> 2 | P7: =IF(M7="","",M7^O7) -> 0.59224947 | Q7: =IF(M7="","",M7^O7) -> 0.59224947 | R7: 2097 | S7: =$S$2 -> 2771 | T7: =$T$2 -> 3079.0526 | U7: 2514 | V7: =$V$2 -> 2642.5 | W7: =$W$2 -> 3051.6667
A8: =A7+31 -> 45264 | B8: 84 | C8: 10 | D8: 18 | E8: 2968 | F8: =0.6 + 0.1 * ((B8 - AVERAGE($B$2:$B$32)) / STDEVA($B$2:$B$32)) -> 0.62405877 | G8: =IF(B8/AVERAGE($B$2:$B$32)<0.75,"Seco",IF(B8/AVERAGE($B$2:$B$32)<1.25,"Normal","Chuvoso")) -> Normal | H8: =E8/AVERAGE($E$2:$E$32) -> 0.95511357 | I8: =IF(H8<0.75,"Baixa", IF(H8<1.25,"Normal", "Alta")) -> Normal | J8: Montagem | K8: =ROUNDUP( 1+3*(E8/AVERAGE($E$2:$E$32))+2*(B8/AVERAGE($B$2:$B$32)),0) -> 7 | L8: =IF(ISNUMBER(E7),(E8/E7)-1,"") -> -0.27574427 | M8: =IF(ISNUMBER(E7),E8/E7,"") -> 0.72425573 | N8: =$C$38/E8 -> 1.0107817 | O8: =IF(B8>MEDIAN($B$2:$B$20),2,1) -> 2 | P8: =IF(M8="","",M8^O8) -> 0.52454637 | Q8: =IF(M8="","",M8^O8) -> 0.52454637 | R8: 2180 | S8: =$S$2 -> 2771 | T8: =$T$2 -> 3079.0526 | U8: 2771 | V8: =$V$2 -> 2642.5 | W8: =$W$2 -> 3051.6667
A9: =A8+31 -> 45295 | B9: 79 | C9: 4 | D9: 19 | E9: 2771 | F9: =0.6 + 0.1 * ((B9 - AVERAGE($B$2:$B$32)) / STDEVA($B$2:$B$32)) -> 0.60199303 | G9: =IF(B9/AVERAGE($B$2:$B$32)<0.75,"Seco",IF(B9/AVERAGE($B$2:$B$32)<1.25,"Normal","Chuvoso")) -> Normal | H9: =E9/AVERAGE($E$2:$E$32) -> 0.89171822 | I9: =IF(H9<0.75,"Baixa", IF(H9<1.25,"Normal", "Alta")) -> Normal | J9: Costura | K9: =ROUNDUP( 1+3*(E9/AVERAGE($E$2:$E$32))+2*(B9/AVERAGE($B$2:$B$32)),0) -> 6 | L9: =IF(ISNUMBER(E8),(E9/E8)-1,"") -> -0.066374663 | M9: =IF(ISNUMBER(E8),E9/E8,"") -> 0.93362534 | N9: =$C$38/E9 -> 1.0826416 | O9: =IF(B9>MEDIAN($B$2:$B$20),2,1) -> 1 | P9: =IF(M9="","",M9^O9) -> 0.93362534 | Q9: =IF(M9="","",M9^O9) -> 0.93362534 | R9: 2205 | S9: =$S$2 -> 2771 | T9: =$T$2 -> 3079.0526 | U9: 2978 | V9: =$V$2 -> 2642.5 | W9: =$W$2 -> 3051.6667
A10: =A9+31 -> 45326 | B10: 74 | C10: 3 | D10: 30 | E10: 2097 | F10: =0.6 + 0.1 * ((B10 - AVERAGE($B$2:$B$32)) / STDEVA($B$2:$B$32)) -> 0.5799273 | G10: =IF(B10/AVERAGE($B$2:$B$32)<0.75,"Seco",IF(B10/AVERAGE($B$2:$B$32)<1.25,"Normal","Chuvoso")) -> Normal | H10: =E10/AVERAGE($E$2:$E$32) -> 0.67482249 | I10: =IF(H10<0.75,"Baixa", IF(H10<1.25,"Normal", "Alta")) -> Baixa | J10: Varetas | K10: =ROUNDUP( 1+3*(E10/AVERAGE($E$2:$E$32))+2*(B10/AVERAGE($B$2:$B$32)),0) -> 5 | L10: =IF(ISNUMBER(E9),(E10/E9)-1,"") -> -0.24323349 | M10: =IF(ISNUMBER(E9),E10/E9,"") -> 0.75676651 | N10: =$C$38/E10 -> 1.4306152 | O10: =IF(B10>MEDIAN($B$2:$B$20),2,1) -> 1 | P10: =IF(M10="","",M10^O10) -> 0.75676651 | Q10: =IF(M10="","",M10^O10) -> 0.75676651 | R10: 2254 | S10: =$S$2 -> 2771 | T10: =$T$2 -> 3079.0526 | U10: 3490 | V10: =$V$2 -> 2642.5 | W10: =$W$2 -> 3051.6667
A11: =A10+31 -> 45357 | B11: 80 | C11: 6 | D11: 28 | E11: 2254 | F11: =0.6 + 0.1 * ((B11 - AVERAGE($B$2:$B$32)) / STDEVA($B$2:$B$32)) -> 0.60640618 | G11: =IF(B11/AVERAGE($B$2:$B$32)<0.75,"Seco",IF(B11/AVERAGE($B$2:$B$32)<1.25,"Normal","Chuvoso")) -> Normal | H11: =E11/AVERAGE($E$2:$E$32) -> 0.72534568 | I11: =IF(H11<0.75,"Baixa", IF(H11<1.25,"Normal", "Alta")) -> Baixa | J11: Montagem | K11: =ROUNDUP( 1+3*(E11/AVERAGE($E$2:$E$32))+2*(B11/AVERAGE($B$2:$B$32)),0) -> 6 | L11: =IF(ISNUMBER(E10),(E11/E10)-1,"") -> 0.07486886 | M11: =IF(ISNUMBER(E10),E11/E10,"") -> 1.0748689 | N11: =$C$38/E11 -> 1.3309672 | O11: =IF(B11>MEDIAN($B$2:$B$20),2,1) -> 1 | P11: =IF(M11="","",M11^O11) -> 1.0748689 | Q11: =IF(M11="","",M11^O11) -> 1.0748689 | R11: 2260 | S11: =$S$2 -> 2771 | T11: =$T$2 -> 3079.0526 | U11: 3499 | V11: =$V$2 -> 2642.5 | W11: =$W$2 -> 3051.6667
A12: =A11+31 -> 45388 | B12: 87 | C12: 12 | D12: 18 | E12: 2978 | F12: =0.6 + 0.1 * ((B12 - AVERAGE($B$2:$B$32)) / STDEVA($B$2:$B$32)) -> 0.63729821 | G12: =IF(B12/AVERAGE($B$2:$B$32)<0.75,"Seco",IF(B12/AVERAGE($B$2:$B$32)<1.25,"Normal","Chuvoso")) -> Normal | H12: =E12/AVERAGE($E$2:$E$32) -> 0.9583316 | I12: =IF(H12<0.75,"Baixa", IF(H12<1.25,"Normal", "Alta")) -> Normal | J12: Tecido | K12: =ROUNDUP( 1+3*(E12/AVERAGE($E$2:$E$32))+2*(B12/AVERAGE($B$2:$B$32)),0) -> 7 | L12: =IF(ISNUMBER(E11),(E12/E11)-1,"") -> 0.32120674 | M12: =IF(ISNUMBER(E11),E12/E11,"") -> 1.3212067 | N12: =$C$38/E12 -> 1.0073875 | O12: =IF(B12>MEDIAN($B$2:$B$20),2,1) -> 2 | P12: =IF(M12="","",M12^O12) -> 1.7455873 | Q12: =IF(M12="","",M12^O12) -> 1.7455873 | R12: 2320 | S12: =$S$2 -> 2771 | T12: =$T$2 -> 3079.0526 | U12: 4920 | V12: =$V$2 -> 2642.5 | W12: =$W$2 -> 3051.6667
A13: =A12+31 -> 45419 | B13: 58 | C13: 19 | D13: 14 | E13: 2514 | F13: =0.6 + 0.1 * ((B13 - AVERAGE($B$2:$B$32)) / STDEVA($B$2:$B$32)) -> 0.50931694 | G13: =IF(B13/AVERAGE($B$2:$B$32)<0.75,"Seco",IF(B13/AVERAGE($B$2:$B$32)<1.25,"Normal","Chuvoso")) -> Seco | H13: =E13/AVERAGE($E$2:$E$32) -> 0.80901466 | I13: =IF(H13<0.75,"Baixa", IF(H13<1.25,"Normal", "Alta")) -> Normal | J13: Costura | K13: =ROUNDUP( 1+3*(E13/AVERAGE($E$2:$E$32))+2*(B13/AVERAGE($B$2:$B$32)),0) -> 5 | L13: =IF(ISNUMBER(E12),(E13/E12)-1,"") -> -0.15580927 | M13: =IF(ISNUMBER(E12),E13/E12,"") -> 0.84419073 | N13: =$C$38/E13 -> 1.1933174 | O13: =IF(B13>MEDIAN($B$2:$B$20),2,1) -> 1 | P13: =IF(M13="","",M13^O13) -> 0.84419073 | Q13: =IF(M13="","",M13^O13) -> 0.84419073 | R13: 2358 | S13: =$S$2 -> 2771 | T13: =$T$2 -> 3079.0526 | U13: 5555 | V13: =$V$2 -> 2642.5 | W13: =$W$2 -> 3051.6667
A14: =A13+31 -> 45450 | B14: 54 | C14: 26 | D14: 13 | E14: 2205 | F14: =0.6 + 0.1 * ((B14 - AVERAGE($B$2:$B$32)) / STDEVA($B$2:$B$32)) -> 0.49166435 | G14: =IF(B14/AVERAGE($B$2:$B$32)<0.75,"Seco",IF(B14/AVERAGE($B$2:$B$32)<1.25,"Normal","Chuvoso")) -> Seco | H14: =E14/AVERAGE($E$2:$E$32) -> 0.7095773 | I14: =IF(H14<0.75,"Baixa", IF(H14<1.25,"Normal", "Alta")) -> Baixa | J14: Costura | K14: =ROUNDUP( 1+3*(E14/AVERAGE($E$2:$E$32))+2*(B14/AVERAGE($B$2:$B$32)),0) -> 5 | L14: =IF(ISNUMBER(E13),(E14/E13)-1,"") -> -0.12291169 | M14: =IF(ISNUMBER(E13),E14/E13,"") -> 0.87708831 | N14: =$C$38/E14 -> 1.3605442 | O14: =IF(B14>MEDIAN($B$2:$B$20),2,1) -> 1 | P14: =IF(M14="","",M14^O14) -> 0.87708831 | Q14: =IF(M14="","",M14^O14) -> 0.87708831 | R14: 2410 | S14: =$S$2 -> 2771 | T14: =$T$2 -> 3079.0526
A15: =A14+31 -> 45481 | B15: 42 | C15: 30 | D15: 13 | E15: 1979 | F15: =0.6 + 0.1 * ((B15 - AVERAGE($B$2:$B$32)) / STDEVA($B$2:$B$32)) -> 0.43870659 | G15: =IF(B15/AVERAGE($B$2:$B$32)<0.75,"Seco",IF(B15/AVERAGE($B$2:$B$32)<1.25,"Normal","Chuvoso")) -> Seco | H15: =E15/AVERAGE($E$2:$E$32) -> 0.63684964 | I15: =IF(H15<0.75,"Baixa", IF(H15<1.25,"Normal", "Alta")) -> Baixa | J15: Montagem | K15: =ROUNDUP( 1+3*(E15/AVERAGE($E$2:$E$32))+2*(B15/AVERAGE($B$2:$B$32)),0) -> 4 | L15: =IF(ISNUMBER(E14),(E15/E14)-1,"") -> -0.10249433 | M15: =IF(ISNUMBER(E14),E15/E14,"") -> 0.89750567 | N15: =$C$38/E15 -> 1.5159171 | O15: =IF(B15>MEDIAN($B$2:$B$20),2,1) -> 1 | P15: =IF(M15="","",M15^O15) -> 0.89750567 | Q15: =IF(M15="","",M15^O15) -> 0.89750567 | R15: 2514 | S15: =$S$2 -> 2771 | T15: =$T$2 -> 3079.0526
A16: =A15+31 -> 45512 | B16: 49 | C16: 31 | D16: 10 | E16: 2358 | F16: =0.6 + 0.1 * ((B16 - AVERAGE($B$2:$B$32)) / STDEVA($B$2:$B$32)) -> 0.46959862 | G16: =IF(B16/AVERAGE($B$2:$B$32)<0.75,"Seco",IF(B16/AVERAGE($B$2:$B$32)<1.25,"Normal","Chuvoso")) -> Seco | H16: =E16/AVERAGE($E$2:$E$32) -> 0.75881327 | I16: =IF(H16<0.75,"Baixa", IF(H16<1.25,"Normal", "Alta")) -> Normal | J16: Montagem | K16: =ROUNDUP( 1+3*(E16/AVERAGE($E$2:$E$32))+2*(B16/AVERAGE($B$2:$B$32)),0) -> 5 | L16: =IF(ISNUMBER(E15),(E16/E15)-1,"") -> 0.19151086 | M16: =IF(ISNUMBER(E15),E16/E15,"") -> 1.1915109 | N16: =$C$38/E16 -> 1.2722646 | O16: =IF(B16>MEDIAN($B$2:$B$20),2,1) -> 1 | P16: =IF(M16="","",M16^O16) -> 1.1915109 | Q16: =IF(M16="","",M16^O16) -> 1.1915109 | R16: 2600 | S16: =$S$2 -> 2771 | T16: =$T$2 -> 3079.0526 | AB16: Dados | AC16: Desvios | AD16: Desv. Pos. | AE16: Desv. Neg.
A17: =A16+31 -> 45543 | B17: 84 | C17: 19 | D17: 14 | E17: 3490 | F17: =0.6 + 0.1 * ((B17 - AVERAGE($B$2:$B$32)) / STDEVA($B$2:$B$32)) -> 0.62405877 | G17: =IF(B17/AVERAGE($B$2:$B$32)<0.75,"Seco",IF(B17/AVERAGE($B$2:$B$32)<1.25,"Normal","Chuvoso")) -> Normal | H17: =E17/AVERAGE($E$2:$E$32) -> 1.1230951 | I17: =IF(H17<0.75,"Baixa", IF(H17<1.25,"Normal", "Alta")) -> Normal | J17: Varetas | K17: =ROUNDUP( 1+3*(E17/AVERAGE($E$2:$E$32))+2*(B17/AVERAGE($B$2:$B$32)),0) -> 7 | L17: =IF(ISNUMBER(E16),(E17/E16)-1,"") -> 0.48006785 | M17: =IF(ISNUMBER(E16),E17/E16,"") -> 1.4800679 | N17: =$C$38/E17 -> 0.85959885 | O17: =IF(B17>MEDIAN($B$2:$B$20),2,1) -> 2 | P17: =IF(M17="","",M17^O17) -> 2.1906009 | Q17: =IF(M17="","",M17^O17) -> 2.1906009 | R17: 2771 | S17: =$S$2 -> 2771 | T17: =$T$2 -> 3079.0526 | AB17: =B2 -> 58 | AC17: =AB17-$AC$48 -> -20.548387 | AD17: =IF(AC17>=0,AC17,0) -> 0 | AE17: =IF(AC17<0,AC17,0) -> -20.548387
A18: =A17+31 -> 45574 | B18: 107 | C18: 15 | D18: 18 | E18: 4920 | F18: =0.6 + 0.1 * ((B18 - AVERAGE($B$2:$B$32)) / STDEVA($B$2:$B$32)) -> 0.72556116 | G18: =IF(B18/AVERAGE($B$2:$B$32)<0.75,"Seco",IF(B18/AVERAGE($B$2:$B$32)<1.25,"Normal","Chuvoso")) -> Chuvoso | H18: =E18/AVERAGE($E$2:$E$32) -> 1.5832745 | I18: =IF(H18<0.75,"Baixa", IF(H18<1.25,"Normal", "Alta")) -> Alta | J18: Varetas | K18: =ROUNDUP( 1+3*(E18/AVERAGE($E$2:$E$32))+2*(B18/AVERAGE($B$2:$B$32)),0) -> 9 | L18: =IF(ISNUMBER(E17),(E18/E17)-1,"") -> 0.40974212 | M18: =IF(ISNUMBER(E17),E18/E17,"") -> 1.4097421 | N18: =$C$38/E18 -> 0.6097561 | O18: =IF(B18>MEDIAN($B$2:$B$20),2,1) -> 2 | P18: =IF(M18="","",M18^O18) -> 1.9873728 | Q18: =IF(M18="","",M18^O18) -> 1.9873728 | R18: 2890 | S18: =$S$2 -> 2771 | T18: =$T$2 -> 3079.0526 | AB18: =B3 -> 49 | AC18: =AB18-$AC$48 -> -29.548387 | AD18: =IF(AC18>=0,AC18,0) -> 0 | AE18: =IF(AC18<0,AC18,0) -> -29.548387
A19: =A18+31 -> 45605 | B19: 118 | C19: 13 | D19: 19 | E19: 5555 | F19: =0.6 + 0.1 * ((B19 - AVERAGE($B$2:$B$32)) / STDEVA($B$2:$B$32)) -> 0.77410578 | G19: =IF(B19/AVERAGE($B$2:$B$32)<0.75,"Seco",IF(B19/AVERAGE($B$2:$B$32)<1.25,"Normal","Chuvoso")) -> Chuvoso | H19: =E19/AVERAGE($E$2:$E$32) -> 1.7876199 | I19: =IF(H19<0.75,"Baixa", IF(H19<1.25,"Normal", "Alta")) -> Alta | J19: Tecido | K19: =ROUNDUP( 1+3*(E19/AVERAGE($E$2:$E$32))+2*(B19/AVERAGE($B$2:$B$32)),0) -> 10 | L19: =IF(ISNUMBER(E18),(E19/E18)-1,"") -> 0.12906504 | M19: =IF(ISNUMBER(E18),E19/E18,"") -> 1.129065 | N19: =$C$38/E19 -> 0.54005401 | O19: =IF(B19>MEDIAN($B$2:$B$20),2,1) -> 2 | P19: =IF(M19="","",M19^O19) -> 1.2747879 | Q19: =IF(M19="","",M19^O19) -> 1.2747879 | R19: 2950 | S19: =$S$2 -> 2771 | T19: =$T$2 -> 3079.0526 | AB19: =B4 -> 62 | AC19: =AB19-$AC$48 -> -16.548387 | AD19: =IF(AC19>=0,AC19,0) -> 0 | AE19: =IF(AC19<0,AC19,0) -> -16.548387
A20: =A19+31 -> 45636 | B20: 91 | C20: 8 | D20: 19 | E20: 3499 | F20: =0.6 + 0.1 * ((B20 - AVERAGE($B$2:$B$32)) / STDEVA($B$2:$B$32)) -> 0.6549508 | G20: =IF(B20/AVERAGE($B$2:$B$32)<0.75,"Seco",IF(B20/AVERAGE($B$2:$B$32)<1.25,"Normal","Chuvoso")) -> Normal | H20: =E20/AVERAGE($E$2:$E$32) -> 1.1259914 | I20: =IF(H20<0.75,"Baixa", IF(H20<1.25,"Normal", "Alta")) -> Normal | J20: Montagem | K20: =ROUNDUP( 1+3*(E20/AVERAGE($E$2:$E$32))+2*(B20/AVERAGE($B$2:$B$32)),0) -> 7 | L20: =IF(ISNUMBER(E19),(E20/E19)-1,"") -> -0.37011701 | M20: =IF(ISNUMBER(E19),E20/E19,"") -> 0.62988299 | N20: =$C$38/E20 -> 0.85738783 | O20: =IF(B20>MEDIAN($B$2:$B$20),2,1) -> 2 | P20: =IF(M20="","",M20^O20) -> 0.39675258 | Q20: =IF(M20="","",M20^O20) -> 0.39675258 | R20: 2968 | S20: =$S$2 -> 2771 | T20: =$T$2 -> 3079.0526 | AB20: =B5 -> 100 | AC20: =AB20-$AC$48 -> 21.451613 | AD20: =IF(AC20>=0,AC20,0) -> 21.451613 | AE20: =IF(AC20<0,AC20,0) -> 0
A21: =A20+31 -> 45667 | B21: 82 | C21: 5 | D21: 18 | E21: 2890 | F21: =0.6 + 0.1 * ((B21 - AVERAGE($B$2:$B$32)) / STDEVA($B$2:$B$32)) -> 0.61523248 | G21: =IF(B21/AVERAGE($B$2:$B$32)<0.75,"Seco",IF(B21/AVERAGE($B$2:$B$32)<1.25,"Normal","Chuvoso")) -> Normal | H21: =E21/AVERAGE($E$2:$E$32) -> 0.93001287 | I21: =IF(H21<0.75,"Baixa", IF(H21<1.25,"Normal", "Alta")) -> Normal | J21: Costura | K21: =ROUNDUP( 1+3*(E21/AVERAGE($E$2:$E$32))+2*(B21/AVERAGE($B$2:$B$32)),0) -> 6 | L21: =IF(ISNUMBER(E20),(E21/E20)-1,"") -> -0.17404973 | M21: =IF(ISNUMBER(E20),E21/E20,"") -> 0.82595027 | N21: =$C$38/E21 -> 1.0380623 | O21: =IF(B21>MEDIAN($B$2:$B$20),2,1) -> 2 | P21: =IF(M21="","",M21^O21) -> 0.68219385 | Q21: =IF(M21="","",M21^O21) -> 0.68219385 | R21: 2978 | S21: =$S$2 -> 2771 | T21: =$T$2 -> 3079.0526 | AB21: =B6 -> 110 | AC21: =AB21-$AC$48 -> 31.451613 | AD21: =IF(AC21>=0,AC21,0) -> 31.451613 | AE21: =IF(AC21<0,AC21,0) -> 0
A22: =A21+31 -> 45698 | B22: 74 | C22: 4 | D22: 30 | E22: 2180 | F22: =0.6 + 0.1 * ((B22 - AVERAGE($B$2:$B$32)) / STDEVA($B$2:$B$32)) -> 0.5799273 | G22: =IF(B22/AVERAGE($B$2:$B$32)<0.75,"Seco",IF(B22/AVERAGE($B$2:$B$32)<1.25,"Normal","Chuvoso")) -> Normal | H22: =E22/AVERAGE($E$2:$E$32) -> 0.7015322 | I22: =IF(H22<0.75,"Baixa", IF(H22<1.25,"Normal", "Alta")) -> Baixa | J22: Varetas | K22: =ROUNDUP( 1+3*(E22/AVERAGE($E$2:$E$32))+2*(B22/AVERAGE($B$2:$B$32)),0) -> 5 | L22: =IF(ISNUMBER(E21),(E22/E21)-1,"") -> -0.24567474 | M22: =IF(ISNUMBER(E21),E22/E21,"") -> 0.75432526 | N22: =$C$38/E22 -> 1.3761468 | O22: =IF(B22>MEDIAN($B$2:$B$20),2,1) -> 1 | P22: =IF(M22="","",M22^O22) -> 0.75432526 | Q22: =IF(M22="","",M22^O22) -> 0.75432526 | R22: 3490 | S22: =$S$2 -> 2771 | T22: =$T$2 -> 3079.0526 | AB22: =B7 -> 102 | AC22: =AB22-$AC$48 -> 23.451613 | AD22: =IF(AC22>=0,AC22,0) -> 23.451613 | AE22: =IF(AC22<0,AC22,0) -> 0
A23: =A22+31 -> 45729 | B23: 78 | C23: 7 | D23: 16 | E23: 2320 | F23: =0.6 + 0.1 * ((B23 - AVERAGE($B$2:$B$32)) / STDEVA($B$2:$B$32)) -> 0.59757989 | G23: =IF(B23/AVERAGE($B$2:$B$32)<0.75,"Seco",IF(B23/AVERAGE($B$2:$B$32)<1.25,"Normal","Chuvoso")) -> Normal | H23: =E23/AVERAGE($E$2:$E$32) -> 0.74658473 | I23: =IF(H23<0.75,"Baixa", IF(H23<1.25,"Normal", "Alta")) -> Baixa | J23: Montagem | K23: =ROUNDUP( 1+3*(E23/AVERAGE($E$2:$E$32))+2*(B23/AVERAGE($B$2:$B$32)),0) -> 6 | L23: =IF(ISNUMBER(E22),(E23/E22)-1,"") -> 0.064220183 | M23: =IF(ISNUMBER(E22),E23/E22,"") -> 1.0642202 | N23: =$C$38/E23 -> 1.2931034 | O23: =IF(B23>MEDIAN($B$2:$B$20),2,1) -> 1 | P23: =IF(M23="","",M23^O23) -> 1.0642202 | Q23: =IF(M23="","",M23^O23) -> 1.0642202 | R23: 3499 | S23: =$S$2 -> 2771 | T23: =$T$2 -> 3079.0526 | AB23: =B8 -> 84 | AC23: =AB23-$AC$48 -> 5.4516129 | AD23: =IF(AC23>=0,AC23,0) -> 5.4516129 | AE23: =IF(AC23<0,AC23,0) -> 0
A24: =A23+31 -> 45760 | B24: 84 | C24: 11 | D24: 18 | E24: 2950 | F24: =0.6 + 0.1 * ((B24 - AVERAGE($B$2:$B$32)) / STDEVA($B$2:$B$32)) -> 0.62405877 | G24: =IF(B24/AVERAGE($B$2:$B$32)<0.75,"Seco",IF(B24/AVERAGE($B$2:$B$32)<1.25,"Normal","Chuvoso")) -> Normal | H24: =E24/AVERAGE($E$2:$E$32) -> 0.9493211 | I24: =IF(H24<0.75,"Baixa", IF(H24<1.25,"Normal", "Alta")) -> Normal | J24: Tecido | K24: =ROUNDUP( 1+3*(E24/AVERAGE($E$2:$E$32))+2*(B24/AVERAGE($B$2:$B$32)),0) -> 6 | L24: =IF(ISNUMBER(E23),(E24/E23)-1,"") -> 0.27155172 | M24: =IF(ISNUMBER(E23),E24/E23,"") -> 1.2715517 | N24: =$C$38/E24 -> 1.0169492 | O24: =IF(B24>MEDIAN($B$2:$B$20),2,1) -> 2 | P24: =IF(M24="","",M24^O24) -> 1.6168438 | Q24: =IF(M24="","",M24^O24) -> 1.6168438 | R24: 3650 | S24: =$S$2 -> 2771 | T24: =$T$2 -> 3079.0526 | AB24: =B9 -> 79 | AC24: =AB24-$AC$48 -> 0.4516129 | AD24: =IF(AC24>=0,AC24,0) -> 0.4516129 | AE24: =IF(AC24<0,AC24,0) -> 0
A25: =A24+31 -> 45791 | B25: 63 | C25: 17 | D25: 14 | E25: 2600 | F25: =0.6 + 0.1 * ((B25 - AVERAGE($B$2:$B$32)) / STDEVA($B$2:$B$32)) -> 0.53138268 | G25: =IF(B25/AVERAGE($B$2:$B$32)<0.75,"Seco",IF(B25/AVERAGE($B$2:$B$32)<1.25,"Normal","Chuvoso")) -> Normal | H25: =E25/AVERAGE($E$2:$E$32) -> 0.83668978 | I25: =IF(H25<0.75,"Baixa", IF(H25<1.25,"Normal", "Alta")) -> Normal | J25: Costura | K25: =ROUNDUP( 1+3*(E25/AVERAGE($E$2:$E$32))+2*(B25/AVERAGE($B$2:$B$32)),0) -> 6 | L25: =IF(ISNUMBER(E24),(E25/E24)-1,"") -> -0.11864407 | M25: =IF(ISNUMBER(E24),E25/E24,"") -> 0.88135593 | N25: =$C$38/E25 -> 1.1538462 | O25: =IF(B25>MEDIAN($B$2:$B$20),2,1) -> 1 | P25: =IF(M25="","",M25^O25) -> 0.88135593 | Q25: =IF(M25="","",M25^O25) -> 0.88135593 | R25: 3650 | S25: =$S$2 -> 2771 | T25: =$T$2 -> 3079.0526 | AB25: =B10 -> 74 | AC25: =AB25-$AC$48 -> -4.5483871 | AD25: =IF(AC25>=0,AC25,0) -> 0 | AE25: =IF(AC25<0,AC25,0) -> -4.5483871
A26: =A25+31 -> 45822 | B26: 56 | C26: 26 | D26: 13 | E26: 2260 | F26: =0.6 + 0.1 * ((B26 - AVERAGE($B$2:$B$32)) / STDEVA($B$2:$B$32)) -> 0.50049065 | G26: =IF(B26/AVERAGE($B$2:$B$32)<0.75,"Seco",IF(B26/AVERAGE($B$2:$B$32)<1.25,"Normal","Chuvoso")) -> Seco | H26: =E26/AVERAGE($E$2:$E$32) -> 0.7272765 | I26: =IF(H26<0.75,"Baixa", IF(H26<1.25,"Normal", "Alta")) -> Baixa | J26: Costura | K26: =ROUNDUP( 1+3*(E26/AVERAGE($E$2:$E$32))+2*(B26/AVERAGE($B$2:$B$32)),0) -> 5 | L26: =IF(ISNUMBER(E25),(E26/E25)-1,"") -> -0.13076923 | M26: =IF(ISNUMBER(E25),E26/E25,"") -> 0.86923077 | N26: =$C$38/E26 -> 1.3274336 | O26: =IF(B26>MEDIAN($B$2:$B$20),2,1) -> 1 | P26: =IF(M26="","",M26^O26) -> 0.86923077 | Q26: =IF(M26="","",M26^O26) -> 0.86923077 | R26: 3908 | S26: =$S$2 -> 2771 | T26: =$T$2 -> 3079.0526 | AB26: =B11 -> 80 | AC26: =AB26-$AC$48 -> 1.4516129 | AD26: =IF(AC26>=0,AC26,0) -> 1.4516129 | AE26: =IF(AC26<0,AC26,0) -> 0
A27: =A26+31 -> 45853 | B27: 45 | C27: 30 | D27: 12 | E27: 1920 | F27: =0.6 + 0.1 * ((B27 - AVERAGE($B$2:$B$32)) / STDEVA($B$2:$B$32)) -> 0.45194603 | G27: =IF(B27/AVERAGE($B$2:$B$32)<0.75,"Seco",IF(B27/AVERAGE($B$2:$B$32)<1.25,"Normal","Chuvoso")) -> Seco | H27: =E27/AVERAGE($E$2:$E$32) -> 0.61786322 | I27: =IF(H27<0.75,"Baixa", IF(H27<1.25,"Normal", "Alta")) -> Baixa | J27: Montagem | K27: =ROUNDUP( 1+3*(E27/AVERAGE($E$2:$E$32))+2*(B27/AVERAGE($B$2:$B$32)),0) -> 4 | L27: =IF(ISNUMBER(E26),(E27/E26)-1,"") -> -0.15044248 | M27: =IF(ISNUMBER(E26),E27/E26,"") -> 0.84955752 | N27: =$C$38/E27 -> 1.5625 | O27: =IF(B27>MEDIAN($B$2:$B$20),2,1) -> 1 | P27: =IF(M27="","",M27^O27) -> 0.84955752 | Q27: =IF(M27="","",M27^O27) -> 0.84955752 | R27: 4098 | S27: =$S$2 -> 2771 | T27: =$T$2 -> 3079.0526 | AB27: =B12 -> 87 | AC27: =AB27-$AC$48 -> 8.4516129 | AD27: =IF(AC27>=0,AC27,0) -> 8.4516129 | AE27: =IF(AC27<0,AC27,0) -> 0
A28: =A27+31 -> 45884 | B28: 50 | C28: 30 | D28: 11 | E28: 2410 | F28: =0.6 + 0.1 * ((B28 - AVERAGE($B$2:$B$32)) / STDEVA($B$2:$B$32)) -> 0.47401176 | G28: =IF(B28/AVERAGE($B$2:$B$32)<0.75,"Seco",IF(B28/AVERAGE($B$2:$B$32)<1.25,"Normal","Chuvoso")) -> Seco | H28: =E28/AVERAGE($E$2:$E$32) -> 0.77554707 | I28: =IF(H28<0.75,"Baixa", IF(H28<1.25,"Normal", "Alta")) -> Normal | J28: Montagem | K28: =ROUNDUP( 1+3*(E28/AVERAGE($E$2:$E$32))+2*(B28/AVERAGE($B$2:$B$32)),0) -> 5 | L28: =IF(ISNUMBER(E27),(E28/E27)-1,"") -> 0.25520833 | M28: =IF(ISNUMBER(E27),E28/E27,"") -> 1.2552083 | N28: =$C$38/E28 -> 1.2448133 | O28: =IF(B28>MEDIAN($B$2:$B$20),2,1) -> 1 | P28: =IF(M28="","",M28^O28) -> 1.2552083 | Q28: =IF(M28="","",M28^O28) -> 1.2552083 | R28: 4920 | S28: =$S$2 -> 2771 | T28: =$T$2 -> 3079.0526 | AB28: =B13 -> 58 | AC28: =AB28-$AC$48 -> -20.548387 | AD28: =IF(AC28>=0,AC28,0) -> 0 | AE28: =IF(AC28<0,AC28,0) -> -20.548387
... A32: =A31+31 -> 46008 | B32: 91 | C32: 8 | D32: 19 | E32: 3650 | F32: =0.6 + 0.1 * ((B32 - AVERAGE($B$2:$B$32)) / STDEVA($B$2:$B$32)) -> 0.6549508 | G32: =IF(B32/AVERAGE($B$2:$B$32)<0.75,"Seco",IF(B32/AVERAGE($B$2:$B$32)<1.25,"Normal","Chuvoso")) -> Normal | H32: =E32/AVERAGE($E$2:$E$32) -> 1.1745837 | I32: =IF(H32<0.75,"Baixa", IF(H32<1.25,"Normal", "Alta")) -> Normal | J32: Montagem | K32: =ROUNDUP( 1+3*(E32/AVERAGE($E$2:$E$32))+2*(B32/AVERAGE($B$2:$B$32)),0) -> 7 | L32: =IF(ISNUMBER(E31),(E32/E31)-1,"") -> -0.38344595 | M32: =IF(ISNUMBER(E31),E32/E31,"") -> 0.61655405 | N32: =$C$38/E32 -> 0.82191781 | O32: =IF(B32>MEDIAN($B$2:$B$20),2,1) -> 2 | P32: =IF(M32="","",M32^O32) -> 0.3801389 | Q32: =IF(M32="","",M32^O32) -> 0.3801389 | R32: 5920 | S32: =$S$2 -> 2771 | T32: =$T$2 -> 3079.0526 | AB32: =B17 -> 84 | AC32: =AB32-$AC$48 -> 5.4516129 | AD32: =IF(AC32>=0,AC32,0) -> 5.4516129 | AE32: =IF(AC32<0,AC32,0) -> 0
A33: Notas | AB33: =B18 -> 107 | AC33: =AB33-$AC$48 -> 28.451613 | AD33: =IF(AC33>=0,AC33,0) -> 28.451613 | AE33: =IF(AC33<0,AC33,0) -> 0
A34: Dados fictícios para fins acadêmicos relacionando condições metereológicas com a venda mensal de guarda-chuvas. Unidades: Preciptação em mm. Temperatura em oC, Velocidade do vento em km/h. | AB34: =B19 -> 118 | AC34: =AB34-$AC$48 -> 39.451613 | AD34: =IF(AC34>=0,AC34,0) -> 39.451613 | AE34: =IF(AC34<0,AC34,0) -> 0
AB35: =B20 -> 91 | AC35: =AB35-$AC$48 -> 12.451613 | AD35: =IF(AC35>=0,AC35,0) -> 12.451613 | AE35: =IF(AC35<0,AC35,0) -> 0
AB36: =B21 -> 82 | AC36: =AB36-$AC$48 -> 3.4516129 | AD36: =IF(AC36>=0,AC36,0) -> 3.4516129 | AE36: =IF(AC36<0,AC36,0) -> 0
A37: Outros dados | AB37: =B22 -> 74 | AC37: =AB37-$AC$48 -> -4.5483871 | AD37: =IF(AC37>=0,AC37,0) -> 0 | AE37: =IF(AC37<0,AC37,0) -> -4.5483871
A38: custo marketing | C38: 3000 | D38: R$/mês | H38: 1 | I38: {=SORT(B2:B32)} -> 42 | AB38: =B23 -> 78 | AC38: =AB38-$AC$48 -> -0.5483871 | AD38: =IF(AC38>=0,AC38,0) -> 0 | AE38: =IF(AC38<0,AC38,0) -> -0.5483871
H39: =H38+1 -> 2 | I39: 45 | AB39: =B24 -> 84 | AC39: =AB39-$AC$48 -> 5.4516129 | AD39: =IF(AC39>=0,AC39,0) -> 5.4516129 | AE39: =IF(AC39<0,AC39,0) -> 0
A40: n | B40: =COUNT(B42:B60) -> 19 | C40: =ROUNDUP(1+3.322*LOG10(B40),0) -> 6 | H40: =H39+1 -> 3 | I40: 49 | AB40: =B25 -> 63 | AC40: =AB40-$AC$48 -> -15.548387 | AD40: =IF(AC40>=0,AC40,0) -> 0 | AE40: =IF(AC40<0,AC40,0) -> -15.548387
A41: ID | B41: Prep | C41: Desv. Prep. | D41: Temp | E41: Desv. Temp. | H41: =H40+1 -> 4 | I41: 49 | L41: Vento | M41: Desv. Vento | N41: Vendas | O41: Media Vendas | P41: Desv. Vendas | AB41: =B26 -> 56 | AC41: =AB41-$AC$48 -> -22.548387 | AD41: =IF(AC41>=0,AC41,0) -> 0 | AE41: =IF(AC41<0,AC41,0) -> -22.548387
A42: 1 | B42: =B2 -> 58 | C42: =(B42-$B$73)/$B$74 -> -0.90683058 | D42: =C2 -> 26 | E42: =(D42-$D$73)/$D$74 -> 1.0558006 | H42: =H41+1 -> 5 | I42: 50 | L42: =D2 -> 14 | M42: =(L42-$L$73)/$L$74 -> -0.55654086 | N42: =E2 -> 1861 | O42: =$N$73 -> 3107.4839 | P42: =(N42-$O$42)/$N$74 -> -1.0470347 | AB42: =B27 -> 45 | AC42: =AB42-$AC$48 -> -33.548387 | AD42: =IF(AC42>=0,AC42,0) -> 0 | AE42: =IF(AC42<0,AC42,0) -> -33.548387
A43: =A42+1 -> 2 | B43: =B3 -> 49 | C43: =(B43-$B$73)/$B$74 -> -1.3040138 | D43: =C3 -> 28 | E43: =(D43-$D$73)/$D$74 -> 1.276948 | H43: =H42+1 -> 6 | I43: 54 | L43: =D3 -> 12 | M43: =(L43-$L$73)/$L$74 -> -0.95776799 | N43: =E3 -> 1745 | O43: =$N$73 -> 3107.4839 | P43: =(N43-$O$42)/$N$74 -> -1.1444737 | AB43: =B28 -> 50 | AC43: =AB43-$AC$48 -> -28.548387 | AD43: =IF(AC43>=0,AC43,0) -> 0 | AE43: =IF(AC43<0,AC43,0) -> -28.548387
A44: =A43+1 -> 3 | B44: =B4 -> 62 | C44: =(B44-$B$73)/$B$74 -> -0.73030469 | D44: =C4 -> 29 | E44: =(D44-$D$73)/$D$74 -> 1.3875218 | H44: =H43+1 -> 7 | I44: 56 | L44: =D4 -> 12 | M44: =(L44-$L$73)/$L$74 -> -0.95776799 | N44: =E4 -> 1977 | O44: =$N$73 -> 3107.4839 | P44: =(N44-$O$42)/$N$74 -> -0.94959583 | AB44: =B29 -> 92 | AC44: =AB44-$AC$48 -> 13.451613 | AD44: =IF(AC44>=0,AC44,0) -> 13.451613 | AE44: =IF(AC44<0,AC44,0) -> 0
A45: =A44+1 -> 4 | B45: =B5 -> 100 | C45: =(B45-$B$73)/$B$74 -> 0.94669127 | D45: =C5 -> 18 | E45: =(D45-$D$73)/$D$74 -> 0.17121091 | H45: =H44+1 -> 8 | I45: 58 | J45: Q1 | L45: =D5 -> 14 | M45: =(L45-$L$73)/$L$74 -> -0.55654086 | N45: =E5 -> 3908 | O45: =$N$73 -> 3107.4839 | P45: =(N45-$O$42)/$N$74 -> 0.67242603 | AB45: =B30 -> 112 | AC45: =AB45-$AC$48 -> 33.451613 | AD45: =IF(AC45>=0,AC45,0) -> 33.451613 | AE45: =IF(AC45<0,AC45,0) -> 0
A46: =A45+1 -> 5 | B46: =B6 -> 110 | C46: =(B46-$B$73)/$B$74 -> 1.388006 | D46: =C6 -> 14 | E46: =(D46-$D$73)/$D$74 -> -0.27108394 | H46: =H45+1 -> 9 | I46: 58 | L46: =D6 -> 15 | M46: =(L46-$L$73)/$L$74 -> -0.35592729 | N46: =E6 -> 5325 | O46: =$N$73 -> 3107.4839 | P46: =(N46-$O$42)/$N$74 -> 1.8626927 | AB46: =B31 -> 120 | AC46: =AB46-$AC$48 -> 41.451613 | AD46: =IF(AC46>=0,AC46,0) -> 41.451613 | AE46: =IF(AC46<0,AC46,0) -> 0
A47: =A46+1 -> 6 | B47: =B7 -> 102 | C47: =(B47-$B$73)/$B$74 -> 1.0349542 | D47: =C7 -> 13 | E47: =(D47-$D$73)/$D$74 -> -0.38165766 | H47: =H46+1 -> 10 | I47: 62 | L47: =D7 -> 17 | M47: =(L47-$L$73)/$L$74 -> 0.045299837 | N47: =E7 -> 4098 | O47: =$N$73 -> 3107.4839 | P47: =(N47-$O$42)/$N$74 -> 0.83202424 | AB47: =B32 -> 91 | AC47: =AB47-$AC$48 -> 12.451613 | AD47: =IF(AC47>=0,AC47,0) -> 12.451613 | AE47: =IF(AC47<0,AC47,0) -> 0
A48: =A47+1 -> 7 | B48: =B8 -> 84 | C48: =(B48-$B$73)/$B$74 -> 0.24058771 | D48: =C8 -> 10 | E48: =(D48-$D$73)/$D$74 -> -0.7133788 | H48: =H47+1 -> 11 | I48: 63 | L48: =D8 -> 18 | M48: =(L48-$L$73)/$L$74 -> 0.2459134 | N48: =E8 -> 2968 | O48: =$N$73 -> 3107.4839 | P48: =(N48-$O$42)/$N$74 -> -0.11716514 | AB48: Media | AC48: =AVERAGE(AB17:AB47) -> 78.548387
A49: =A48+1 -> 8 | B49: =B9 -> 79 | C49: =(B49-$B$73)/$B$74 -> 0.019930342 | D49: =C9 -> 4 | E49: =(D49-$D$73)/$D$74 -> -1.3768211 | H49: =H48+1 -> 12 | I49: 74 | L49: =D9 -> 19 | M49: =(L49-$L$73)/$L$74 -> 0.44652697 | N49: =E9 -> 2771 | O49: =$N$73 -> 3107.4839 | P49: =(N49-$O$42)/$N$74 -> -0.28264329 | AB49: Soma Desv. | AC49: =SUM(AC17:AC47) -> 0
A50: =A49+1 -> 9 | B50: =B10 -> 74 | C50: =(B50-$B$73)/$B$74 -> -0.20072702 | D50: =C10 -> 3 | E50: =(D50-$D$73)/$D$74 -> -1.4873948 | H50: =H49+1 -> 13 | I50: 74 | L50: =D10 -> 30 | M50: =(L50-$L$73)/$L$74 -> 2.6532762 | N50: =E10 -> 2097 | O50: =$N$73 -> 3107.4839 | P50: =(N50-$O$42)/$N$74 -> -0.84879696
A51: =A50+1 -> 10 | B51: =B11 -> 80 | C51: =(B51-$B$73)/$B$74 -> 0.064061815 | D51: =C11 -> 6 | E51: =(D51-$D$73)/$D$74 -> -1.1556736 | H51: =H50+1 -> 14 | I51: 78 | L51: =D11 -> 28 | M51: =(L51-$L$73)/$L$74 -> 2.252049 | N51: =E11 -> 2254 | O51: =$N$73 -> 3107.4839 | P51: =(N51-$O$42)/$N$74 -> -0.71691843
A52: =A51+1 -> 11 | B52: =B12 -> 87 | C52: =(B52-$B$73)/$B$74 -> 0.37298212 | D52: =C12 -> 12 | E52: =(D52-$D$73)/$D$74 -> -0.49223137 | H52: =H51+1 -> 15 | I52: 79 | L52: =D12 -> 18 | M52: =(L52-$L$73)/$L$74 -> 0.2459134 | N52: =E12 -> 2978 | O52: =$N$73 -> 3107.4839 | P52: =(N52-$O$42)/$N$74 -> -0.10876524
A53: =A52+1 -> 12 | B53: =B13 -> 58 | C53: =(B53-$B$73)/$B$74 -> -0.90683058 | D53: =C13 -> 19 | E53: =(D53-$D$73)/$D$74 -> 0.28178462 | H53: =H52+1 -> 16 | I53: 80 | J53: Q2 | L53: =D13 -> 14 | M53: =(L53-$L$73)/$L$74 -> -0.55654086 | N53: =E13 -> 2514 | O53: =$N$73 -> 3107.4839 | P53: =(N53-$O$42)/$N$74 -> -0.49852088
A54: =A53+1 -> 13 | B54: =B14 -> 54 | C54: =(B54-$B$73)/$B$74 -> -1.0833565 | D54: =C14 -> 26 | E54: =(D54-$D$73)/$D$74 -> 1.0558006 | H54: =H53+1 -> 17 | I54: 82 | L54: =D14 -> 13 | M54: =(L54-$L$73)/$L$74 -> -0.75715442 | N54: =E14 -> 2205 | O54: =$N$73 -> 3107.4839 | P54: =(N54-$O$42)/$N$74 -> -0.75807797
A55: =A54+1 -> 14 | B55: =B15 -> 42 | C55: =(B55-$B$73)/$B$74 -> -1.6129341 | D55: =C15 -> 30 | E55: =(D55-$D$73)/$D$74 -> 1.4980955 | H55: =H54+1 -> 18 | I55: 84 | L55: =D15 -> 13 | M55: =(L55-$L$73)/$L$74 -> -0.75715442 | N55: =E15 -> 1979 | O55: =$N$73 -> 3107.4839 | P55: =(N55-$O$42)/$N$74 -> -0.94791585
A56: =A55+1 -> 15 | B56: =B16 -> 49 | C56: =(B56-$B$73)/$B$74 -> -1.3040138 | D56: =C16 -> 31 | E56: =(D56-$D$73)/$D$74 -> 1.6086692 | H56: =H55+1 -> 19 | I56: 84 | L56: =D16 -> 10 | M56: =(L56-$L$73)/$L$74 -> -1.3589951 | N56: =E16 -> 2358 | O56: =$N$73 -> 3107.4839 | P56: =(N56-$O$42)/$N$74 -> -0.62955941
A57: =A56+1 -> 16 | B57: =B17 -> 84 | C57: =(B57-$B$73)/$B$74 -> 0.24058771 | D57: =C17 -> 19 | E57: =(D57-$D$73)/$D$74 -> 0.28178462 | H57: =H56+1 -> 20 | I57: 84 | L57: =D17 -> 14 | M57: =(L57-$L$73)/$L$74 -> -0.55654086 | N57: =E17 -> 3490 | O57: =$N$73 -> 3107.4839 | P57: =(N57-$O$42)/$N$74 -> 0.32130996
A58: =A57+1 -> 17 | B58: =B18 -> 107 | C58: =(B58-$B$73)/$B$74 -> 1.2556116 | D58: =C18 -> 15 | E58: =(D58-$D$73)/$D$74 -> -0.16051023 | H58: =H57+1 -> 21 | I58: 87 | L58: =D18 -> 18 | M58: =(L58-$L$73)/$L$74 -> 0.2459134 | N58: =E18 -> 4920 | O58: =$N$73 -> 3107.4839 | P58: =(N58-$O$42)/$N$74 -> 1.5224965
A59: =A58+1 -> 18 | B59: =B19 -> 118 | C59: =(B59-$B$73)/$B$74 -> 1.7410578 | D59: =C19 -> 13 | E59: =(D59-$D$73)/$D$74 -> -0.38165766 | H59: =H58+1 -> 22 | I59: 91 | L59: =D19 -> 19 | M59: =(L59-$L$73)/$L$74 -> 0.44652697 | N59: =E19 -> 5555 | O59: =$N$73 -> 3107.4839 | P59: =(N59-$O$42)/$N$74 -> 2.0558906
A60: =A59+1 -> 19 | B60: =B20 -> 91 | C60: =(B60-$B$73)/$B$74 -> 0.54950801 | D60: =C20 -> 8 | E60: =(D60-$D$73)/$D$74 -> -0.93452622 | H60: =H59+1 -> 23 | I60: 91 | L60: =D20 -> 19 | M60: =(L60-$L$73)/$L$74 -> 0.44652697 | N60: =E20 -> 3499 | O60: =$N$73 -> 3107.4839 | P60: =(N60-$O$42)/$N$74 -> 0.32886987
A61: =A60+1 -> 20 | B61: =B21 -> 82 | C61: =(B61-$B$73)/$B$74 -> 0.15232476 | D61: =C21 -> 5 | E61: =(D61-$D$73)/$D$74 -> -1.2662474 | H61: =H60+1 -> 24 | I61: 92 | J61: Q3 | L61: =D21 -> 18 | M61: =(L61-$L$73)/$L$74 -> 0.2459134 | N61: =E21 -> 2890 | O61: =$N$73 -> 3107.4839 | P61: =(N61-$O$42)/$N$74 -> -0.18268441
A62: =A61+1 -> 21 | B62: =B22 -> 74 | C62: =(B62-$B$73)/$B$74 -> -0.20072702 | D62: =C22 -> 4 | E62: =(D62-$D$73)/$D$74 -> -1.3768211 | H62: =H61+1 -> 25 | I62: 100 | L62: =D22 -> 30 | M62: =(L62-$L$73)/$L$74 -> 2.6532762 | N62: =E22 -> 2180 | O62: =$N$73 -> 3107.4839 | P62: =(N62-$O$42)/$N$74 -> -0.77907774
A63: =A62+1 -> 22 | B63: =B23 -> 78 | C63: =(B63-$B$73)/$B$74 -> -0.02420113 | D63: =C23 -> 7 | E63: =(D63-$D$73)/$D$74 -> -1.0450999 | H63: =H62+1 -> 26 | I63: 102 | L63: =D23 -> 16 | M63: =(L63-$L$73)/$L$74 -> -0.15531373 | N63: =E23 -> 2320 | O63: =$N$73 -> 3107.4839 | P63: =(N63-$O$42)/$N$74 -> -0.66147905
A64: =A63+1 -> 23 | B64: =B24 -> 84 | C64: =(B64-$B$73)/$B$74 -> 0.24058771 | D64: =C24 -> 11 | E64: =(D64-$D$73)/$D$74 -> -0.60280508 | H64: =H63+1 -> 27 | I64: 107 | L64: =D24 -> 18 | M64: =(L64-$L$73)/$L$74 -> 0.2459134 | N64: =E24 -> 2950 | O64: =$N$73 -> 3107.4839 | P64: =(N64-$O$42)/$N$74 -> -0.13228497
A65: =A64+1 -> 24 | B65: =B25 -> 63 | C65: =(B65-$B$73)/$B$74 -> -0.68617322 | D65: =C25 -> 17 | E65: =(D65-$D$73)/$D$74 -> 0.060637198 | H65: =H64+1 -> 28 | I65: 110 | L65: =D25 -> 14 | M65: =(L65-$L$73)/$L$74 -> -0.55654086 | N65: =E25 -> 2600 | O65: =$N$73 -> 3107.4839 | P65: =(N65-$O$42)/$N$74 -> -0.42628168
A66: =A65+1 -> 25 | B66: =B26 -> 56 | C66: =(B66-$B$73)/$B$74 -> -0.99509353 | D66: =C26 -> 26 | E66: =(D66-$D$73)/$D$74 -> 1.0558006 | H66: =H65+1 -> 29 | I66: 112 | L66: =D26 -> 13 | M66: =(L66-$L$73)/$L$74 -> -0.75715442 | N66: =E26 -> 2260 | O66: =$N$73 -> 3107.4839 | P66: =(N66-$O$42)/$N$74 -> -0.71187849
A67: =A66+1 -> 26 | B67: =B27 -> 45 | C67: =(B67-$B$73)/$B$74 -> -1.4805397 | D67: =C27 -> 30 | E67: =(D67-$D$73)/$D$74 -> 1.4980955 | H67: =H66+1 -> 30 | I67: 118 | L67: =D27 -> 12 | M67: =(L67-$L$73)/$L$74 -> -0.95776799 | N67: =E27 -> 1920 | O67: =$N$73 -> 3107.4839 | P67: =(N67-$O$42)/$N$74 -> -0.9974753
A68: =A67+1 -> 27 | B68: =B28 -> 50 | C68: =(B68-$B$73)/$B$74 -> -1.2598824 | D68: =C28 -> 30 | E68: =(D68-$D$73)/$D$74 -> 1.4980955 | H68: =H67+1 -> 31 | I68: 120 | L68: =D28 -> 11 | M68: =(L68-$L$73)/$L$74 -> -1.1583816 | N68: =E28 -> 2410 | O68: =$N$73 -> 3107.4839 | P68: =(N68-$O$42)/$N$74 -> -0.5858799
A69: =A68+1 -> 28 | B69: =B29 -> 92 | C69: =(B69-$B$73)/$B$74 -> 0.59363949 | D69: =C29 -> 18 | E69: =(D69-$D$73)/$D$74 -> 0.17121091 | L69: =D29 -> 15 | M69: =(L69-$L$73)/$L$74 -> -0.35592729 | N69: =E29 -> 3650 | O69: =$N$73 -> 3107.4839 | P69: =(N69-$O$42)/$N$74 -> 0.45570845
A70: =A69+1 -> 29 | B70: =B30 -> 112 | C70: =(B70-$B$73)/$B$74 -> 1.4762689 | D70: =C30 -> 18 | E70: =(D70-$D$73)/$D$74 -> 0.17121091 | L70: =D30 -> 18 | M70: =(L70-$L$73)/$L$74 -> 0.2459134 | N70: =E30 -> 5080 | O70: =$N$73 -> 3107.4839 | P70: =(N70-$O$42)/$N$74 -> 1.656895
A71: =A70+1 -> 30 | B71: =B31 -> 120 | C71: =(B71-$B$73)/$B$74 -> 1.8293207 | D71: =C31 -> 12 | E71: =(D71-$D$73)/$D$74 -> -0.49223137 | L71: =D31 -> 19 | M71: =(L71-$L$73)/$L$74 -> 0.44652697 | N71: =E31 -> 5920 | O71: =$N$73 -> 3107.4839 | P71: =(N71-$O$42)/$N$74 -> 2.3624871
A72: =A71+1 -> 31 | B72: =B32 -> 91 | C72: =(B72-$B$73)/$B$74 -> 0.54950801 | D72: =C32 -> 8 | E72: =(D72-$D$73)/$D$74 -> -0.93452622 | L72: =D32 -> 19 | M72: =(L72-$L$73)/$L$74 -> 0.44652697 | N72: =E32 -> 3650 | O72: =$N$73 -> 3107.4839 | P72: =(N72-$O$42)/$N$74 -> 0.45570845
B73: =AVERAGE(B42:B72) -> 78.548387 | D73: =AVERAGE(D42:D72) -> 16.451613 | L73: =AVERAGE(L42:L72) -> 16.774194 | N73: =AVERAGE(N42:N72) -> 3107.4839
B74: =STDEVA(B42:B72) -> 22.659566 | D74: =STDEVA(D42:D72) -> 9.0437408 | L74: =STDEVA(L42:L72) -> 4.9847078 | N74: =STDEVA(N42:N72) -> 1190.4895
A77: K | B77: AUC
A78: 1 | B78: =1-(1/A78^2) -> 0
A79: =A78+0.1 -> 1.1 | B79: =1-(1/A79^2) -> 0.17355372
A80: =A79+0.1 -> 1.2 | B80: =1-(1/A80^2) -> 0.30555556
A81: =A80+0.1 -> 1.3 | B81: =1-(1/A81^2) -> 0.40828402
A82: =A81+0.1 -> 1.4 | B82: =1-(1/A82^2) -> 0.48979592
A83: =A82+0.1 -> 1.5 | B83: =1-(1/A83^2) -> 0.55555556
A84: =A83+0.1 -> 1.6 | B84: =1-(1/A84^2) -> 0.609375
A85: =A84+0.1 -> 1.7 | B85: =1-(1/A85^2) -> 0.65397924
A86: =A85+0.1 -> 1.8 | B86: =1-(1/A86^2) -> 0.69135802
A87: =A86+0.1 -> 1.9 | B87: =1-(1/A87^2) -> 0.72299169
A88: =A87+0.1 -> 2 | B88: =1-(1/A88^2) -> 0.75
A89: =A88+0.1 -> 2.1 | B89: =1-(1/A89^2) -> 0.77324263
A90: =A89+0.1 -> 2.2 | B90: =1-(1/A90^2) -> 0.79338843
... A108: =A107+0.1 -> 4 | B108: =1-(1/A108^2) -> 0.9375
A110: Valores | B110: Normal | C110: Std1 | D110: Std2 | E110: Std3 | L110: Rótulos
A111: -4 | B111: =_xlfn.NORM.DIST(A111,0,1,FALSE) -> 0.00013383023 | C111: =IF(AND(A111>=-1,A111<=1),A111,"") | D111: =IF(OR(AND(A111>=-2,A111<-1),AND(A111>=1,A111<2)),A111,"") | E111: =IF(OR(A111<-2,A111>2),A111,"") -> -4 | L111: =IF(INT(A111)=A111,A111,"") -> -4
A112: =A111+0.25 -> -3.75 | B112: =_xlfn.NORM.DIST(A112,0,1,FALSE) -> 0.00035259568 | C112: =IF(AND(A112>=-1,A112<=1),A112,"") | D112: =IF(OR(AND(A112>=-2,A112<-1),AND(A112>=1,A112<2)),A112,"") | E112: =IF(OR(A112<-2,A112>2),A112,"") -> -3.75 | L112: =IF(INT(A112)=A112,A112,"")
A113: =A112+0.25 -> -3.5 | B113: =_xlfn.NORM.DIST(A113,0,1,FALSE) -> 0.00087268269 | C113: =IF(AND(A113>=-1,A113<=1),A113,"") | D113: =IF(OR(AND(A113>=-2,A113<-1),AND(A113>=1,A113<2)),A113,"") | E113: =IF(OR(A113<-2,A113>2),A113,"") -> -3.5 | L113: =IF(INT(A113)=A113,A113,"")
A114: =A113+0.25 -> -3.25 | B114: =_xlfn.NORM.DIST(A114,0,1,FALSE) -> 0.0020290481 | C114: =IF(AND(A114>=-1,A114<=1),A114,"") | D114: =IF(OR(AND(A114>=-2,A114<-1),AND(A114>=1,A114<2)),A114,"") | E114: =IF(OR(A114<-2,A114>2),A114,"") -> -3.25 | L114: =IF(INT(A114)=A114,A114,"")
A115: =A114+0.25 -> -3 | B115: =_xlfn.NORM.DIST(A115,0,1,FALSE) -> 0.0044318484 | C115: =IF(AND(A115>=-1,A115<=1),A115,"") | D115: =IF(OR(AND(A115>=-2,A115<-1),AND(A115>=1,A115<2)),A115,"") | E115: =IF(OR(A115<-2,A115>2),A115,"") -> -3 | L115: =IF(INT(A115)=A115,A115,"") -> -3
A116: =A115+0.25 -> -2.75 | B116: =_xlfn.NORM.DIST(A116,0,1,FALSE) -> 0.0090935625 | C116: =IF(AND(A116>=-1,A116<=1),A116,"") | D116: =IF(OR(AND(A116>=-2,A116<-1),AND(A116>=1,A116<2)),A116,"") | E116: =IF(OR(A116<-2,A116>2),A116,"") -> -2.75 | L116: =IF(INT(A116)=A116,A116,"")
A117: =A116+0.25 -> -2.5 | B117: =_xlfn.NORM.DIST(A117,0,1,FALSE) -> 0.0175283 | C117: =IF(AND(A117>=-1,A117<=1),A117,"") | D117: =IF(OR(AND(A117>=-2,A117<-1),AND(A117>=1,A117<2)),A117,"") | E117: =IF(OR(A117<-2,A117>2),A117,"") -> -2.5 | L117: =IF(INT(A117)=A117,A117,"")
A118: =A117+0.25 -> -2.25 | B118: =_xlfn.NORM.DIST(A118,0,1,FALSE) -> 0.031739652 | C118: =IF(AND(A118>=-1,A118<=1),A118,"") | D118: =IF(OR(AND(A118>=-2,A118<-1),AND(A118>=1,A118<2)),A118,"") | E118: =IF(OR(A118<-2,A118>2),A118,"") -> -2.25 | L118: =IF(INT(A118)=A118,A118,"")
A119: =A118+0.25 -> -2 | B119: =_xlfn.NORM.DIST(A119,0,1,FALSE) -> 0.053990967 | C119: =IF(AND(A119>=-1,A119<=1),A119,"") | D119: =IF(OR(AND(A119>=-2,A119<-1),AND(A119>=1,A119<2)),A119,"") -> -2 | E119: =IF(OR(A119<-2,A119>2),A119,"") | L119: =IF(INT(A119)=A119,A119,"") -> -2
A120: =A119+0.25 -> -1.75 | B120: =_xlfn.NORM.DIST(A120,0,1,FALSE) -> 0.086277319 | C120: =IF(AND(A120>=-1,A120<=1),A120,"") | D120: =IF(OR(AND(A120>=-2,A120<-1),AND(A120>=1,A120<2)),A120,"") -> -1.75 | E120: =IF(OR(A120<-2,A120>2),A120,"") | L120: =IF(INT(A120)=A120,A120,"")
A121: =A120+0.25 -> -1.5 | B121: =_xlfn.NORM.DIST(A121,0,1,FALSE) -> 0.1295176 | C121: =IF(AND(A121>=-1,A121<=1),A121,"") | D121: =IF(OR(AND(A121>=-2,A121<-1),AND(A121>=1,A121<2)),A121,"") -> -1.5 | E121: =IF(OR(A121<-2,A121>2),A121,"") | L121: =IF(INT(A121)=A121,A121,"")
A122: =A121+0.25 -> -1.25 | B122: =_xlfn.NORM.DIST(A122,0,1,FALSE) -> 0.18264909 | C122: =IF(AND(A122>=-1,A122<=1),A122,"") | D122: =IF(OR(AND(A122>=-2,A122<-1),AND(A122>=1,A122<2)),A122,"") -> -1.25 | E122: =IF(OR(A122<-2,A122>2),A122,"") | L122: =IF(INT(A122)=A122,A122,"")
A123: =A122+0.25 -> -1 | B123: =_xlfn.NORM.DIST(A123,0,1,FALSE) -> 0.24197072 | C123: =IF(AND(A123>=-1,A123<=1),A123,"") -> -1 | D123: =IF(OR(AND(A123>=-2,A123<-1),AND(A123>=1,A123<2)),A123,"") | E123: =IF(OR(A123<-2,A123>2),A123,"") | L123: =IF(INT(A123)=A123,A123,"") -> -1
...

Sheet Página3
B2: Estatística Descritiva Univariada e Bivariada
B3: A estatística envolve técnicas para coletar, organizar, descrever, analisar e interpretar dados, ou provenientes de experimentos, ou vindos de estudos observacionais (Barbetta, 2010).
B10: Fig. 1 - Técnicas envolvidas no processo estatístico. Fluxo inicia na coleta, organização, descrição, análise e interepretação dos dados. Fonte: Autor, 2026.
B11: A análise estatística de dados geralmente tem por objetivo tomadas de decisões, resoluções de problemas ou produção de conhecimento. Mas novos conhecimentos normalmente geram novos problemas de pesquisa, resultando em um processo iterativo (Barbetta, 2010).
B23: Fig. 2 - Processo iterativo das pesquisas empíricas. Ciclo iniciando nas pesquisas, dados, informações e novos conhecimento e/ou problemas. Fonte: Autor, 2026.
B24: A estatística aplicada pode ser dividida em duas áreas: estatística descritiva e estatística inferencial.
B25: A estatística descritiva consiste em métodos para sumarizar dados amostrais por meio de tabelas, gráficos e medidas-resumo. Em contraste, a estatística inferencial consiste em métodos que utilizam resultados amostrais para tomar decisões ou fazer previsões sobre uma população subjacente (Mann, 2012; Weiss, 2010).
B39: Fig. 3 - Diferenças entre Estatística Descritiva e Inferencial. Ilustração de um levantamento por amostragem para avaliar a preferência do consumidor. Fonte: Barbetta, 2010.
B40: O termo univariada refere-se ao fato de que apenas uma variável está sendo considerada. O principal objetivo da estatística univariada é descrever e resumir os dados. Quando duas ou mais variáveis são analisadas, utiliza-se a análise ou estatística bivariada ou multivariada, respectivamente. Nesse caso, o interesse principal recai sobre as relações entre um conjunto de variáveis.
B42: Saiba mais
B43: Estatística Descritiva
B44: Estatística Inferencial
... B53: Por favor, cite da seguinte forma: Rudolph, A., Krois, J., Hartmann, K. (2023): Estatística e Análise de Geodados usando Python (SOGA-Py). Departamento de Ciências da Terra, Universidade Livre de Berlim.

Sheet Página4a
B2: Manipulação de Dados, Tabelas e Gráficos
B3: Na análise exploratória de dados, além de descrever os dados, busca-se compreender características do processo que os gerou. Por meio do uso adequado de tabelas, gráficos e medidas estatísticas, é possível identificar padrões e estruturas que não são evidentes nos dados brutos.
B5: Fig. 4 – Estrutura de um conjunto de dados. As linhas representam os indivíduos ou casos observados, enquanto as colunas correspondem às variáveis associadas a cada indivíduo (por exemplo, sexo, idade, nível de instrução e provedor). O conjunto de dados é formado pela combinação sistemática dessas observações, organizando a informação de cada indivíduo segundo as variáveis analisadas. Fonte: Barbetta, 2010.
B6: Dados e Variáveis
B7: Os dados podem ser observações de variáveis qualitativas ou de variáveis quantitativas. E as técnicas de análise serão diferentes para cada caso. Quando os possíveis resultados de uma variável são números de certa escala, dizemos que essa variável é quantitativa. Quando os possíveis resultados são atributos ou qualidades, a variável é dita qualitativa (Barbetta, 2010)
B9: Fig. 5 – Classificação das variáveis estatísticas. O diagrama ilustra a distinção entre variáveis quantitativas, que geram dados numéricos passíveis de operações aritméticas, e variáveis qualitativas ou categóricas, que produzem dados classificados em categorias ou rótulos. Essa classificação orienta a escolha das técnicas estatísticas adequadas para análise dos dados. Fonte: Barbetta, 2010.
B10: Dentre as variáveis qualitativas, ainda podemos fazer uma distinção entre dois tipos: variável qualitativa nominal, para a qual não existe nenhuma ordenação nas possíveis realizações, e variável qualitativa ordinal, para a qual existe uma ordem nos seus resultados. O tipo de defeitos de produção dos guarda-chuvas é um variável qualitativa nominal, enquanto o nível de vendas ou índice pluviomẽtrico são exemplos de variáveis qualitativas ordinais (MORETIN, 2017).
B11: Análise de Variáveis Qualitativas
B12: Um dos primeiros passos para analisar um arquivo de dados, especialmente quando o número de observações for grande, é a distribuição de frequências de cada variável.
B13: Categorias | C13: Freq. Absoluta | D13: Freq. Relativa
B14: {=UNIQUE(dados!G2:G32)} -> Seco | C14: =COUNTIFS(dados!$G$2:$G$32,B14) -> 9 | D14: =C14/$C$17 -> 0.29032258
B15: Normal | C15: =COUNTIFS(dados!$G$2:$G$32,B15) -> 15 | D15: =C15/$C$17 -> 0.48387097
B16: Chuvoso | C16: =COUNTIFS(dados!$G$2:$G$32,B16) -> 7 | D16: =C16/$C$17 -> 0.22580645
B17: Total | C17: =SUM(C14:C16) -> 31 | D17: =SUM(D14:D16) -> 1
B27: Fig. 6 – Distribuição das classes do índice pluviométrico. A tabela e os gráficos apresentam a frequência absoluta e relativa das categorias seco, normal e chuvoso ao longo do período analisado. Observa-se predominância de meses classificados como normais, seguidos por meses secos e chuvosos, indicando que a maior parte das observações apresenta precipitação próxima à média histórica.
B28: Tipo de Falha | C28: Qtde | D28: Perc. | E28: Perc. Acum.
B29: =dados!F45 -> Varetas | C29: =dados!G45 -> 59 | D29: =C29/SUM($C$29:$C$32) -> 0.2979798 | E29: =D29 -> 0.2979798
B30: =dados!F43 -> Montagem | C30: =dados!G43 -> 56 | D30: =C30/SUM($C$29:$C$32) -> 0.28282828 | E30: =D30+E29 -> 0.58080808
B31: =dados!F42 -> Costura | C31: =dados!G42 -> 42 | D31: =C31/SUM($C$29:$C$32) -> 0.21212121 | E31: =D31+E30 -> 0.79292929
B32: =dados!F44 -> Tecido | C32: =dados!G44 -> 41 | D32: =C32/SUM($C$29:$C$32) -> 0.20707071 | E32: =D32+E31 -> 1
B44: Fig. 7 – Distribuição das classes do índice pluviométrico com uso do Diagrama de Pareto. A tabela e os gráficos apresentam a frequência absoluta e relativa das categorias seco, normal e chuvoso ao longo do período analisado. Observa-se predominância de meses classificados como normais, seguidos por meses secos e chuvosos, indicando que a maior parte das observações apresenta precipitação próxima à média histórica.
B45: Análise de Variáveis Quantitativas
B46: A variável quantitativa pode ser contínua, quando assume qualquer valor entre dois limites (ex: peso, altura, medições como pluviometria, vento e temperatura), ou pode ser discreta, quando só pode assumir valores pertencentes a um conjunto enumerável (ex: nº de filhos, contagem em geral, como as vendas ou quantidade de defeitos dos guarda-chuvas) .
B58: Fig. 8 – Evolução temporal da temperatura e do vento. O gráfico apresenta as séries mensais de temperatura (°C) e velocidade do vento (km/h) ao longo do período analisado. Observa-se um comportamento sazonal da temperatura, com alternância entre períodos mais quentes e mais frios, enquanto o vento apresenta variações menos regulares, com picos pontuais ao longo do tempo.
B71: Fig. 9 – Distribuição da precipitação mensal ao longo do período analisado. As barras representam os valores observados de precipitação mensal, enquanto a linha suavizada indica a tendência temporal da série, evidenciando a sazonalidade do regime pluviométrico, com períodos recorrentes de maior e menor volume de chuvas.
B72: Lim. Inf. | C72: Lim. Sup. | D72: Notação | E72: Frequência
B73: 30 | C73: =B73+$H$79 -> 45 | D73: =CONCATENATE("[",B73,", ",C73,")") -> [30, 45) | E73: =COUNTIFS(dados!$B$2:$B$32,">="&B73,dados!$B$2:$B$32,"<"&C73) -> 1 | F73: Tamanho da Amostra (n) | H73: =COUNT(dados!B2:B32) -> 31
B74: =C73 -> 45 | C74: =B74+$H$79 -> 60 | D74: =CONCATENATE("[",B74,", ",C74,")") -> [45, 60) | E74: =COUNTIFS(dados!$B$2:$B$32,">="&B74,dados!$B$2:$B$32,"<"&C74) -> 8 | F74: Máximo | H74: =MAX(dados!B2:B32) -> 120
B75: =C74 -> 60 | C75: =B75+$H$79 -> 75 | D75: =CONCATENATE("[",B75,", ",C75,")") -> [60, 75) | E75: =COUNTIFS(dados!$B$2:$B$32,">="&B75,dados!$B$2:$B$32,"<"&C75) -> 4 | F75: Mínimo | H75: =MIN(dados!B2:B32) -> 42
B76: =C75 -> 75 | C76: =B76+$H$79 -> 90 | D76: =CONCATENATE("[",B76,", ",C76,")") -> [75, 90) | E76: =COUNTIFS(dados!$B$2:$B$32,">="&B76,dados!$B$2:$B$32,"<"&C76) -> 8 | F76: Amplitude total (A) | H76: =MAX(dados!B5:B35)-MIN(dados!B5:B35) -> 78
B77: =C76 -> 90 | C77: =B77+$H$79 -> 105 | D77: =CONCATENATE("[",B77,", ",C77,")") -> [90, 105) | E77: =COUNTIFS(dados!$B$2:$B$32,">="&B77,dados!$B$2:$B$32,"<"&C77) -> 5 | F77: Número de Classes Sturges (k) | H77: =ROUNDUP(1+3.3*LOG(H73),0) -> 6
B78: =C77 -> 105 | C78: =B78+$H$79 -> 120 | D78: =CONCATENATE("[",B78,", ",C78,")") -> [105, 120) | E78: =COUNTIFS(dados!$B$2:$B$32,">="&B78,dados!$B$2:$B$32,"<"&C78) -> 4 | F78: Amplitude Classe (h) | H78: =H76/H77 -> 13
B79: =C78 -> 120 | C79: =B79+$H$79 -> 135 | D79: =CONCATENATE("[",B79,", ",C79,")") -> [120, 135) | E79: =COUNTIFS(dados!$B$2:$B$32,">="&B79,dados!$B$2:$B$32,"<"&C79) -> 1 | F79: Amplitude Classe (h) | H79: 15
B90: Fig. 10 – Histograma da pluviometria. A tabela e os gráficos apresentam a frequência absoluta e relativa das categorias seco, normal e chuvoso ao longo do período analisado. Observa-se predominância de meses classificados como normais, seguidos por meses secos e chuvosos, indicando que a maior parte das observações apresenta precipitação próxima à média histórica.
B103: Fig. 11 – Gráfico de dispersão entre precipitação e vendas. Cada ponto representa a relação entre a precipitação mensal e o volume de vendas de guarda-chuvas, enquanto a linha indica o ajuste de uma relação linear. Observa-se uma associação positiva, sugerindo que meses com maior precipitação tendem a apresentar maiores volumes de venda.
B104: Saiba mais
B105: Variáveis
B106: DIstribuição de Frequências
B107: Gráfico de Barras
B108: Gráfico de Pizza
B109: Gráfico de Linha
B110: Histograma
B111: Gráfico de Dispersão
B113: Citação
B114: Estas aulas são baseadas no projeto de e-learning SOGA-Py que foi desenvolvido no Departamento de Ciências da Terra por Annette Rudolph, Joachim Krois e Kai Hartmann. O contato pode ser realizado por e-mail, pelo endereço soga[at]zedat.fu-berlin.de.
... B117: Por favor, cite da seguinte forma: Rudolph, A., Krois, J., Hartmann, K. (2023): Estatística e Análise de Geodados usando Python (SOGA-Py). Departamento de Ciências da Terra, Universidade Livre de Berlim.

Sheet Página4
B2: Medidas de Tendência Central
B3: Para obter intuição sobre qualquer conjunto de dados, este pode ser descrito por meio de medidas-resumo numéricas. Existem três principais medidas de tendência central: a média, a mediana e a moda. No entanto, há também outras medidas de tendência central, como a média harmônica, a média ponderada e a média geométrica. Nas próximas páginas serão apresentadas as definições e aplicações dessas medidas.
B22: Fig. 12 - Diveras médias generalizadas Mp(1,x). Hierarquia completa, do menor para o maior valor, é: média harmônica, geométricas, arimtimética, quadrática (RMS) e cúbica. Fonte: Wikipedia, 2026.
B23: Se p é um número real não nulo, e x1, …, xn são números reais positivos, então a média generalizada, ou média de potência, com expoente p desses números reais positivos é definida como.
H24: (1)
B25: A média generalizada pode ser expressa na forma usando raiz p-ésima:
H26: (2)
B27: Para p → -∞, define-se a média como o mínimo dos valores observados:
H29: (3)
B31: Para p = −1, define-se a média como a média harmônica:
H32: (1)
B33: Para p = 0, define-se a média como a média geométrica:
H34: (1)
B35: Para p = 1, define-se a média como a média aritmética:
H36: (1)
B37: Para p = 2, define-se a média como a média quadrática, também conhecida como root mean square (RMS):
H38: (1)
B39: Para p → ∞, define-se a média como o máximo dos valores observados:
H41: (1)
B43: Saiba mais
B44: Tendência Central
B45: Média
B46: Mediana
B47: Moda
B48: Média Harmônica
B49: Média Ponderada
B51: Citação
B52: Estas aulas são baseadas no projeto de e-learning SOGA-Py que foi desenvolvido no Departamento de Ciências da Terra por Annette Rudolph, Joachim Krois e Kai Hartmann. O contato pode ser realizado por e-mail, pelo endereço soga[at]zedat.fu-berlin.de.
B54: Você pode utilizar este projeto livremente sob a Licença Creative Commons Atribuição-CompartilhaIgual 4.0 Internacional.
B55: Por favor, cite da seguinte forma: Rudolph, A., Krois, J., Hartmann, K. (2023): Estatística e Análise de Geodados usando Python (SOGA-Py). Departamento de Ciências da Terra, Universidade Livre de Berlim.

Sheet Página5
B2: Média Aritimética
B3: A média aritmética é definida da seguinte forma:
B7: A média aritmética calculada para dados amostrais é denotada por x̄ (lê-se “x barra”), enquanto a média aritmética para dados populacionais é denotada por μ (letra grega mu, lê-se "mi"). Assim, a média aritmética pode ser calculada pelas seguintes expressões:
H8: (1)
B9: ou
B11: onde ∑ᵢ₌₁ⁿ xᵢ representa a soma de todos os valores (x₁, x₂, …, xₙ), N corresponde ao tamanho da população e n ao tamanho da amostra.
B12: Exemplo 1
B13: Considere o conjunto de dados de unidades vendidas de guarda-chuvas por mês ao longo de um determinado período, no qual as vendas variam entre meses devido a fatores sazonais e operacionais.
B14: Pergunta central: Qual é a média mensal de vendas nesse período?
B15: Cálculo por Etapas
B16: Soma Valores | C16: =SUM(dados!E2:E20) -> 58502 | D16: un | E16: A média aritmética é sensível a valores atípicos, ou seja, números muito altos ou muito baixos distorcem a medida estatística.
B17: Tamanho Amostra | C17: =COUNT(dados!E2:E20) -> 19 | D17: mês
B18: xart (manual) | C18: =C16/C17 -> 3079.0526 | D18: un/mês
B19: Cálculo Direto
B20: xart (manual) | C20: =SUM(dados!E2:E20)/COUNT(dados!E2:E20) -> 3079.0526 | D20: un/mês
B21: xart (função) | C21: =AVERAGE(dados!E2:E20) -> 3079.0526 | D21: un/mês
B23: Média Geométrica
B24: Ao estudar fenômenos como inflação ou crescimento populacional, que envolvem aumentos ou reduções periódicas (conhecidos como taxas de variação ou índices), a média geométrica é mais adequada para determinar a variação média ao longo de todo o período analisado. Para calcular a média geométrica de uma sequência de n valores ( x1, x2, ..., xn ), multiplica-se esses valores e, em seguida, extrai-se a raiz n-ésima desse produto:
B26: que pode ser escrita como
H27: (2)
B28: onde ∏ᵢ₌₁ⁿ xᵢ indica que os valores são combinados por multiplicação, e n representa o número de observações, sendo utilizado como o índice da raiz que normaliza o produto para a escala original dos dados.
B29: Exemplo 2
B30: Considere os fatores de crescimento de vendas de guarda-chuvas ao longo dos meses. Como cada variação incide sobre o resultado anterior, deseja-se uma taxa média única que represente essa evolução tratando todos os meses com igual relevância
B31: Pergunta central: Qual é a média de vendas no período?
B32: Cálculo por Etapas
B33: Produtório Valores | C33: =PRODUCT(dados!M3:M20) -> 1.880172 | E33: A média geométrica é sensível à volatilidade e a valores nulos. Suaviza o efeito de valores atípicos, sendo uma medida mais conservadora e realista do crescimento acumulado
B34: Tamanho Amostra | C34: =COUNT(dados!$M$3:$M$20) -> 18
B35: xgeo (manual) | C35: =POWER(C33,1/C34) -> 1.0356981
B36: Cálculo Direto
B37: xgeo (manual) | C37: =POWER(PRODUCT(dados!M2:M20),1/COUNT(dados!M2:M20)) -> 1.0356981
B38: xgeo (função) | C38: =GEOMEAN(dados!M2:M20) -> 1.0356981
B40: Média Harmônica
B41: A média harmônica é mais adequada quando desejamos calcular a média de grandezas inversas, como velocidade (km/h) ou densidade populacional (hab/km²).
B42: A média harmônica xh de números reais positivos x1, x2, ..., xn é definida por
H43: (3)
B44: onde ∑ᵢ₌₁ⁿ 1/xᵢ representa a soma dos inversos dos valores observados (x₁, x₂, …, xₙ), e n corresponde ao número total de observações consideradas no cálculo, sendo utilizado para obter a taxa média efetiva.
B45: Exemplo 3
B46: Considere o custo de aquisição por unidade vendida sob um investimento fixo mensal de marketing. Como o volume de vendas oscila drasticamente entre meses secos e chuvosos, deseja-se uma taxa que represente o custo médio real por guarda-chuva, ponderando cada período pelo seu volume de vendas.
B47: Pergunta central: Qual é o custo médio por unidade que reflete o gasto total sobre a produção total do período?
B48: Cálculo por Etapas
B49: Tamanho Amostra | C49: =COUNT(dados!$N$2:$N$20) -> 19
B50: Somatório | C50: =SUMPRODUCT(1/dados!N2:N20) -> 19.500667 | D50: un/R$ | E50: A média harmônica é sensível a valores baixos e mais robusta para taxas e razões, pois preserva as relações entre os dados.
B51: xhrm (manual) | C51: =C49/C50 -> 0.97432566 | D51: R$/un
B52: Cálculo Direto
B53: xhrm (manual) | C53: =COUNT(dados!$N$2:$N$20)/SUMPRODUCT(1/dados!N2:N20) -> 0.97432566 | D53: R$/un
B54: xhrm (função) | C54: =HARMEAN(dados!N2:N20) -> 0.97432566 | D54: R$/un
B56: Média Aritimética Ponderada
B57: Há aplicações em que determinados valores de um conjunto de dados são considerados mais importantes do que outros. De forma geral, para uma sequência de n valores x1, x2, …, xn e seus respectivos pesos w1, w2, ..., wn, a média (aritmética) ponderada é dada por
H58: (4)
B59: onde ∑ᵢ₌₁ⁿ wᵢxᵢ representa a soma dos valores observados ponderados por seus respectivos pesos, e ∑ᵢ₌₁ⁿ wᵢ corresponde à soma total dos pesos, que normaliza o resultado de acordo com a importância relativa de cada observação.
B60: Exemplo 4
B61: Considere o conjunto de dados de unidades vendidas de guarda-chuvas por mês. Nem todos os meses têm a mesma importância para a análise do negócio, como por exemplo, meses mais chuvosos são mais relevantes para o faturamento.
B62: Pergunta central: Qual é a média de unidades vendidas de guarda-chuvas considerando que meses mais chuvosos devem ter maior impacto na análise do negócio?
B63: Cálculo por Etapas
B64: Somatório Num. | C64: =SUMPRODUCT(dados!E2:E20,dados!O2:O20) -> 95243 | D64: un/mês | E64: A média ponderada atribui maior importância aos meses mais chuvosos, refletindo melhor a relevância desses períodos para o faturamento.
B65: Somatório Pesos | C65: =SUM(dados!O2:O20) -> 28
B66: xpon (manual) | C66: =SUMPRODUCT(dados!E2:E20,dados!O2:O20)/SUM(dados!O2:O20) -> 3401.5357 | D66: un/mês
B68: Média Geométrica Ponderada
B69: A média geométrica ponderada para os números reais positivos x1, x2, …, xn é definida pela seguinte equação:
H70: (5)
B71: onde ∏ᵢ₌₁ⁿ xᵢʷᵢ representa o produto dos valores observados elevados aos seus respectivos pesos, e ∑ᵢ₌₁ⁿ wᵢ corresponde à soma dos pesos, sendo utilizada no expoente para normalizar o produto e obter um valor representativo na mesma escala dos dados originais.
B72: Exemplo 5
B73: Considere os fatores de crescimento de vendas de guarda-chuvas e a precipitação mensal. Como os meses chuvosos são mais relevantes para a estratégia, deseja-se uma taxa média única que incorpore essa diferença de importância entre os períodos.
B74: Pergunta central: Qual é a taxa única de variação mensal que melhor representa a performance real da empresa nesse período?
B75: Cálculo por Etapas
B76: Produtório | C76: =PRODUCT(dados!Q3:Q20) -> 5.5338288
B77: Expoente | C77: =1/SUM(dados!O3:O20) -> 0.037037037
B78: xgpn (manual) | C78: =C76^C77 -> 1.0654166
B79: Cálculo Direto
B80: xgpn (manual) | C80: {=POWER(PRODUCT(POWER(dados!M3:dados!M20,dados!O3:dados!O20)),1/SUM(dados!O3:dados!O20))} -> 1.0654166 | D80: Uso da função ARRAY() para conjunto de dados das multiplicações
C81: =EXP(SUMPRODUCT(LN(dados!M3:dados!M20), dados!O3:dados!O20) / SUM(dados!O3:dados!O20)) -> 1.0654166 | D81: Uso da regra do logaritmo: ln(a⋅b)=ln(a)+ln(b)
B83: Média Harmôníca Ponderada
B84: A média harmônica ponderada para os números reais positivos x1, x2, …, xn é definida pela seguinte equação:
H85: (6)
B87: Exemplo 6
B88: Considere o custo unitário de aquisição de clientes em meses com investimento fixo de marketing. Como meses com volumes de vendas diferentes impactam o custo total de forma desigual, deseja-se uma taxa média que pondere esses custos pela quantidade de unidades vendidas em cada período.
B89: Pergunta central: Qual é o custo médio por unidade no período, considerando que o investimento foi fixo e que os meses de maior volume de vendas devem ter maior peso na média final?
B90: Cálculo por Etapas
B91: Somatório Pesos | C91: =SUM(dados!O2:O20) -> 28
B92: Somatório Divisões | C92: =SUMPRODUCT(dados!O2:O20,1/dados!N2:N20) -> 31.747667
B93: xhpn (manual) | C93: =C91/C92 -> 0.88195458
B94: Cálculo Direto
B95: xhpn (manual) | C95: =SUM(dados!O2:O20)/SUMPRODUCT(dados!O2:O20,1/dados!N2:N20) -> 0.88195458
B97: Saiba mais
B98: Média Generalizada
B99: Média Harmônica
B100: Média Geométrica
B101: Média Aritmética
B102: Média Quadrática
B104: Citação
B105: Estas aulas são baseadas no projeto de e-learning SOGA-Py que foi desenvolvido no Departamento de Ciências da Terra por Annette Rudolph, Joachim Krois e Kai Hartmann. O contato pode ser realizado por e-mail, pelo endereço soga[at]zedat.fu-berlin.de.
B107: Você pode utilizar este projeto livremente sob a Licença Creative Commons Atribuição-CompartilhaIgual 4.0 Internacional.
B108: Por favor, cite da seguinte forma: Rudolph, A., Krois, J., Hartmann, K. (2023): Estatística e Análise de Geodados usando Python (SOGA-Py). Departamento de Ciências da Terra, Universidade Livre de Berlim.

Sheet Página6
B2: Mediana
B3: Outra medida de tendência central muito importante é a mediana. A mediana é o valor do termo central de um conjunto de dados que foi ordenado em ordem crescente. Assim, a mediana divide um conjunto de dados ordenado em duas partes iguais.
B4: O cálculo da mediana consiste nos dois passos a seguir:
B5: 1. Ordenar o conjunto de dados em ordem crescente.
B6: 2. Identificar o termo central. O valor desse termo é a mediana.
B7: Observe que, se o número de observações em um conjunto de dados for ímpar, a mediana é dada pelo valor do termo central dos dados ordenados. Entretanto, se o número de observações for par, a mediana é dada pela média aritmética dos valores dos dois termos centrais (Mann, 2012).
B8: Seja x1, x2, ..., xn um conjunto de observações reais, e seja x1 ≤ x2, ..., ≤ xn a amostra ordenada em ordem crescente, a mediana é definida por
H9: (7)
B10: onde n representa o tamanho da amostra.
B11: Exemplo 7a
B12: Considere o conjunto de dados de unidades vendidas de guarda-chuvas por mês ao longo de um determinado período, no qual as vendas variam entre meses devido a fatores sazonais e operacionais.
B13: Pergunta central: Qual valor mensal de unidades vendidas considerado representativo do período analisado?
B14: Cálculo por Etapas
B15: Tamanho Amostra | C15: =COUNT(dados!E2:E32) -> 31
B16: Posição x(n+1/2) | C16: =(C15+1)/2 -> 16
B17: Mediana (manual) | C17: {=INDEX(dados!R2:R20,C16)} -> 2771
B18: Cálculo Direto
B19: Mediana (manual) | C19: {=INDEX(dados!R2:R32,(COUNT(dados!E2:E32)+1)/2)} -> 2771
B20: Mediana (função) | C20: =MEDIAN(dados!E2:E20) -> 2771
B21: Média (função) | C21: =AVERAGE(dados!E2:E20) -> 3079.0526
B22: Exemplo 7b | D22: Fig. 13 - Histograma das unidades vendidas. Observe a posição da média e da mediana no histograma. Note que o valor discrepante da classe [5500, 6500) puxa mais a média do que a mediana.
B23: Considere o conjunto de dados de unidades vendidas de guarda-chuvas por mês ao longo de um determinado período, no qual as vendas variam entre meses devido a fatores sazonais e operacionais.
B24: Pergunta central: Qual valor mensal de unidades vendidas considerado representativo do período de 2024?
B25: Cálculo por Etapas
B26: Tamanho Amostra | C26: =COUNT(dados!R9:R20) -> 12
B27: Posição x(n/2) | C27: =C26/2 -> 6
B28: Posição x(n/2+1) | C28: =C27+1 -> 7
B29: Elemento x(n/2) | C29: {=INDEX(dados!U2:U13,C27)} -> 2514
B30: Elemento x(n/2+1) | C30: {=INDEX(dados!U2:U13,C28)} -> 2771
B31: Mediana (manual) | C31: =(C29+C30)/2 -> 2642.5
B32: Cálculo Direto
B33: Mediana (manual) | C33: {=(INDEX(dados!U2:U13,COUNT(dados!U2:U13)/2)+INDEX(dados!U2:U13,(COUNT(dados!U2:U108)/2)+1))/2} -> 2642.5
B34: Mediana (função) | C34: =MEDIAN(dados!E9:E20) -> 2642.5 | D34: Fig. 14 - Distribuição das unidades vendidas. Observe a robustez da mediana e sensibilidade da média aos valores atípicos como os meses e out/23 e nov/24.
B35: Média (função) | C35: =AVERAGE(dados!E9:E20) -> 3051.6667
B37: Saiba mais
B38: Média Aritmética
B39: Mediana
B40: Valor Atípico (Outlier)
B42: Citação
B43: Estas aulas são baseadas no projeto de e-learning SOGA-Py que foi desenvolvido no Departamento de Ciências da Terra por Annette Rudolph, Joachim Krois e Kai Hartmann. O contato pode ser realizado por e-mail, pelo endereço soga[at]zedat.fu-berlin.de.
B45: Você pode utilizar este projeto livremente sob a Licença Creative Commons Atribuição-CompartilhaIgual 4.0 Internacional.
B46: Por favor, cite da seguinte forma: Rudolph, A., Krois, J., Hartmann, K. (2023): Estatística e Análise de Geodados usando Python (SOGA-Py). Departamento de Ciências da Terra, Universidade Livre de Berlim.

Sheet Página7
B2: Moda
B3: Em Estatística, a moda representa o valor mais comum em um conjunto de dados. Portanto, a moda é o valor que ocorre com maior frequência em um conjunto de dados (Mann, 2012). Em termos de uma distribuição gráfica de frequências, a moda corresponde ao(s) pico(s) do gráfico.
B4: Uma limitação importante da moda é que um conjunto de dados pode não possuir moda ou pode possuir mais de uma moda, enquanto sempre haverá apenas uma média e apenas uma mediana. Por exemplo, um conjunto de dados no qual cada valor ocorre apenas uma vez não possui moda. Um conjunto de dados em que apenas um valor ocorre com a maior frequência possui uma única moda; nesse caso, o conjunto de dados é denominado unimodal. Um conjunto de dados com dois valores que ocorrem com maior frequência possui duas modas; a distribuição, nesse caso, é dita bimodal. Se mais de dois valores em um conjunto de dados ocorrerem com a maior frequência, então o conjunto possui mais de duas modas e é classificado como multimodal (Mann, 2012).
B5: Considere uma amostra x1, x2, ..., xn e o conjunto dos valores distintos observados S={v1, v2 ,…, vk}. Defina a frequência absoluta de um valor v ∈ S por
B7: onde 1{xi=v} é a função indicadora, igual a 1 se xi=v e 0 caso contrário.
B8: A moda é definida como o conjunto dos valores que maximizam a frequência:
H9: (8)
B10: Interpretação por casos
B11: Se |Mo⁡(X)∣=0|, diz-se que não há moda.
B12: Se |Mo⁡(X)|=1, a distribuição é unimodal e a moda é o único elemento desse conjunto.
B13: Se |Mo⁡(X)|=2, a distribuição é bimodal.
B14: Se |Mo⁡(X)∣>2|, a distribuição é multimodal.
B27: Figura 15 – Distribuições unimodal, bimodal e multimodal. A figura ilustra distribuições de frequência com uma, duas e mais de duas modas, evidenciadas pelos picos da curva. Observa-se que a moda corresponde aos máximos locais da distribuição e pode não ser única. Fonte: Adaptado de Freie Universität Berlin, SOGA – The Mode.
B28: Exemplo 8
B29: Considere o conjunto de dados de temperatura média mensal, uma variável quantitativa discreta, observada ao longo do período analisado no dataset de guarda-chuvas.
B30: Pergunta central: Qual ou quais valores de temperatura ocorrem com maior frequência no período analisado?
B31: Cálculo por Etapas
B32: Valores Únicos | C32: Ordenados | D32: Frequência | E32: Moda | F32: Quantidade | G32: Tipo
B33: {=UNIQUE(dados!C2:C32)} -> 26 | C33: {=SORT(B33:B52)} -> 3 | D33: =COUNTIF(dados!$C$2:$C$32, C33) -> 1 | E33: =IFERROR(__xludf.DUMMYFUNCTION("FILTER(C33:C52,D33:D52=MAX(D33:D52))"),18.0) -> 18 | F33: =COUNT(E33:E52) -> 3 | G33: =IF(F33=0,"Não há moda",IF(F33=1,"Unimodal",IF(F33=2,"Bimodal","Multimodal"))) -> Multimodal
B34: 28 | C34: 4 | D34: =COUNTIF(dados!$C$2:$C$32, C34) -> 2 | E34: =IFERROR(__xludf.DUMMYFUNCTION("""COMPUTED_VALUE"""),26.0) -> 26
B35: 29 | C35: 5 | D35: =COUNTIF(dados!$C$2:$C$32, C35) -> 1 | E35: =IFERROR(__xludf.DUMMYFUNCTION("""COMPUTED_VALUE"""),30.0) -> 30
B36: 18 | C36: 6 | D36: =COUNTIF(dados!$C$2:$C$32, C36) -> 1
B37: 14 | C37: 7 | D37: =COUNTIF(dados!$C$2:$C$32, C37) -> 1
B38: 13 | C38: 8 | D38: =COUNTIF(dados!$C$2:$C$32, C38) -> 2
B39: 10 | C39: 10 | D39: =COUNTIF(dados!$C$2:$C$32, C39) -> 1
B40: 4 | C40: 11 | D40: =COUNTIF(dados!$C$2:$C$32, C40) -> 1
B41: 3 | C41: 12 | D41: =COUNTIF(dados!$C$2:$C$32, C41) -> 2
B42: 6 | C42: 13 | D42: =COUNTIF(dados!$C$2:$C$32, C42) -> 2
B43: 12 | C43: 14 | D43: =COUNTIF(dados!$C$2:$C$32, C43) -> 1
B44: 19 | C44: 15 | D44: =COUNTIF(dados!$C$2:$C$32, C44) -> 1
B45: 30 | C45: 17 | D45: =COUNTIF(dados!$C$2:$C$32, C45) -> 1
B46: 31 | C46: 18 | D46: =COUNTIF(dados!$C$2:$C$32, C46) -> 3
B47: 15 | C47: 19 | D47: =COUNTIF(dados!$C$2:$C$32, C47) -> 2
... B50: 7 | C50: 29 | D50: =COUNTIF(dados!$C$2:$C$32, C50) -> 1
B51: 11 | C51: 30 | D51: =COUNTIF(dados!$C$2:$C$32, C51) -> 3 | E51: Fig. 16 - Distribuição das frequência de temperatura. Identificação das modas na distribuição da temperatura no período.
B52: 17 | C52: 31 | D52: =COUNTIF(dados!$C$2:$C$32, C52) -> 1
B53: Cálculo por Tabela Dinâmica
B54: Valores Únicos | C54: Frequência | D54: Moda | E54: Quantidade | F54: Tipo
B55: =dados!Y17 -> 3 | C55: =dados!Z17 -> 1 | D55: =IFERROR(__xludf.DUMMYFUNCTION("FILTER(B55:B74,C55:C74=MAX(C55:C74))"),18.0) -> 18 | E55: =COUNT(D55:D75) -> 3 | F55: =IF(E55=0,"Não há moda",IF(E55=1,"Unimodal",IF(E55=2,"Bimodal","Multimodal"))) -> Multimodal
B56: =dados!Y18 -> 4 | C56: =dados!Z18 -> 2 | D56: =IFERROR(__xludf.DUMMYFUNCTION("""COMPUTED_VALUE"""),26.0) -> 26
B57: =dados!Y19 -> 5 | C57: =dados!Z19 -> 1 | D57: =IFERROR(__xludf.DUMMYFUNCTION("""COMPUTED_VALUE"""),30.0) -> 30
B58: =dados!Y20 -> 6 | C58: =dados!Z20 -> 1
B59: =dados!Y21 -> 7 | C59: =dados!Z21 -> 1
B60: =dados!Y22 -> 8 | C60: =dados!Z22 -> 2
B61: =dados!Y23 -> 10 | C61: =dados!Z23 -> 1
B62: =dados!Y24 -> 11 | C62: =dados!Z24 -> 1
B63: =dados!Y25 -> 12 | C63: =dados!Z25 -> 2
B64: =dados!Y26 -> 13 | C64: =dados!Z26 -> 2
B65: =dados!Y27 -> 14 | C65: =dados!Z27 -> 1
B66: =dados!Y28 -> 15 | C66: =dados!Z28 -> 1
B67: =dados!Y29 -> 17 | C67: =dados!Z29 -> 1
B68: =dados!Y30 -> 18 | C68: =dados!Z30 -> 3
B69: =dados!Y31 -> 19 | C69: =dados!Z31 -> 2
... B72: =dados!Y34 -> 29 | C72: =dados!Z34 -> 1
B73: =dados!Y35 -> 30 | C73: =dados!Z35 -> 3 | D73: Fig. 17 - Distribuição da temperatura. Identificação das modas na distribuição da temperatura no período.
B74: =dados!Y36 -> 31 | C74: =dados!Z36 -> 1
B75: =dados!Y37 -> Total geral | C75: =dados!Z37 -> 31
B76: Cálculo Direto
B77: Moda Única | C77: =MODE(dados!C2:C20) -> 26 | D77: Ao contrário da média e da mediana, a moda pode ser aplicada tanto a dados quantitativos (numéricos) quanto a dados qualitativos (categóricos)
B78: Moda Múlipla | C78: {=_xlfn.MODE.MULT(dados!C2:C20)} -> 13
C79: 19
C80: 26
B92: Fig. 18 - Distribuição das frequência de temperatura. Identificação das modas na distribuição da temperatura no período usando um hsitograma com largura de classe 1.
B95: Saiba mais
B96: Moda
B97: Sumário Estatístico
B99: Citação
B100: Estas aulas são baseadas no projeto de e-learning SOGA-Py que foi desenvolvido no Departamento de Ciências da Terra por Annette Rudolph, Joachim Krois e Kai Hartmann. O contato pode ser realizado por e-mail, pelo endereço soga[at]zedat.fu-berlin.de.
B102: Você pode utilizar este projeto livremente sob a Licença Creative Commons Atribuição-CompartilhaIgual 4.0 Internacional.
B103: Por favor, cite da seguinte forma: Rudolph, A., Krois, J., Hartmann, K. (2023): Estatística e Análise de Geodados usando Python (SOGA-Py). Departamento de Ciências da Terra, Universidade Livre de Berlim.

Sheet Página8
B2: Medidas de Dispersão
B3: As medidas de tendência central, como a média, a mediana e a moda, não revelam todo o panorama da distribuição de um conjunto de dados. Dois conjuntos de dados com a mesma média podem apresentar dispersões completamente diferentes. A variação entre os valores das observações de um conjunto de dados pode ser muito maior ou muito menor do que a de outro conjunto. Assim, a média, a mediana ou a moda, isoladamente, geralmente não são suficientes para revelar a forma da distribuição de um conjunto de dados. Também é necessária uma medida que forneça informações sobre a variação entre os valores dos dados. Essas medidas são chamadas de medidas de dispersão. As medidas de tendência central e de dispersão, quando consideradas em conjunto, fornecem uma descrição mais completa de um conjunto de dados do que as medidas de tendência central isoladamente (Mann, 2012).
B5: Saiba mais
B6: Medidas de Dispersão
B8: Citação
B9: Estas aulas são baseadas no projeto de e-learning SOGA-Py que foi desenvolvido no Departamento de Ciências da Terra por Annette Rudolph, Joachim Krois e Kai Hartmann. O contato pode ser realizado por e-mail, pelo endereço soga[at]zedat.fu-berlin.de.
B11: Você pode utilizar este projeto livremente sob a Licença Creative Commons Atribuição-CompartilhaIgual 4.0 Internacional.
B12: Por favor, cite da seguinte forma: Rudolph, A., Krois, J., Hartmann, K. (2023): Estatística e Análise de Geodados usando Python (SOGA-Py). Departamento de Ciências da Terra, Universidade Livre de Berlim.

Sheet Página9
B2: Variânca e Desvio Padrão
B3: A variância é a média dos quadrados dos desvios em relação à média. A variância para dados populacionais é denotada por σ² (lê-se sigma ao quadrado) e a variância calculada para dados amostrais é denotada por s². Matematicamente, tem-se:
H4: (9)
B5: e
H6: (10)
B7: onde σ² é chamada de variância populacional e s² é a variância amostral. A quantidade xi​−μ, respectivamente xi​−xˉ, nas expressões acima, é denominada desvio do valor xi (x1,x2,…,xn) em relação à média (Mann, 2012).
B16: Fig. 19 – Desvios da precipitação em relação à média e graus de liberdade. A figura ilustra os desvios das observações em relação à média amostral, evidenciando que os desvios positivos e negativos se compensam de modo que sua soma é sempre nula. Nesta caso, essa restrição implica que, embora existam n=19 desvios, apenas n−1=18 podem variar livremente, caracterizando 18 graus de liberdade associados aos desvios. Essa perda de um grau de liberdade justifica o uso do denominador n−1 na variância amostral, conhecido como correção de Bessel, garantindo uma estimativa não viesada da variância populacional.
B27: Fig. 20 – Desvios padronizados das variáveis climáticas e de vendas ao longo das observações. A figura apresenta o gráfico de dispersão dos desvios padronizados da precipitação, temperatura, velocidade do vento e unidades vendidas, calculados em relação às respectivas médias e desvios padrão. O eixo horizontal representa o identificador das observações, enquanto o eixo vertical mostra os valores padronizados no intervalo de −3 a 3, permitindo a comparação direta entre variáveis originalmente expressas em unidades distintas. Observa-se que, após a padronização, todas as variáveis passam a oscilar em torno de zero, evidenciando diferenças relativas de dispersão e destacando observações mais afastadas da média em termos de número de desvios padrão.
B28: O desvio padrão é a medida de dispersão mais utilizada. O valor do desvio padrão indica o quão próximos os valores de um conjunto de dados estão agrupados em torno da média. Em geral, um valor menor de desvio padrão indica que os valores do conjunto de dados estão distribuídos em um intervalo relativamente menor em torno da média. Em contraste, um valor maior de desvio padrão indica que os valores do conjunto de dados estão distribuídos em um intervalo relativamente maior em torno da média (Mann, 2012).
B29: O desvio padrão é obtido tomando-se a raiz quadrada da variância. Consequentemente, o desvio padrão calculado para dados populacionais é denotado por σ, e o desvio padrão calculado para dados amostrais é denotado por s.
H30: (11)
B31: e
H32: (12)
B33: onde σ é o desvio padrão da população e s é o desvio padrão da amostra.
B34: Exemplo 9
B35: Como exercício, calculamos a média, a mediana, a variância e o desvio padrão para algumas variáveis numéricas de interesse do conjunto de dados sobre as vendas mensais de guarda-chuvas, apresentando os resultados de forma organizada e clara.
B36: Cálculo por Etapas para Uma Variável
B37: =dados!A1 -> Mês | C37: Venda Mensal | D37: Desvio Quad. | F37: Resumo para variável Venda
B38: =dados!A2 -> 45078 | C38: =dados!E2 -> 1861 | D38: =(C38-$G$39)^2 -> 1483652.2 | F38: n (amostra) | G38: =COUNT(C38:C56) -> 19 | H38: un/mês
B39: =dados!A3 -> 45109 | C39: =dados!E3 -> 1745 | D39: =(C39-$G$39)^2 -> 1779696.4 | F39: Média (amostra) | G39: =SUM(C38:C56)/COUNT(C38:C56) -> 3079.0526 | H39: un/mês2
B40: =dados!A4 -> 45140 | C40: =dados!E4 -> 1977 | D40: =(C40-$G$39)^2 -> 1214520 | F40: s2 (manual) | G40: =SUM(D38:D56)/(G38-1) -> 1427114.3 | H40: un/mês2
B41: =dados!A5 -> 45171 | C41: =dados!E5 -> 3908 | D41: =(C41-$G$39)^2 -> 687153.74 | F41: s (manual) | G41: =SQRT(G40) -> 1194.6189 | H41: un/mês
B42: =dados!A6 -> 45202 | C42: =dados!E6 -> 5325 | D42: =(C42-$G$39)^2 -> 5044279.6
B43: =dados!A7 -> 45233 | C43: =dados!E7 -> 4098 | D43: =(C43-$G$39)^2 -> 1038253.7
B44: =dados!A8 -> 45264 | C44: =dados!E8 -> 2968 | D44: =(C44-$G$39)^2 -> 12332.687
B45: =dados!A9 -> 45295 | C45: =dados!E9 -> 2771 | D45: =(C45-$G$39)^2 -> 94896.424
B46: =dados!A10 -> 45326 | C46: =dados!E10 -> 2097 | D46: =(C46-$G$39)^2 -> 964427.37
B47: =dados!A11 -> 45357 | C47: =dados!E11 -> 2254 | D47: =(C47-$G$39)^2 -> 680711.84
B48: =dados!A12 -> 45388 | C48: =dados!E12 -> 2978 | D48: =(C48-$G$39)^2 -> 10211.634
B49: =dados!A13 -> 45419 | C49: =dados!E13 -> 2514 | D49: =(C49-$G$39)^2 -> 319284.48
B50: =dados!A14 -> 45450 | C50: =dados!E14 -> 2205 | D50: =(C50-$G$39)^2 -> 763968
B51: =dados!A15 -> 45481 | C51: =dados!E15 -> 1979 | D51: =(C51-$G$39)^2 -> 1210115.8
B52: =dados!A16 -> 45512 | C52: =dados!E16 -> 2358 | D52: =(C52-$G$39)^2 -> 519916.9
B53: =dados!A17 -> 45543 | C53: =dados!E17 -> 3490 | D53: =(C53-$G$39)^2 -> 168877.74
... B56: =dados!A20 -> 45636 | C56: =dados!E20 -> 3499 | D56: =(C56-$G$39)^2 -> 176355.79
B57: Cálculo Direto
B58: Variável | C58: Mínimo | D58: Máximo | E58: Média | F58: Mediana | G58: Variância | H58: Desvio Padrão
B59: Precip. (mm) | C59: =MIN(dados!B2:B32) -> 42 | D59: =MAX(dados!B2:B32) -> 120 | E59: =AVERAGE(dados!B2:B32) -> 78.548387 | F59: =MEDIAN(dados!B2:B32) -> 80 | G59: =VARA(dados!B2:B32) -> 513.45591 | H59: =STDEVA(dados!B2:B32) -> 22.659566
B60: Temp. (oC) | C60: =MIN(dados!C2:C32) -> 3 | D60: =MAX(dados!C2:C32) -> 31 | E60: =AVERAGE(dados!C2:C32) -> 16.451613 | F60: =MEDIAN(dados!C2:C32) -> 15 | G60: =VARA(dados!C2:C32) -> 81.789247 | H60: =STDEVA(dados!C2:C32) -> 9.0437408
B61: Vento (km/h) | C61: =MIN(dados!D2:D32) -> 10 | D61: =MAX(dados!D2:D32) -> 30 | E61: =AVERAGE(dados!D2:D32) -> 16.774194 | F61: =MEDIAN(dados!D2:D32) -> 16 | G61: =VARA(dados!D2:D32) -> 24.847312 | H61: =STDEVA(dados!D2:D32) -> 4.9847078
B62: Venda (mês) | C62: =MIN(dados!E2:E32) -> 1745 | D62: =MAX(dados!E2:E32) -> 5920 | E62: =AVERAGE(dados!E2:E32) -> 3107.4839 | F62: =MEDIAN(dados!E2:E32) -> 2771 | G62: =VARA(dados!E2:E32) -> 1417265.3 | H62: =STDEVA(dados!E2:E32) -> 1190.4895
B63: Teorema de Chebyshev
B64: Ao utilizar a média e o desvio padrão, podemos determinar a proporção ou porcentagem do total de observações que se encontram dentro de um determinado intervalo em torno da média. O teorema de Chebyshev fornece um limite inferior para a proporção de dados contida entre dois pontos que estão em lados opostos da média e à mesma distância dela.
B65: Para qualquer número k maior que 1, pelo menos 1−1/k² dos valores dos dados estão situados a até k desvios padrão da média.
G67: O teorema aplica-se tanto a dados amostrais quanto a dados populacionais. Observe que o teorema de Chebyshev é válido para distribuições de qualquer forma. Entretanto, ele só pode ser utilizado para valores de k maiores que 1. Isso ocorre porque, quando k = 1, o valor de (1 − 1/k²) é zero, e quando k < 1, o valor de (1 − 1/k²) é negativo (Mann, 2012).
B79: Fig. 21 – Proporção mínima de dados dentro de k desvios padrão segundo o Teorema de Chebyshev. A figura apresenta a relação entre o valor de k e a proporção mínima 1−1/k^2 dos dados contida no intervalo [μ−kσ, μ+kσ], conforme o Teorema de Chebyshev. Observa-se que a proporção mínima aumenta monotonicamente com k e que o teorema só é aplicável para k>1, pois para k=1 o limite inferior é zero.
B80: Regra Empírica
B81: Enquanto o teorema de Chebyshev é aplicável a distribuições de qualquer forma, a regra empírica aplica-se apenas a um tipo específico de distribuição, chamada distribuição em forma de sino ou distribuição normal. Essa regra estabelece três resultados aproximados:
G83: Para uma distribuição em forma de sino, aproximadamente:
G84: - 68% das observações estão dentro de um desvio padrão em relação à média;
G87: - 95% das observações estão dentro de dois desvios padrão em relação à média;
G90: - 99,7% das observações estão dentro de três desvios padrão em relação à média.
B95: Fig. 22 – Regra empírica aplicada à distribuição normal padrão. A figura apresenta o histograma de densidade de uma distribuição em forma de sini (normal padrão), evidenciando a regra empírica. Observa-se que aproximadamente 68% das observações estão contidas no intervalo de um desvio padrão em torno da média, cerca de 95% dentro de dois desvios padrão e aproximadamente 99,7% dentro de três desvios padrão. Esses resultados ilustram o comportamento típico de uma distribuição normal em forma de sino e a concentração progressiva dos dados em torno da média à medida que o intervalo em desvios padrão é ampliado.
B96: Exemplo 10
B97: Para obter uma visão geral da forma da distribuição de cada variável numérica, utilizamos gráficos do tipo histograma. Esse tipo de gráfico permite visualizar a frequência (ou densidade) dos valores ao longo de intervalos definidos, facilitando a análise da dispersão, da simetria e da presença de valores extremos
B115: Fig. 23 – Histogramas das variáveis precipitação, temperatura, vento e vendas mensais. A figura apresenta os histogramas das variáveis precipitação, temperatura, velocidade do vento e vendas mensais de guarda-chuvas, permitindo avaliar a forma das distribuições, a dispersão e a presença de assimetria ou valores extremos. Dessa forma, os histogramas indicam que a aplicação direta da regra empírica é limitada, sendo mais adequada apenas como referência qualitativa, especialmente para a variável temperatura. Para as demais variáveis, a assimetria observada sugere cautela na interpretação baseada em normalidade, reforçando a importância da análise gráfica antes da aplicação de pressupostos teóricos.
B116: Variável: Precipitação
C117: Lim. Inf. | D117: Lim. Sup. | E117: Num. Obs. | F117: Proporção
B118: Intervalo 1dp | C118: =E59-H59 -> 55.888821 | D118: =E59+H59 -> 101.20795 | E118: =COUNTIFS(dados!$B$2:$B$32,">="&C118,dados!$B$2:$B$32,"<="&D118) -> 19 | F118: =E118/COUNT(dados!$B$2:$B$32) -> 0.61290323
B119: Intervalo 2dp | C119: =E59-H59*2 -> 33.229256 | D119: =E59+H59*2 -> 123.86752 | E119: =COUNTIFS(dados!$B$2:$B$32,">="&C119,dados!$B$2:$B$32,"<="&D119) -> 31 | F119: =E119/COUNT(dados!$B$2:$B$32) -> 1
B120: Intervalo 3dp | C120: =E59-H59*3 -> 10.56969 | D120: =E59+H59*3 -> 146.52708 | E120: =COUNTIFS(dados!$B$2:$B$32,">="&C120,dados!$B$2:$B$32,"<="&D120) -> 31 | F120: =E120/COUNT(dados!$B$2:$B$32) -> 1
B122: Variável: Temperatura
C123: Lim. Inf. | D123: Lim. Sup. | E123: Num. Obs. | F123: Proporção
B124: Intervalo 1dp | C124: =E60-H60 -> 7.4078721 | D124: =E60+H60 -> 25.495354 | E124: =COUNTIFS(dados!$C$2:$C$32,">="&C124,dados!$C$2:$C$32,"<="&D124) -> 16 | F124: =E124/COUNT(dados!$B$2:$B$32) -> 0.51612903
B125: Intervalo 2dp | C125: =E60-H60*2 -> -1.6358687 | D125: =E60+H60*2 -> 34.539094 | E125: =COUNTIFS(dados!$C$2:$C$32,">="&C125,dados!$C$2:$C$32,"<="&D125) -> 31 | F125: =E125/COUNT(dados!$B$2:$B$32) -> 1
B126: Intervalo 3dp | C126: =E60-H60*3 -> -10.679609 | D126: =E60+H60*3 -> 43.582835 | E126: =COUNTIFS(dados!$C$2:$C$32,">="&C126,dados!$C$2:$C$32,"<="&D126) -> 31 | F126: =E126/COUNT(dados!$B$2:$B$32) -> 1
B128: Saiba mais
B129: Variância
B130: Desvio Padrão
B131: Teorema de Chebyshev
B132: Distribuição Contínua
B134: Citação
B135: Estas aulas são baseadas no projeto de e-learning SOGA-Py que foi desenvolvido no Departamento de Ciências da Terra por Annette Rudolph, Joachim Krois e Kai Hartmann. O contato pode ser realizado por e-mail, pelo endereço soga[at]zedat.fu-berlin.de.
B137: Você pode utilizar este projeto livremente sob a Licença Creative Commons Atribuição-CompartilhaIgual 4.0 Internacional.
B138: Por favor, cite da seguinte forma: Rudolph, A., Krois, J., Hartmann, K. (2023): Estatística e Análise de Geodados usando Python (SOGA-Py). Departamento de Ciências da Terra, Universidade Livre de Berlim.

Sheet Página10
B2: Amplitude
B3: A amplitude é uma medida de dispersão simples de calcular. Ela é definida como a diferença entre o maior e o menor valor de um conjunto de dados {x1, x2, ..., xn}:
H4: (13)
B5: A amplitude, assim como a média, apresenta a desvantagem de ser influenciada por valores extremos. Consequentemente, a amplitude não é uma boa medida de dispersão para conjuntos de dados que contêm valores atípicos (outliers). Outra desvantagem do uso da amplitude como medida de dispersão é que seu cálculo se baseia apenas em dois valores: o maior e o menor. Todos os demais valores do conjunto de dados são ignorados no cálculo da amplitude. Dessa forma, a amplitude não é uma medida de dispersão muito satisfatória (Mann, 2012).
B7: Saiba mais
B8: Amplitude
B10: Citação
B11: Estas aulas são baseadas no projeto de e-learning SOGA-Py que foi desenvolvido no Departamento de Ciências da Terra por Annette Rudolph, Joachim Krois e Kai Hartmann. O contato pode ser realizado por e-mail, pelo endereço soga[at]zedat.fu-berlin.de.
B13: Você pode utilizar este projeto livremente sob a Licença Creative Commons Atribuição-CompartilhaIgual 4.0 Internacional.
B14: Por favor, cite da seguinte forma: Rudolph, A., Krois, J., Hartmann, K. (2023): Estatística e Análise de Geodados usando Python (SOGA-Py). Departamento de Ciências da Terra, Universidade Livre de Berlim.

Sheet Página11
B2: Medidas de Posição
B3: Uma medida de posição determina a posição de um único valor em relação aos demais valores de uma amostra ou de uma população. Diferentemente da média ou do desvio padrão, as medidas descritivas baseadas em não são sensíveis à influência de poucos valores extremos. Por esse motivo, medidas descritivas baseadas em quantis são frequentemente preferidas àquelas baseadas na média e no desvio padrão (Weiss, 2010).
B4: Quantis são pontos de corte que dividem o intervalo dos dados em subintervalos contíguos com probabilidades iguais. Alguns quantis são particularmente importantes: a mediana divide o conjunto de dados em duas partes iguais, os 50% inferiores e os 50% superiores. Os quartis dividem os dados em quatro partes iguais, e os percentis os dividem em centésimos, ou seja, 100 partes iguais. Observe que a mediana corresponde ao 50º percentil. Os decis dividem o conjunto de dados em dez partes iguais, e os quintis em cinco partes iguais. Há sempre um quantil a menos do que o número de grupos formados (por exemplo, existem 3 quartis que dividem os dados em 4 partes iguais).
B5: O cálculo de qualquer medida de posição pode ser expressa em termos da posição relativa de um determinado ponto de corte no conjunto de dados.
B6: Dado um conjunto de dados ordenados x1,x2, … ,xn, a posição Pj da j-ésima medida de posição (também chamada de medida separatriz) pode ser definida por
H7: (13)
B8: onde n representa o número total de observações e m corresponde ao número de partes iguais em que o conjunto de dados é dividido, conforme o tipo de medida de posição considerada (por exemplo, m=4 para quartis, m=10 para decis ou m=100 para percentis).
B9: Se a posição relativa Pj não for inteira, é necessária uma interpolação linear entre os dois valores adjacentes para determinar a medida de posição desejada.
B10: A interpolação linear entre dois pontos (x0, y0) e (x1, y1) pode ser deduzida usando-se proporcionalidade:
H12: (14)
B13: em que x representa a posição fracionária associada à medida de posição, e y corresponde ao valor interpolado da variável de interesse.
B14: Exemplo 10
B15: Com o objetivo de identificar valores extremos de precipitação, analistas decidiram calcular o percentil 95 (P95) da variável precipitação. Esse percentil representa um limite superior a partir do qual apenas aproximadamente 5% das observações apresentam valores mais elevados de precipitação, sendo útil para a caracterização de meses com chuvas excepcionalmente intensas. Observação: Não use a observação referente ao último mês do conjunto de dados.
B16: Cálculo por Etapas
B17: n | C17: =COUNT(dados!B2:B31) -> 30 | D17: (removido dez/25)
B18: m | C18: 100
B19: j | C19: 95
B20: Posição | C20: =C19*(C17+1)/C18 -> 29.45 | D20: =INT(C20) -> 29 | E20: =D20+1 -> 30
B21: Quartil | C21: =D21+(C20-D20)*((E21-D21)/(E20-D20)) -> 30.45 | D21: {=INDEX(dados!$B$206:$B$235,D20,1)} -> 30 | E21: {=INDEX(dados!$B$206:$B$235,E20,1)} -> 31
B22: Cálculo Direto
B23: Variável | C23: P95
B24: Temp. (oC) | C24: =_xlfn.PERCENTILE.EXC(dados!$C$2:$C$32, 0.95) -> 30.4
B26: Saiba mais
B27: Quantis
B28: Interpolação Linear
B30: Citação
B31: Estas aulas são baseadas no projeto de e-learning SOGA-Py que foi desenvolvido no Departamento de Ciências da Terra por Annette Rudolph, Joachim Krois e Kai Hartmann. O contato pode ser realizado por e-mail, pelo endereço soga[at]zedat.fu-berlin.de.
B33: Você pode utilizar este projeto livremente sob a Licença Creative Commons Atribuição-CompartilhaIgual 4.0 Internacional.
B34: Por favor, cite da seguinte forma: Rudolph, A., Krois, J., Hartmann, K. (2023): Estatística e Análise de Geodados usando Python (SOGA-Py). Departamento de Ciências da Terra, Universidade Livre de Berlim.

Sheet Página12
B2: Quartis e Interquartis
B3: Os quartis dividem um conjunto de dados ordenados em quatro partes iguais. Essas três medidas são denominadas primeiro quartil (denotado por Q1), segundo quartil (denotado por Q2) e terceiro quartil (denotado por Q3). O segundo quartil é equivalente à mediana do conjunto de dados. O primeiro quartil corresponde ao valor do termo central entre as observações que são menores do que a mediana, e o terceiro quartil corresponde ao valor do termo central entre as observações que são maiores do que a mediana (Mann, 2012).
B16: Fig. 24 – Representação gráfica dos quartis e da mediana. A figura ilustra a divisão de um conjunto de dados ordenados em quatro partes iguais por meio de três quartis. O primeiro quartil (Q1) delimita os 25% menores valores, a mediana (M ou Q2) divide o conjunto em duas metades iguais, e o terceiro quartil (Q3) separa os 75% menores dos 25% maiores valores. Cada intervalo entre os quantis contém aproximadamente 25% das observações, evidenciando o uso dos quartis como medidas de posição robustas à presença de valores extremos. Fonte: Adaptado de https://www.sigmamagic.com/blogs/what-are-quartiles/ .
B17: Aproximadamente 25% dos valores em um conjunto de dados ordenado são menores que (Q1) e cerca de 75% são maiores que (Q1). O segundo quartil, (Q2), divide um conjunto de dados ordenado em duas partes iguais; portanto, o segundo quartil e a mediana são equivalentes. Aproximadamente 75% dos valores dos dados são menores que (Q3) e cerca de 25% são maiores que (Q3). A diferença entre o terceiro quartil e o primeiro quartil de um conjunto de dados é chamada de interquartil (IQR) (Mann, 2012).
B18: Exemplo 11
B19: Considere o conjunto de dados mensais de vendas de guarda-chuvas, composto pelas variáveis Precipitação, Temperatura, Vento e Vendas. Para cada uma das variáveis do conjunto de dados, construa um resumo estatístico contendo as seguintes medidas: Valor mínimo, Primeiro quartil (Q1), Mediana (Q2), Terceiro quartil (Q3), Valor máximo e Intervalo interquartil (IQR).
B20: Cálculo por Etapas (Variável Preciptação)
B21: n | C21: =COUNT(dados!B2:B32) -> 31
B22: m | C22: 4
B23: j | C23: 1 | D23: 2 | E23: 3
B24: Posição | C24: =C23*($C$21+1)/$C$22 -> 8 | D24: =D23*($C$21+1)/$C$22 -> 16 | E24: =E23*($C$21+1)/$C$22 -> 24
B25: Quartil | C25: {=INDEX(dados!$B$146:$B$176,C24,1)} -> 58 | D25: {=INDEX(dados!$B$146:$B$176,D24,1)} -> 80 | E25: {=INDEX(dados!$B$146:$B$176,E24,1)} -> 92
B26: Cálculo Direto
B27: Variável | C27: Mínimo | D27: Q1 | E27: Q2 | F27: Q3 | G27: Máximo | H27: IQR
B28: Precip. (mm) | C28: =_xlfn.QUARTILE.INC(dados!$B$2:$B$32, 0) -> 42 | D28: =_xlfn.QUARTILE.EXC(dados!$B$2:$B$32, 1) -> 58 | E28: =_xlfn.QUARTILE.EXC(dados!$B$2:$B$32, 2) -> 80 | F28: =_xlfn.QUARTILE.EXC(dados!$B$2:$B$32, 3) -> 92 | G28: =_xlfn.QUARTILE.INC(dados!$B$2:$B$32, 4) -> 120 | H28: =F28-D28 -> 34
B29: Temp. (oC) | C29: =_xlfn.QUARTILE.INC(dados!$C$2:$C$32, 0) -> 3 | D29: =_xlfn.QUARTILE.EXC(dados!$C$2:$C$32, 1) -> 8 | E29: =_xlfn.QUARTILE.EXC(dados!$C$2:$C$32, 2) -> 15 | F29: =_xlfn.QUARTILE.EXC(dados!$C$2:$C$32, 3) -> 26 | G29: =_xlfn.QUARTILE.INC(dados!$C$2:$C$32, 4) -> 31 | H29: =F29-D29 -> 18
B30: Vento (km/h) | C30: =_xlfn.QUARTILE.INC(dados!$D$2:$D$32, 0) -> 10 | D30: =_xlfn.QUARTILE.EXC(dados!$D$2:$D$32, 1) -> 13 | E30: =_xlfn.QUARTILE.EXC(dados!$D$2:$D$32, 2) -> 16 | F30: =_xlfn.QUARTILE.EXC(dados!$D$2:$D$32, 3) -> 19 | G30: =_xlfn.QUARTILE.INC(dados!$D$2:$D$32, 4) -> 30 | H30: =F30-D30 -> 6
B31: Venda (mês) | C31: =_xlfn.QUARTILE.INC(dados!$E$2:$E$32, 0) -> 1745 | D31: =_xlfn.QUARTILE.EXC(dados!$E$2:$E$32, 1) -> 2205 | E31: =_xlfn.QUARTILE.EXC(dados!$E$2:$E$32, 2) -> 2771 | F31: =_xlfn.QUARTILE.EXC(dados!$E$2:$E$32, 3) -> 3650 | G31: =_xlfn.QUARTILE.INC(dados!$E$2:$E$32, 4) -> 5920 | H31: =F31-D31 -> 1445
J36: =_xlfn.PERCENTILE.EXC(dados!B2:B32,0.75) -> 92
B42: Fig. 25 – Distribuição da precipitação mensal por quartis. Observa-se a concentração dos menores valores de precipitação nos quartis inferiores e o deslocamento progressivo da frequência para valores mais elevados nos quartis superiores, evidenciando a variabilidade sazonal do regime pluviométrico ao longo do período analisado.
B44: Saiba mais
B45: Quartis
B46: Interquartil
B47: Teorema de Chebyshev
B48: Distribuição Contínua
B49: Sumário de Cinco Número de Tukey
B51: Citação
B52: Estas aulas são baseadas no projeto de e-learning SOGA-Py que foi desenvolvido no Departamento de Ciências da Terra por Annette Rudolph, Joachim Krois e Kai Hartmann. O contato pode ser realizado por e-mail, pelo endereço soga[at]zedat.fu-berlin.de.
B54: Você pode utilizar este projeto livremente sob a Licença Creative Commons Atribuição-CompartilhaIgual 4.0 Internacional.
B55: Por favor, cite da seguinte forma: Rudolph, A., Krois, J., Hartmann, K. (2023): Estatística e Análise de Geodados usando Python (SOGA-Py). Departamento de Ciências da Terra, Universidade Livre de Berlim.

Sheet Página13
B2: Valos Atípicos (Outliers)
B3: Na análise de dados, a identificação de outliers (valores atípicos), isto é, observações que se afastam significativamente do padrão geral dos dados, é muito importante. Um outlier requer atenção especial. Ele pode ser resultado de um erro de medição ou de registro, uma observação proveniente de uma população diferente ou uma observação extrema incomum. Observe que uma observação extrema não precisa necessariamente ser um outlier; ela pode, em vez disso, ser uma indicação de assimetria da distribuição (Weiss 2010).
B4: Ao observar um outlier, deve-se tentar determinar sua causa. Se o outlier for causado por um erro de medição ou de registro, ou se por algum outro motivo estiver claro que ele não pertence ao conjunto de dados, o outlier pode simplesmente ser removido. No entanto, se não houver uma explicação evidente para o outlier, a decisão de mantê-lo ou não no conjunto de dados constitui um julgamento difícil.
B5: Tradicionalmente, a cerca de Tukey é utilizada como uma ferramenta diagnóstica para a identificação de observações que podem ser consideradas outliers, baseando-se exclusivamente nos quartis e no intervalo interquartil (IQR). Para isso, definem-se o limite inferior e o limite superior de um conjunto de dados. O limite inferior é o valor que se encontra 1,5 vezes o IQR abaixo do primeiro quartil; o limite superior é o valor que se encontra 1,5 vezes o IQR acima do terceiro quartil. Observações que estejam abaixo do limite inferior ou acima do limite superior são consideradas potenciais outliers (Weiss 2010).
B6: Sejam Q1 o primeiro quartil, Q3 o terceiro quartil e IQR=Q3−Q1. O limite inferior L é definido como:
J7: (15)
B8: e o limite superior U é definido como
J9: (16)
B10: Um boxplot, também chamado de diagrama de caixa e bigodes, baseia-se no resumo de cinco números e pode ser utilizado para fornecer uma representação gráfica da posição central e da variabilidade de um conjunto de dados. Esses diagramas foram introduzidos pelo matemático John Wilder Tukey. Diversos tipos de boxplots são comumente utilizados.
B11: Os diagramas de caixa e bigodes fornecem uma representação gráfica dos dados utilizando cinco medidas: a mediana, o primeiro quartil, o terceiro quartil, bem como o menor e o maior valor situados entre os limites inferior e superior do conjunto de dados. O espaçamento entre as diferentes partes da caixa indica o grau de dispersão e de assimetria dos dados. É possível comparar diferentes distribuições construindo boxplots para cada uma delas, além de facilitar a identificação de outliers (Mann 2012). Os boxplots podem ser construídos tanto na orientação horizontal quanto vertical.
B30: Fig. 26 – Boxplot horizontal e assimetria da distribuição. O diagrama de caixa e bigodes ilustra a relação entre quartis, mediana e valores extremos para distribuições com assimetria negativa (à esquerda) e positiva (à direita). A posição relativa da mediana dentro da caixa, o comprimento desigual dos bigodes adjacentes e a presença de outliers indicam o sentido e o grau de assimetria da distribuição, em correspondência com o formato da função densidade de probabilidade associada.
B31: Exemplo 12
B32: Uma empresa varejista que comercializa guarda-chuvas analisa mensalmente variáveis climáticas e de mercado, principalmente precipitação, temperatura, vento e vendas. Para garantir a qualidade da análise estatística, é necessário identificar observações potencialmente atípicas que possam distorcer futuras decisões de negócio.
B33: Rótulos | C33: Mínimo | D33: Q1 | E33: Q2 | F33: Q3 | G33: Máximo | H33: Lim. Inf. | I33: Lim. Sup. | J33: Outliers
B34: Precipitação | C34: =MIN(dados!$B$2:$B$32) -> 42 | D34: =_xlfn.QUARTILE.EXC(dados!$B$2:$B$32,1) -> 58 | E34: =_xlfn.QUARTILE.EXC(dados!$B$2:$B$32,2) -> 80 | F34: =_xlfn.QUARTILE.EXC(dados!$B$2:$B$32,3) -> 92 | G34: =MAX(dados!$B$2:$B$32) -> 120 | H34: =D34-1.5*(F34-D34) -> 7 | I34: =F34+1.5*(F34-D34) -> 143 | J34: =COUNTIF(dados!$B$2:$B$32,"<"&H34) + COUNTIF(dados!$B$2:$B$32,">"&I34) -> 0 | L34: =IFERROR(__xludf.DUMMYFUNCTION("MIN(FILTER(dados!$B$2:$B$32,dados!$B$2:$B$32 >= D34 - 1.5*(F34-D34),dados!$B$2:$B$32 <= F34 + 1.5*(F34-D34)))"),42.0) -> 42
B35: Temperatura | C35: =MIN(dados!$C$2:$C$32) -> 3 | D35: =_xlfn.QUARTILE.EXC(dados!$C$2:$C$32,1) -> 8 | E35: =_xlfn.QUARTILE.EXC(dados!$C$2:$C$32,2) -> 15 | F35: =_xlfn.QUARTILE.EXC(dados!$C$2:$C$32,3) -> 26 | G35: =MAX(dados!$C$2:$C$32) -> 31 | H35: =D35-1.5*(F35-D35) -> -19 | I35: =F35+1.5*(F35-D35) -> 53 | J35: =COUNTIF(dados!$C$2:$C$32,"<"&H35) + COUNTIF(dados!$C$2:$C$32,">"&I35) -> 0
B36: Vento | C36: =MIN(dados!$D$2:$D$32) -> 10 | D36: =_xlfn.QUARTILE.EXC(dados!$D$2:$D$32,1) -> 13 | E36: =_xlfn.QUARTILE.EXC(dados!$D$2:$D$32,2) -> 16 | F36: =_xlfn.QUARTILE.EXC(dados!$D$2:$D$32,3) -> 19 | G36: =MAX(dados!$D$2:$D$32) -> 30 | H36: =D36-1.5*(F36-D36) -> 4 | I36: =F36+1.5*(F36-D36) -> 28 | J36: =COUNTIF(dados!$D$2:$D$32,"<"&H36) + COUNTIF(dados!$D$2:$D$32,">"&I36) -> 2
B37: Vendas | C37: =MIN(dados!$E$2:$E$32) -> 1745 | D37: =_xlfn.QUARTILE.EXC(dados!$E$2:$E$32,1) -> 2205 | E37: =_xlfn.QUARTILE.EXC(dados!$E$2:$E$32,2) -> 2771 | F37: =_xlfn.QUARTILE.EXC(dados!$E$2:$E$32,3) -> 3650 | G37: =MAX(dados!$E$2:$E$32) -> 5920 | H37: =D37-1.5*(F37-D37) -> 37.5 | I37: =F37+1.5*(F37-D37) -> 5817.5 | J37: =COUNTIF(dados!$E$2:$E$32,"<"&H37) + COUNTIF(dados!$E$2:$E$32,">"&I37) -> 1
B50: Fig. 27 – Boxplots das variáveis climáticas e de vendas. Os diagramas de caixa representam a distribuição das variáveis Precipitação, Temperatura, Vento e Vendas, destacando os quartis e a variabilidade dos dados. A precipitação tem mediana posicionada levemente acima do centro da caixa, indicando tendência a valores mais elevados, IQR sugere variabilidade moderada, o bigode superior é mais longo, indicando assimetria positiva, com meses mais chuvosos estendendo a cauda direita. A temperatura tem mediana deslocada do centro da caixa, refletindo assimetria associada à sazonalidade anual com IQR amplo, coerente com variações entre meses mais frios e mais quentes. Bigodes mostram extensão tanto para valores baixos quanto altos, reforçando o efeito sazonal. Vento possui mediana próxima ao centro da caixa, indicando distribuição relativamente equilibrada com IQR pequeno em relação à escala, evidenciando baixa variabilidade. Bigodes superior é mais longo, sugerindo assimetria positiva. Embora não destacados no boxplot, a análise numérica indica outliers com poucos valores acima da cerca superior. Vendas possui mediana situada no intervalo entre aproximadamente 2000 e 3000 unidades. IQR concentrado entre cerca de 2000 e 4000, indicando que a maior parte das vendas ocorre nessa faixa, com picos ocasionais associados a meses de demanda excepcional.. O bigode superior é bastante alongado, indicando assimetria positiva acentuada.
B52: Saiba mais
B53: Outlier
B55: Citação
B56: Estas aulas são baseadas no projeto de e-learning SOGA-Py que foi desenvolvido no Departamento de Ciências da Terra por Annette Rudolph, Joachim Krois e Kai Hartmann. O contato pode ser realizado por e-mail, pelo endereço soga[at]zedat.fu-berlin.de.
B58: Você pode utilizar este projeto livremente sob a Licença Creative Commons Atribuição-CompartilhaIgual 4.0 Internacional.
B59: Por favor, cite da seguinte forma: Rudolph, A., Krois, J., Hartmann, K. (2023): Estatística e Análise de Geodados usando Python (SOGA-Py). Departamento de Ciências da Terra, Universidade Livre de Berlim.

Sheet Página15
A1: i | B1: Altura | C1: Altura Ordenada
A2: 1 | B2: 178 | C2: {=SORT(B2:B9)} -> 155
A3: =A2+1 -> 2 | B3: 169 | C3: 162
A4: =A3+1 -> 3 | B4: 162 | C4: 169
A5: =A4+1 -> 4 | B5: 169 | C5: 169
A6: =A5+1 -> 5 | B6: 175 | C6: 175
A7: =A6+1 -> 6 | B7: 183 | C7: 176
A8: =A7+1 -> 7 | B8: 155 | C8: 178
A9: =A8+1 -> 8 | B9: 176 | C9: 183
A10: Média | B10: =AVERAGE(B2:B9) -> 170.875 | C10: =B10-B11 -> 161.78124 | D10: =B10+B11 -> 179.96876 | E10: =6/8 -> 0.75
A11: DesvPad | B11: =STDEV(B2:B9) -> 9.0937577 | C11: cm
A12: Amplitude | B12: =MAX(B2:B9)-MIN(B2:B9) -> 28 | C12: cm
A13: Variancia | B13: =VARA(B2:B9) -> 82.696429 | C13: cm2
A14: Mediana | B14: =MEDIAN(B2:B9) -> 172 | C14: cm
A15: Moda | B15: =MODE(B2:B9) -> 169 | C15: cm
A16: Quartil 1 | B16: =1*(8+1)/4 -> 2.25 | C16: 151.5 | F16: x | G16: 2 | H16: 2.25 | I16: 3
A17: Quartil 2 | B17: =2*(8+1)/4 -> 4.5 | C17: 172 | F17: y | G17: 169 | H17: =G17+(H16-G16)*((I17-G17)/(I16-G16)) -> 167.25 | I17: 162
A18: Percentil 50 | B18: =50*(8+1)/100 -> 4.5
A19: Quartil 1 | B19: =_xlfn.QUARTILE.INC(B2:B9, 1) -> 167.25
A20: Quartil 3 | B20: =_xlfn.QUARTILE.INC(B2:B9, 3) -> 176.5
A21: IQR | B21: =B20-B19 -> 9.25
A24: Linf | B24: =B19-1.5*B21 -> 153.375
A25: Lsup | B25: =B20+1.5*B21 -> 190.375
